Workbook

Sheet Project Summary 
B5: PROJECT SUMMARY SHEET | C5: PROJECT SUMMARY SHEET
A6: Bill No. | B6: Description | C6: Total Costs Excluding VAT (AED)
A7: 1 | B7: GENERAL ITEMS | C7: ='GENERAL ITEMS'!F29 -> 6055000
A8: 2 | B8: AL DHAHER | C8: ='ALDhaher-Summary '!C13 -> 12197351
A9: 3 | B9: NAHEL | C9: ='Nahel-Summary '!C13 -> 14475731
A10: 4 | B10: AL SAAD | C10: ='AL SAAD-Summary '!C13 -> 15821230
A11: 5 | B11: SWEIHAN | C11: ='SWEIHAN-Summary '!C13 -> 12532257
A12: 6 | B12: DAYWORKS | C12: ='DAYWORKS-Bill 06'!F92 -> 166171.5
B14: Total Costs Excluding VAT ( AED) | C14: =SUM(C7:C12) -> 61247740
B15: Total Value Added Tax (VAT/5%) (AED) | C15: =C14*0.05 -> 3062387
B16: Total Costs Including VAT (AED) | C16: =SUM(C14:C15) -> 64310127
B19: Total Costs in Words Excluding VAT (AED): | C19: Dirhams Sixty-one million, two hundred forty-seven thousand, seven hundred forty.
B20: VAT Amount in Words (AED): | C20: Dirhams Three million, sixty-two thousand, three hundred eighty-seven
B21: Total Costs in Words Including VAT (AED): | C21: Dirhams Sixty-four million, three hundred ten thousand, one hundred twenty-seven and one Fils

Sheet GENERAL ITEMS
B5: Bill No.1, GENERAL ITEMS
A6: Sl.No | B6: Description | C6: UNIT | D6: Quantity (Q) | E6: Unit Rate AED (A) | F6: Total Line Costs Ecxluding VAT B= AED (Q X A)
A7: 1.01 | B7: Procedures
B8: Allow for all costs involved in the preparation and submission of all procedures, co-ordination, method statements etc., required for the implementation of the works such as construction and shutdown requirements, testing and commissioning etc. all according to specifications | C8: Lump sum | D8: 1 | E8: 50000 | F8: =$D8*E8 -> 50000
A9: 1.02 | B9: Planning and Progress Reporting
B10: Allow for all costs involved in the preparation and submission of daily, weekly and monthly planning and progress reporting including reports, photographs etc. all according to specifications. | C10: Lump sum | D10: 1 | E10: 15000 | F10: =$D10*E10 -> 15000
A11: 1.03 | B11: Design, Shop Drawings & Documents
A12: 1.03.1 | B12: Allow for all costs involved in the preparation and submission of all required drawings (compatible with TAQA 's Version of Auto CAD) including all details, shop drawings, vendor drawings, calculations, sketches, graphs and other documentation associated with the work, all according to specifications and according to TAQA GIS specifications. | C12: Lump sum | D12: 1 | E12: 350000 | F12: =$D12*E12 -> 350000
A13: 1.04 | B13: AS-BUILT DOCUMENTATION
B14: Allow for all costs involved in the preparation and submission of As-Built Drawings (compatible with TAQA's Version of Auto CAD) showing accurately to scale full details of installation, sizes and dimensions of pipes, connections, etc., as constructed, all according to specifications and according to TAQA GIS specifications and to be submitted as follows :
A15: 1.04.1 | B15: Three (3) sets of all As-Built drawings compatible with TAQA GIS specifications and projection for new drawings and scanned for existing modified drawings submitted in computer DVD or compacted discs (CD) | C15: Lump sum | D15: 1 | E15: 25000 | F15: =$D15*E15 -> 25000
A16: 1.04.2 | B16: Three (3) sets including soft copies of all As Built drawings to be submitted to the TPD as per the TPD requirements and as per the CDMS license agreement including obtaining the final approval of the TPD for the As Built Drawings | C16: Lump sum | D16: 1 | E16: 25000 | F16: =$D16*E16 -> 25000
A17: 1.04.3 | B17: Three (3) sets of As-Built Record Manuals containing all documents of equipment, materials etc. used for the project with records of their test certificates, calibration, and setting values all properly indexed and bounded in size files with hard covers. | C17: Lump sum | D17: 1 | E17: 25000 | F17: =$D17*E17 -> 25000
A18: 1.05 | B18: OPERATION AND MAINTENANCE MANUALS
A19: 1.05.1 | B19: Allow for all costs involved in the preparation and submission of one (1) set of operation and maintenance manuals (hard +soft copy) containing clear and precise instructions of operation and maintenance procedures with reference to the appropriate drawings and inclusive of the required related As-Built drawings. | C19: Lump sum | D19: 1 | E19: 25000 | F19: =$D19*E19 -> 25000
A20: 1.06 | B20: TEMPORARY FACILITIES FOR TQD Engineer (SITE OFFICE)
A21: 1.06.1 | B21: Allow for all costs involved in provision of the required temporary facilities (site office) and services for the sole use of TAQA / Engineers all in accordance with the Specification. | C21: Lump sum | D21: 1 | E21: 3200000 | F21: =$D21*E21 -> 3200000
A22: 1.06.2 | B22: Maintenance and running cost for above site office for TAQA Engineer during construction period complete as specified. | C22: Lump sum | D22: 1 | E22: 180000 | F22: =$D22*E22 -> 180000
A23: 1.07 | B23: Temporary Facilities for Construction
A24: 1.07.1 | B24: Allow for all costs involved in setting up, maintenance, running costs etc. for all required temporary facilities for the construction including site preparation, workshops, fabrication yards, stores, sheds, site office, accommodation, first aid facilities, access roads etc. all according to the specification. | C24: Lump sum | D24: 1 | E24: 2000000 | F24: =$D24*E24 -> 2000000
A25: 1.08 | B25: Mobilization
A26: 1.08.1 | B26: Allow for all costs involved in mobilization of all labor, supervision personnel, construction material, equipment & plant, transport, consumables etc. which are required to set up the site including site office, fire and safety equipment all according to specifications. | C26: Lump sum | D26: 1 | E26: 120000 | F26: =$D26*E26 -> 120000
A27: 1.09 | B27: Demobilization
A28: 1.09.1 | B28: Allow for all costs for demobilization of personnel and removal from site of all constructional plant, surplus material, site offices, rubbish, temporary work and any other kind of works not being part of the permanent works and leave the whole of the site and work, clean and in a workmanlike condition to the satisfaction of the TAQA Engineer. | C28: Lump sum | D28: 1 | E28: 40000 | F28: =$D28*E28 -> 40000
B29: Total Costs for Bill No.1 excluding VAT (AED) | F29: =SUM(F8:F28) -> 6055000

Sheet ALDhaher-Summary 
B5: SUMMARY SHEET- AL DHAHER
A6: Bill No. | B6: Description | C6: Total Costs Excluding VAT (AED)
A7: 1 | B7: SUPPLY OF PIPEWORKS | C7: ='AL Dhaher Bill 01'!F47 -> 673272.09
A8: 2 | B8: CIVIL WORKS | C8: ='AL Dhaher-Bill 02'!F121 -> 3543338.8 | E8: .
A9: 3 | B9: ELECTRICAL WORKS | C9: ='AL Dhaher-Bill 03'!F82 -> 2504427.1
A10: 4 | B10: CONSTRUCTION OF PIPELINES | C10: ='AL Dhaher-Bill 04'!F48 -> 380969.59
A11: 5 | B11: INSTRUMENTATION AND CONTROL/ SCADA | C11: ='AL Dhaher-Bill 05'!F41 -> 5095343.2
B13: Total Costs Excluding VAT ( AED) | C13: =SUM(C7:C11) -> 12197351
B14: Total Value Added Tax (VAT/5%) (AED) | C14: =C13*0.05 -> 609867.54
B15: Total Costs Including VAT (AED) | C15: =SUM(C13:C14) -> 12807218
B18: Total Costs in Words Excluding VAT (AED): | C18: Dirhams Twelve million, one hundred ninety-seven thousand, three hundred fifty and seventy-six Fils
B19: VAT Amount in Words (AED): | C19: Dirhams Six hundred nine thousand, eight hundred sixty-seven and fifty-four Fils
B20: Total Costs in Words Including VAT (AED): | C20: Dirhams Twelve million, eight hundred seven thousand, two hundred eighteen and thirty Fils

Sheet AL Dhaher Bill 01
B5: Bill No.1, SUPPLY OF PIPEWORKS
A6: Sl.No | B6: Description | C6: UNIT | D6: Quantity (Q) | E6: Unit Rate AED (A) | F6: Total Line Costs Ecxluding VAT B= AED (Q X A)
B7: Storm Water Works
A8: 1.001 | B8: Supply the following ISO standard uPVC including warning tape and all other accessories as per TAQA standard specifications | C8: Lump Sum | D8: 1 | E8: 4147.3461 | F8: =$D8*E8 -> 4147.3461
B9: Sewerage Works
A10: 1.002 | B10: Supply the following ISO standard uPVC including warning tape and all other accessories as per TAQA standard specifications | C10: Lump Sum | D10: 1 | E10: 2862.4256 | F10: =$D10*E10 -> 2862.4256
B11: Gully Trap
A12: 1.003 | B12: Supply the following ISO standard Gully trap including all other accessories as per TAQA standard specifications | C12: Lump Sum | D12: 1 | E12: 225.86715 | F12: =$D12*E12 -> 225.86715
B13: Potable Water Works
B14: Ductile Iron (DI) Pipe
B15: Supply and Install DI pipe as specified complete with installation of detectable warning tapes and other accessories all in accordance with TAQA standard specification, data sheet and drawings.
A16: 1.004 | B16: DI - Standard Socket Spigot pipes | C16: Lump Sum | D16: 1 | E16: 65745.943 | F16: =$D16*E16 -> 65745.943
B17: HDPE Pipe
A18: 1.005 | B18: Supply ISO Standard HDPE pipes, fittings, all in accordance with TAQA standard specification, data sheet and drawings. | C18: Lump Sum | D18: 1 | E18: 52597.628 | F18: =$D18*E18 -> 52597.628
B19: Gate Valves
A20: 1.006 | B20: Supply of PN 16 Manual Gate Valves above ground in accordance with specification, drawings and data sheet. | C20: Lump Sum | D20: 1 | E20: 3811.1852 | F20: =$D20*E20 -> 3811.1852
B21: Air Valves
A22: 1.007 | B22: Supply of Air Valves in accordance with specification, drawings and data sheet. | C22: Lump Sum | D22: 1 | E22: 3241.9362 | F22: =$D22*E22 -> 3241.9362
B23: Bulk Connection Chamber Valves & Fittings
A24: 1.008 | B24: Supply of Manual Check Valves & Fittings in accordance with specification, drawings and data sheet. | C24: Lump Sum | D24: 1 | E24: 10605.084 | F24: =$D24*E24 -> 10605.084
A25: 1.009 | B25: Supply of Manual Butterfly Valves & Fittings in accordance with specification, drawings and data sheet. | C25: Lump Sum | D25: 1 | E25: 10297.676 | F25: =$D25*E25 -> 10297.676
A26: 1.01 | B26: Supply of Settlement Type Electromagnetic Flow Meter & Fittings on 355mm dia line in accordance with specification, drawings and data sheet. | C26: Lump Sum | D26: 1 | E26: 56222.749 | F26: =$D26*E26 -> 56222.749
A27: 1.011 | B27: Supply of Control Valve & Fittings in accordance with specification, drawings and data sheet. | C27: Lump Sum | D27: 1 | E27: 36220.094 | F27: =$D27*E27 -> 36220.094
B28: Flange Connection Chamber Fittings
A29: 1.012 | B29: Supply of Flange Connection Chamber Fittings in accordance with specification, drawings and data sheet. | C29: Lump Sum | D29: 1 | E29: 808.10245 | F29: =$D29*E29 -> 808.10245
B30: Wash Out Valves
A31: 1.013 | B31: Supply of Wash Out Valves in accordance with specification, drawings and data sheet. | C31: Lump Sum | D31: 1 | E31: 9222.9458 | F31: =$D31*E31 -> 9222.9458
B32: Bip Tap
A33: 1.014 | B33: Supply of BIP TAP including all fittings and accessories | C33: Lump Sum | D33: 1 | E33: 451.73429 | F33: =$D33*E33 -> 451.73429
B34: Flow Meter Validation Unit
A35: 1.015 | B35: Supply flow meter validation unit with validation software all as per specifications. The unit shall be supplied with power supply with rechargeable batteries and integral charger unit. | C35: Lump Sum | D35: 1 | E35: 32123.327 | F35: =$D35*E35 -> 32123.327
B36: Flow Control Valve
A37: 1.015a | B37: Supply a flow control valve for the above-ground (vertical pipeline) validation unit, complete with validation software, in full compliance with the project specifications. The unit shall include a power supply with rechargeable batteries and an integral charging unit, ensuring continuous and reliable operation. All components shall be suitable for the intended application and delivered ready for installation and commissioning. | C37: Lump Sum | D37: 1 | E37: 52063.269 | F37: =$D37*E37 -> 52063.269
B38: Electromagnetic Flow Meter
A39: 1.016 | B39: Supply of 4" flow meter. all in accordance with specification, data sheet and drawings. | C39: Lump Sum | D39: 1 | E39: 292655.72 | F39: =$D39*E39 -> 292655.72
B40: PPR Pipes
A41: 1.017 | B41: Supply , PPR 20-25mm pipes Including valves and chambers all as specified and shown on drawings. | C41: Lump Sum | D41: 1 | E41: 2234.1875 | F41: =$D41*E41 -> 2234.1875
B42: Flexible hoses
A43: 1.018 | B43: Supply of PN 16 Flexible hoses of sufficient length, with one end flanged and necessary attachments including fasteners, gaskets etc. for filling bays as specified. | C43: Lump Sum | D43: 1 | E43: 24694.808 | F43: =$D43*E43 -> 24694.808
B44: Booster Set
B45: Domestic water booster set, with two or three vertical multi-stage pumps as shown on drawings, control box, skid mounted, installed, connected and tested complete with stainless steel headers, pump individual isolating ball valves, check valves, isolating butterfly valves PN 20, lug and wafer type lever operated, strainer cast iron body PN 20, flexible connections, concrete inertia pad, house pad, vibration eliminator pad, low level control float switches, pressure switch and controls all supplied from pump manufacturer diaphragm tank (s), food quality synthetic rubber membrane, steel painted body, working pressure 10 bars with isolating valve and pressure gauge, electric connections, wiring and accessories all as specified and shown on the drawings.
A46: 1.19 | B46: Water booster set 1 duty + I standby 1.0 L/S @30m head each pump | C46: Lump Sum | D46: 1 | E46: 13040.063 | F46: =$D46*E46 -> 13040.063
B47: Total Costs for Bill No.1 excluding VAT (AED) | F47: =SUM(F8:F46) -> 673272.09

Sheet AL Dhaher-Bill 02
C1: _
B5: Bill No.2, CIVIL WORKS
A6: Sl.No | B6: Description | C6: UNIT | D6: Quantity (Q) | E6: Unit Rate AED (A) | F6: Total Line Costs Ecxluding VAT B= AED (Q X A)
B7: Trial trench and Trial pits
A8: 2.001 | B8: Trial trench and Trial pits | C8: Lump Sum | D8: 1 | E8: 6512.0008 | F8: =$D8*E8 -> 6512.0008
B9: Trenches for Pipelines
B10: Excavate and Backfill Trenches for Pipelines
B11: Excavate, dewater and backfill trenches for pipelines including shoring, surveying, etc. for a maximum cover to pipelines of 1.2 m as per specification and as shown in drawings for the following sizes of pipelines
B12: PPR Pipelines
A13: 2.002 | B13: PPR Pipelines | C13: Lump Sum | D13: 1 | E13: 16716.137 | F13: =$D13*E13 -> 16716.137
B14: DI Pipelines
A15: 2.003 | B15: DI Pipelines | C15: Lump Sum | D15: 1 | E15: 69669.435 | F15: =$D15*E15 -> 69669.435
B16: HDPE Pipelines
A17: 2.004 | B17: HDPE Pipelines | C17: Lump Sum | D17: 1 | E17: 85982.062 | F17: =$D17*E17 -> 85982.062
B18: uPVC Pipelines for Storm Water Works
A19: 2.005 | B19: uPVC Pipelines | C19: Lump Sum | D19: 1 | E19: 19225.772 | F19: =$D19*E19 -> 19225.772
B20: uPVC Pipelines for Sewerage Works
A21: 2.006 | B21: uPVC Pipelines | C21: Lump Sum | D21: 1 | E21: 16716.137 | F21: =$D21*E21 -> 16716.137
B22: E.O.I for Excavate and Backfill Trenches for Pipelines
B23: E.O.I. for excavation of every additional 500 mm excavation depth exceeding 1.2 m cover, including dewatering, shoring, backfilling and disposal of surplus material all as per specification for the following sizes of pipelines
B24: PPR Pipelines
A25: 2.007 | B25: PPR Pipelines | C25: Lump Sum | D25: 1 | E25: 4920.8528 | F25: =$D25*E25 -> 4920.8528
B26: DI Pipelines
A27: 2.008 | B27: DI Pipelines | C27: Lump Sum | D27: 1 | E27: 4920.8528 | F27: =$D27*E27 -> 4920.8528
B28: HDPE Pipelines
A29: 2.009 | B29: DI Pipelines | C29: Lump Sum | D29: 1 | E29: 4920.8528 | F29: =$D29*E29 -> 4920.8528
B30: uPVC Pipelines for Storm Water Works
A31: 2.01 | B31: uPVC Pipelines | C31: Lump Sum | D31: 1 | E31: 4920.8528 | F31: =$D31*E31 -> 4920.8528
B32: uPVC Pipelines for Sewerage Works
A33: 2.011 | B33: uPVC Pipelines | C33: Lump Sum | D33: 1 | E33: 4920.8528 | F33: =$D33*E33 -> 4920.8528
A34: 2.012 | B34: E.O.I for excavation in rock using rock breaker including disposal of excavated material as per the Municipality requirements - the rock should be classified as per specs by lab test | C34: Lump Sum | D34: 1 | E34: 4920.8528 | F34: =$D34*E34 -> 4920.8528
A35: 2.013 | B35: E.O.I. for supply, place and compact aPPRoved imported bedding / fill material/gatch including disposal of surplus material as per specifications and as ordered and authorized by TAQA Engineer | C35: Lump Sum | D35: 1 | E35: 4920.8528 | F35: =$D35*E35 -> 4920.8528
A36: 2.014 | B36: General excavation for any other purpose including dewatering, backfilling as required or instructed by TAQA Engineer. | C36: Lump Sum | D36: 1 | E36: 22741.229 | F36: =$D36*E36 -> 22741.229
B37: Construction of Manholes and Facilities at Pipelines for Storm Water Works
A38: 2.015 | B38: Manholes including excavation, dewatering, shoring, backfilling, concrete works including the Removable cover slab, benching, blinding and screeds connection joints and protection coating to all internal concrete surfaces, waterproofing , tanking , heavy duty ductile cover & frame, complete in all respect as detailed on drawing and as per specification | C38: Lump Sum | D38: 1 | E38: 77523.116 | F38: =$D38*E38 -> 77523.116
B39: Construction of Manholes and Facilities at Pipelines for Sewer Works
A40: 2.016 | B40: Manholes including excavation, dewatering, shoring, backfilling, concrete works including the Removable cover slab, benching, blinding and screeds connection joints and protection coating to all internal concrete surfaces, waterproofing , tanking , heavy duty ductile cover & frame, complete in all respect as detailed on drawing and as per specification | C40: Lump Sum | D40: 1 | E40: 91075.144 | F40: =$D40*E40 -> 91075.144
A41: 2.017 | B41: Construction Storm water channels excavation, dewatering, shoring, backfilling, concrete works including the gratings complete in all respect as detailed on drawing and as per specification | C41: Lump Sum | D41: 1 | E41: 148452.34 | F41: =$D41*E41 -> 148452.34
A42: 2.018 | B42: Construction of Concrete support (thrust blocks) for fittngs including reinforcement, formwork, backfilling etc. as per authority requirements, specifications and drawings | C42: Lump Sum | D42: 1 | E42: 29690.467 | F42: =$D42*E42 -> 29690.467
B43: Backdrops
A44: 2.019 | B44: Construction of Backdrop complete with concrete surround as per SWS standard drawing | C44: Lump Sum | D44: 1 | E44: 16730.9 | F44: =$D44*E44 -> 16730.9
B45: Construction of Chambers, and Facilities at Pipelines
B46: Construction of Concrete Chambers
B47: Construct reinforced concrete chambers, as per TAQA's standard specification with precast cover slab for chambers on pipelines including the supply of all materials complete with protection board and water proofing of outside walls from top to bottom water stop at construction joints, installation of hot dipped galvanized lifting hooks in cover slab, supports for valve spindle extension casting in of anchor flange sealing flange (water stop),access cover frame, surface box, chamber indication plate owner information plate ventilation pipes bolting of aluminum ladder excavation dewatering, backfilling, etc., all as per specification and as shown on tender drawings (for lifting hooks, ladder, vent pipes, chamber protection & water stop) all as directed and authorized by AADC Engineer (not include supply of pipework inside chambers)
A48: 2.02 | B48: Gate Valve Chamber (s) as per Drawing | C48: Lump Sum | D48: 1 | E48: 21651.753 | F48: =$D48*E48 -> 21651.753
A49: 2.021 | B49: Air Valve Chamber (s) as per Drawing | C49: Lump Sum | D49: 1 | E49: 21651.753 | F49: =$D49*E49 -> 21651.753
A50: 2.022 | B50: Wash Out Valve Chamber (s) as per Drawing | C50: Lump Sum | D50: 1 | E50: 21651.753 | F50: =$D50*E50 -> 21651.753
A51: 2.023 | B51: Flange Connection Chamber (s) as per Drawing | C51: Lump Sum | D51: 1 | E51: 21651.753 | F51: =$D51*E51 -> 21651.753
A52: 2.024 | B52: Bulk Connection Chamber (s) as per Drawings | C52: Lump Sum | D52: 1 | E52: 30017.202 | F52: =$D52*E52 -> 30017.202
A53: 2.025 | B53: Manual Check Valve Chamber (s) as per Drawings | C53: Lump Sum | D53: 1 | E53: 21651.753 | F53: =$D53*E53 -> 21651.753
B54: GRP Tank
A55: 2.026 | B55: Supply, GRP tank glass reinforced plastic construction, GRP panel not less than 8mm, insulation 25mm, all as specified and shown on drawings. | C55: Lump Sum | D55: 1 | E55: 6023.1239 | F55: =$D55*E55 -> 6023.1239
A56: 2.027 | B56: Install,test and commissioning GRP tank glass reinforced plastic construction, GRP panel not less than 8mm, insulation 25mm, all as specified and shown on drawings. | C56: Lump Sum | D56: 1 | E56: 4015.4159 | F56: =$D56*E56 -> 4015.4159
B57: Structural Steel Column for Ladder Support
A58: 2.028 | B58: Supply, fabrication, and installation of structural steel column for ladder support, including all required base plates, anchor bolts, connections, welding, surface treatment , and complete erection at site. Works shall be carried out as per approved drawings, specifications, and relevant standards. All associated materials, labor, equipment, and coordination are to be included to complete the item in all respects. | C58: Lump Sum | D58: 1 | E58: 116091.36 | F58: =$D58*E58 -> 116091.36
B59: Steel Ladders
A60: 2.029 | B60: Supply and Install Steel adjustable ladder including supporting frame, shade and hand rail as shown on drawing | C60: Lump Sum | D60: 1 | E60: 62510.733 | F60: =$D60*E60 -> 62510.733
B61: Car Parking Shed
A62: 2.03 | B62: Car Parking Shed including post, foundation and designated signages all as specified and shown on drawings. | C62: Lump Sum | D62: 1 | E62: 33461.799 | F62: =$D62*E62 -> 33461.799
B63: Garbage Containers
A64: 2.031 | B64: Garbage containers and bins with lid all as specified and shown on drawings. | C64: Lump Sum | D64: 1 | E64: 1806.9372 | F64: =$D64*E64 -> 1806.9372
B65: Road Surface Markings
B66: Surface markings
A67: 2.032 | B67: In accordance with Traffic Control Devices Manual on uniform traffic control devices TR-511 Surface markings including all necessary preparation works, etc.; all in accordance with Road Markings Plan drawings and specifications | C67: Lump Sum | D67: 1 | E67: 6451.4349 | F67: =$D67*E67 -> 6451.4349
B68: Traffic Signs
A69: 2.033 | B69: Supply In accordance with Traffic Control Devices Manual Second Edition September 2020 of Abu Dhabi City Municipality Warning and Regulatory Sign and Posts etc.; all in accordance with Traffic Device Plan drawings and Specification | C69: Lump Sum | D69: 1 | E69: 8833.915 | F69: =$D69*E69 -> 8833.915
A70: 2.034 | B70: Install In accordance with Traffic Control Devices Manual Second Edition September 2020 of Abu Dhabi City Municipality Warning and Regulatory Sign and Posts including all necessary civil works, etc.; all in accordance with Traffic Device Plan drawings and Specification | C70: Lump Sum | D70: 1 | E70: 18738.608 | F70: =$D70*E70 -> 18738.608
B71: Concrete Works
A72: 2.035 | B72: Concrete encasement for road crossing pipes for sewerage including all related works | C72: Lump Sum | D72: 1 | E72: 100385.4 | F72: =$D72*E72 -> 100385.4
A73: 2.035 | B73: Reinforced concrete Coloumn including Concrete foundation, Aluminum Cladding, Steel Truss, Tension cables, 40mm mild steel painted hollow section, lighting, telephone etc as shown on drawing | C73: Lump Sum | D73: 1 | E73: 20077.08 | F73: =$D73*E73 -> 20077.08
A74: 2.036 | B74: Reinforced concrete pedestal for steel ladders as shown on drawing | C74: Lump Sum | D74: 1 | E74: 14303.404 | F74: =$D74*E74 -> 14303.404
A75: 2.037 | B75: Reinforced concrete foundation for LED Screen as shown on drawing | C75: Lump Sum | D75: 1 | E75: 30115.619 | F75: =$D75*E75 -> 30115.619
A76: 2.038 | B76: Reinforced concrete foundation for 14m light pole as shown on drawing | C76: Lump Sum | D76: 1 | E76: 176657.14 | F76: =$D76*E76 -> 176657.14
A77: 2.037 | B77: Concrete Paving including underneath layers all as specified and shown on drawings. | C77: Lump Sum | D77: 1 | E77: 181331.16 | F77: =$D77*E77 -> 181331.16
A78: 2.039 | B78: Supply of Concrete interlock concrete pedestrian paving block; Including sand bed. | C78: Lump Sum | D78: 1 | E78: 18403.99 | F78: =$D78*E78 -> 18403.99
A79: 2.04 | B79: Installation of Concrete interlock concrete pedestrian paving block; Including sand bed all as specified and shown on drawings. | C79: Lump Sum | D79: 1 | E79: 18403.99 | F79: =$D79*E79 -> 18403.99
A80: 2.041 | B80: Supply of Concrete interlock concrete vehicular paving block; Including sand bed. | C80: Lump Sum | D80: 1 | E80: 24969.195 | F80: =$D80*E80 -> 24969.195
A81: 2.042 | B81: Installation of Concrete interlock concrete vehicular paving block; Including sand bed all as specified and shown on drawings. | C81: Lump Sum | D81: 1 | E81: 24969.195 | F81: =$D81*E81 -> 24969.195
A82: 2.043 | B82: Supply of Kerbs, Wheel Stoppers all in accordance with drawing and specifications | C82: Lump Sum | D82: 1 | E82: 7602.5208 | F82: =$D82*E82 -> 7602.5208
A83: 2.044 | B83: Installation of Kerbs, Wheel stoppers complete including excavation, concrete foundation and haunching, cement mortar and backfilling (where required) etc. ; all in accordance with drawing and specifications | C83: Lump Sum | D83: 1 | E83: 7602.5208 | F83: =$D83*E83 -> 7602.5208
... A85: 2.046 | B85: Installation of Chlorinated rubber based quick drying paint for kerbs applied in two coats to exposed faces of concrete kerbs and road separator; colour as per specification and as directed by the Engineer. | C85: Lump Sum | D85: 1 | E85: 2871.0224 | F85: =$D85*E85 -> 2871.0224
B86: NDRC
A87: 2.047 | B87: Supply and installation of Non-Destructive Road Crossing for potable water pipelines, including all necessary materials, equipment, and labor. The scope includes trenchless installation of ducts beneath existing roads or pavements without excavation, ensuring minimal disruption to traffic and surface conditions. Works involve laying, jointing, and pressure testing of ducts in compliance with potable water standards, project specifications, and safety regulations. | C87: Lump Sum | D87: 1 | E87: 84855.186 | F87: =$D87*E87 -> 84855.186
B88: Buildings
B89: Construct the buildings including excavation, backfilling, disposal of surplus material, anti-termite treatment, waterproofings, shoring works, plain cement concrete works, screed, reinforced concrete works, masonry works, metal works, internal finishes, external finishes, doors and windows, all necessary complete all as specified, as shown on the drawings and as per Engineer's approval.
A90: 2.048 | B90: Office, Guard Room, Operator Room & drivers toilet | C90: Lump Sum | D90: 1 | E90: 1429819.3 | F90: =$D90*E90 -> 1429819.3
B91: Gates, Fences and Barbed Wires
A92: 2.049 | B92: Supply Automatic Gate Barrier with Arm | C92: Lump Sum | D92: 1 | E92: 60231.239 | F92: =$D92*E92 -> 60231.239
A93: 2.05 | B93: Install Automatic Gate Barrier with Arm all in accordance with drawing and specifications | C93: Lump Sum | D93: 1 | E93: 21750.17 | F93: =$D93*E93 -> 21750.17
B94: Removal, Refurbishment and Demolishing of Miscellaneous Objects
B95: Demolition
A96: 2.051 | B96: Take up and remove by existing concrete base including underneath layers and dispose to approved tip. | C96: Lump Sum | D96: 1 | E96: 18305.573 | F96: =$D96*E96 -> 18305.573
A97: 2.052 | B97: Demolition of existing Kerbs and dispose to approved tip. | C97: Lump Sum | D97: 1 | E97: 21532.668 | F97: =$D97*E97 -> 21532.668
A98: 2.053 | B98: Demolition of Existing 2.1m Boundary wall including foundation and dispose to approved tip. | C98: Lump Sum | D98: 1 | E98: 90572.725 | F98: =$D98*E98 -> 90572.725
A99: 2.054 | B99: Demolition of existing Storm water channels and dispose to approved tip. | C99: Lump Sum | D99: 1 | E99: 16730.9 | F99: =$D99*E99 -> 16730.9
A100: 2.055 | B100: Removal of existing 180mm HDPE pipe including valves, fittings and handover to Client Store | C100: Lump Sum | D100: 1 | E100: 2278.7485 | F100: =$D100*E100 -> 2278.7485
A101: 2.056 | B101: Removal of existing 150mm DI pipe including valves, fittings and handover to Client Store | C101: Lump Sum | D101: 1 | E101: 5814.2829 | F101: =$D101*E101 -> 5814.2829
A102: 2.057 | B102: Removal of existing Interlocking tiles including underneath layers and handover tiles to Client Store | C102: Lump Sum | D102: 1 | E102: 17968.986 | F102: =$D102*E102 -> 17968.986
A103: 2.058 | B103: Demolition of the existing GI metal sheet Buildings for drivers rest area and dispose to approved tip. | C103: Lump Sum | D103: 1 | E103: 6692.3599 | F103: =$D103*E103 -> 6692.3599
A104: 2.059 | B104: Removal of the existing Prefab structures and hand over to Client store | C104: Lump Sum | D104: 1 | E104: 3346.1799 | F104: =$D104*E104 -> 3346.1799
...

Sheet AL Dhaher-Bill 03
B5: Bill No.3, Electrical Works
A6: Sl.No | B6: Description | C6: UNIT | D6: Quantity (Q) | E6: Unit Rate AED (A) | F6: Total Line Costs Ecxluding VAT B= AED (Q X A)
B7: Electrical
B8: LV Cable
A9: 3.001 | B9: Supply of LV Cables as per drawings and specifications | C9: Lump Sum | D9: 1 | E9: 25880.109 | F9: =$D9*E9 -> 25880.109
A10: 3.002 | B10: Installation of LV Cables as per drawings and specifications | C10: Lump Sum | D10: 1 | E10: 15528.065 | F10: =$D10*E10 -> 15528.065
B11: CAT 6 Cables
A12: 3.003 | B12: Supply of CAT 6 Cables as per drawings and specifications | C12: Lump Sum | D12: 1 | E12: 14762.559 | F12: =$D12*E12 -> 14762.559
A13: 3.004 | B13: Installation OF CAT 6 Cables as per drawings and specifications | C13: Lump Sum | D13: 1 | E13: 4758.2679 | F13: =$D13*E13 -> 4758.2679
B14: FOC Cables
A15: 3.005 | B15: Supply of FOC Cables as per drawings and specifications | C15: Lump Sum | D15: 1 | E15: 14762.559 | F15: =$D15*E15 -> 14762.559
A16: 3.006 | B16: Installation OF FOC Cables as per drawings and specifications | C16: Lump Sum | D16: 1 | E16: 3172.1786 | F16: =$D16*E16 -> 3172.1786
B17: uPVC Ducts
A18: 3.007 | B18: Supply of uPVC ducts including , end caps, draw ropes, aluminium duct marker, warning tapes, cable tiles etc;complete; as per drawings, specification and authority requirement | C18: Lump Sum | D18: 1 | E18: 41827.249 | F18: =$D18*E18 -> 41827.249
A19: 3.008 | B19: Installation of uPVC ducts including excavation, shuttering, reinforcement, concrete encasement, back filling, reinstatement, end caps, draw ropes, aluminium duct marker, warning tapes, cable tiles etc;complete; as per drawings, specification and authority requirement | C19: Lump Sum | D19: 1 | E19: 17567.445 | F19: =$D19*E19 -> 17567.445
B20: Road Crossing uPVC Ducts for LV, FOC & CAT Cables
A21: 3.009 | B21: Supply of uPVC ducts complete; as per drawings, specification and authority requirement | C21: Lump Sum | D21: 1 | E21: 20913.625 | F21: =$D21*E21 -> 20913.625
A22: 3.01 | B22: Installation of uPVC ducts including excavation, shuttering, reinforcement, concrete encasement, back filling, reinstatement, end caps, draw ropes, aluminium duct marker, warning tapes, cable tiles etc;complete; as per drawings, specification and authority requirement | C22: Lump Sum | D22: 1 | E22: 7528.9049 | F22: =$D22*E22 -> 7528.9049
B23: Manholes
A24: 3.011 | B24: Manholes including excavation, backfilling, concrete works, blinding and screeds connection joints and protection coating to all internal concrete surfaces, waterproofing, cover & frame, complete in all respect as detailed on drawing and as per specification | C24: Lump Sum | D24: 1 | E24: 101054.63 | F24: =$D24*E24 -> 101054.63
B25: Main Distribution Board (MDB)
A26: 3.012 | B26: Supply, Main Distribution Board(MDB) complete including enclosure, bus bars, circuit breakers, and insulators, complete all as specified and as shown on drawings. | C26: Lump Sum | D26: 1 | E26: 541293.81 | F26: =$D26*E26 -> 541293.81
A27: 3.013 | B27: Installed, connected, and tested, complete including enclosure, bus bars, circuit breakers, and insulators,complete all as specified and as shown on drawings. | D27: 1 | E27: 24604.264 | F27: =$D27*E27 -> 24604.264
B28: Distribution Board(DB)
A29: 3.014 | B29: Supply, Distribution board complete including enclosure, bus bars, circuit breakers, and insulators, etc... complete all as specified and as shown on drawings. | C29: Lump Sum | D29: 1 | E29: 49208.528 | F29: =$D29*E29 -> 49208.528
A30: 3.015 | B30: Install, Distribution board connected, and tested, complete including enclosure, bus bars, circuit breakers, and insulators, etc... complete all as specified and as shown on drawings. | C30: Lump Sum | D30: 1 | E30: 12302.132 | F30: =$D30*E30 -> 12302.132
B31: Single Pole and Neutral (SPN) Isolator 20A
A32: 3.016 | B32: Supply, Single Pole and Neutral (SPN) Isolator 20A complete all as specified and as shown on drawings. | C32: Lump Sum | D32: 1 | E32: 1505.781 | F32: =$D32*E32 -> 1505.781
A33: 3.017 | B33: Install, connected, and tested, Single Pole and Neutral (SPN) Isolator 20A complete all as specified and as shown on drawings. | C33: Lump Sum | D33: 1 | E33: 903.46858 | F33: =$D33*E33 -> 903.46858
B34: Capacitor Bank 12.5 KVAR
A35: 3.018 | B35: Supply, Capacitor Bank 12.5 KVAR complete all as specified and as shown on drawings. | C35: Lump Sum | D35: 1 | E35: 49208.528 | F35: =$D35*E35 -> 49208.528
A36: 3.019 | B36: Install, connected, and tested, Capacitor Bank 12.5 KVAR complete all as specified and as shown on drawings. | C36: Lump Sum | D36: 1 | E36: 9841.7057 | F36: =$D36*E36 -> 9841.7057
B37: Electrical Meter IP55 Metal Case Meter Enclosure Recessed on wall
A38: 3.02 | B38: Supply, Electrical Meter 83A IP55 Metal Case Meter Enclosure Recessed on wall complete all as specified and as shown on drawings. | C38: Lump Sum | D38: 1 | E38: 9841.7057 | F38: =$D38*E38 -> 9841.7057
A39: 3.021 | B39: Install, connected, and tested, Electrical Meter 83A IP55 Metal Case Meter Enclosure Recessed on wall complete all as specified and as shown on drawings. | C39: Lump Sum | D39: 1 | E39: 2460.4264 | F39: =$D39*E39 -> 2460.4264
B40: LED SCREEN
A41: 3.022 | B41: Supply, LED SCREEN complete all as specified and as shown on drawings. | C41: Lump Sum | D41: 1 | E41: 9841.7057 | F41: =$D41*E41 -> 9841.7057
A42: 3.023 | B42: Install, connected, and tested, LED SCREEN complete all as specified and as shown on drawings. | C42: Lump Sum | D42: 1 | E42: 1279.9138 | F42: =$D42*E42 -> 1279.9138
B43: Telecommunication System
A44: 3.024 | B44: Supply UPVC ducts complete; as per drawings, specification and authority requirement | C44: Lump Sum | D44: 1 | E44: 3178.8709 | F44: =$D44*E44 -> 3178.8709
A45: 3.025 | B45: Installation of upvc ducts including excavation, back filling, reinstatement, end caps, draw ropes, aluminium duct marker, warning tapes etc;complete; as per drawings, specification and authority requirement | C45: Lump Sum | D45: 1 | E45: 1907.3226 | F45: =$D45*E45 -> 1907.3226
B46: Manholes / Joint Boxes
A47: 3.026 | B47: Construct Reinforced concrete Manholes complete including excavation, filling, Manhole concrete, formwork, water proofing, cover & frame etc. in accordance with drawings, specifications and authority requirements. | C47: Lump Sum | D47: 1 | E47: 29011.38 | F47: =$D47*E47 -> 29011.38
B48: Telecom Box
A49: 3.027 | B49: Supply, Telecom Box complete all as specified and as shown on drawings. | C49: Lump Sum | D49: 1 | E49: 75289.049 | F49: =$D49*E49 -> 75289.049
A50: 3.028 | B50: Install, connected, and tested, Telecom Box including Foundation complete all as specified and as shown on drawings. | C50: Lump Sum | D50: 1 | E50: 45173.429 | F50: =$D50*E50 -> 45173.429
B51: Main Distribution Frame (MDF)
A52: 3.029 | B52: Supply, Main Distribution Frame (MDF) complete all as specified and as shown on drawings. | C52: Lump Sum | D52: 1 | E52: 37644.524 | F52: =$D52*E52 -> 37644.524
A53: 3.03 | B53: Install, connected, and tested, Main Distribution Frame (MDF) including Foundation complete all as specified and as shown on drawings. | C53: Lump Sum | D53: 1 | E53: 22586.715 | F53: =$D53*E53 -> 22586.715
B54: ANPR Camera ( Part of Tanker Management System) ( Mounted Height 3M )
A55: 3.031 | B55: Supply, ANPR Camera ( Part of Tanker Management System) ( Mounted Height 3M ) complete all as specified and as shown on drawings. | C55: Lump Sum | D55: 1 | E55: 15039.406 | F55: =$D55*E55 -> 15039.406
A56: 3.032 | B56: Install, ANPR Camera ( Part of Tanker Management System) ( Mounted Height 3M ) complete all as specified and as shown on drawings. | C56: Lump Sum | D56: 1 | E56: 9023.6434 | F56: =$D56*E56 -> 9023.6434
B57: ANPR Camera Pole 3M Height
A58: 3.033 | B58: Supply, Camera Pole 3M Height complete all as specified and as shown on drawings. | C58: Lump Sum | D58: 1 | E58: 2927.9074 | F58: =$D58*E58 -> 2927.9074
A59: 3.034 | B59: Install, Camera Pole 3M Height including Foundation complete all as specified and as shown on drawings. | C59: Lump Sum | D59: 1 | E59: 1756.7445 | F59: =$D59*E59 -> 1756.7445
B60: Area Lighting
A61: 3.035 | B61: Supply, Flood Light complete all as specified and as shown on drawings. | C61: Lump Sum | D61: 1 | E61: 35553.162 | F61: =$D61*E61 -> 35553.162
A62: 3.036 | B62: Install, connect, test Flood Light including complete all as specified and as shown on drawings. | C62: Lump Sum | D62: 1 | E62: 21331.897 | F62: =$D62*E62 -> 21331.897
A63: 3.037 | B63: Supply, Landscape Lighting Pull Box complete all as specified and as shown on drawings. | C63: Lump Sum | D63: 1 | E63: 39819.541 | F63: =$D63*E63 -> 39819.541
A64: 3.038 | B64: Install, connect, and tested, Landscape Lighting Pull Box complete all as specified and as shown on drawings. | C64: Lump Sum | D64: 1 | E64: 23891.725 | F64: =$D64*E64 -> 23891.725
A65: 3.039 | B65: Supply, Lighting Pole of height 14M including luminaries complete all as specified and as shown on drawings. | C65: Lump Sum | D65: 1 | E65: 120462.48 | F65: =$D65*E65 -> 120462.48
A66: 3.04 | B66: Install, connect and test Lighting Pole Height 14M including luminaries complete all as specified and as shown on drawings. | C66: Lump Sum | D66: 1 | E66: 72277.487 | F66: =$D66*E66 -> 72277.487
B67: Road Crossing for Area lighting Cables
A68: 3.041 | B68: Supply UPVC ducts complete; as per drawings, specification and authority requirement | C68: Lump Sum | D68: 1 | E68: 234826.54 | F68: =$D68*E68 -> 234826.54
A69: 3.042 | B69: Installation of uPVC ducts including excavation, shuttering, reinforcement, concrete encasement, back filling, reinstatement, end caps, draw ropes, aluminium duct marker, warning tapes, cable tiles etc;complete; as per drawings, specification and authority requirement | C69: Lump Sum | D69: 1 | E69: 140895.93 | F69: =$D69*E69 -> 140895.93
B70: Distribution Board (Area Lighting)
A71: 3.043 | B71: Supply,DB complete all as specified and as shown on drawings. | C71: Lump Sum | D71: 1 | E71: 9841.7057 | F71: =$D71*E71 -> 9841.7057
A72: 3.044 | B72: Installed, connected, and tested, DB complete including enclosure, bus bars, circuit breakers, and insulators, etc... complete all as specified and as shown on drawings. | C72: Lump Sum | D72: 1 | E72: 4920.8528 | F72: =$D72*E72 -> 4920.8528
B73: Earthing
A74: 3.045 | B74: Supply Earthing to Control Cabinet and poles including earth electrodes, earth pits and earthing cable from LCC or light pole to earth pit, complete as shown on drawing and as per specification | C74: Lump Sum | D74: 1 | E74: 41827.249 | F74: =$D74*E74 -> 41827.249
A75: 3.046 | B75: Install Earthing to Control Cabinet and poles including earth electrodes, earth pits and earthing cable from LCC or light pole to earth pit, complete as shown on drawing and as per specification | C75: Lump Sum | D75: 1 | E75: 25096.35 | F75: =$D75*E75 -> 25096.35
B76: Buildings
A77: 3.047 | B77: MEP works for building includes Power, lighting, fire alarm, fire extinguishers, Emrgency Lighting, Earthing, HVAC & Drainage system; complete all as specified, as shown on the drawings and as per Engineer's approval. | C77: Lump Sum | D77: 1 | E77: 344459.7 | F77: =$D77*E77 -> 344459.7
B78: SPARE PARTS FOR ELECTRICAL EQUIPMENT
A79: 3.048 | B79: Spare parts for sub-distribution boards complete as specified. | C79: Lump Sum | D79: 1 | E79: 41827.249 | F79: =$D79*E79 -> 41827.249
B80: Temporary power supply
A81: 3.049 | B81: Provision of temporary power supply including all necessary equipment, cables, connections, and distribution boards as required for the site. Contractor shall coordinate with TAQA for all connection requirements, approvals, and inspections to ensure compliance with utility regulations. | C81: Lump Sum | D81: 1 | E81: 123808.66 | F81: =$D81*E81 -> 123808.66
B82: Total Costs for Bill No.3 excluding VAT (AED) | F82: =SUM(F9:F81) -> 2504427.1

Sheet AL Dhaher-Bill 04
B5: Bill No.4, CONSTRUCTION OF PIPELINES
A6: Sl.No | B6: Description | C6: UNIT | D6: Quantity (Q) | E6: Unit Rate AED (A) | F6: Total Line Costs Ecxluding VAT B= AED (Q X A)
B7: Construction of uPVC Pipeline
B8: Construct Upvc pipeline as specified complete include installation of detectable warning tapes and other accessories as per specification. Rates shall include all costs for commissioning and handing over in full commercial operation. For the following pipelines
B9: Upvc pipe line
A10: 4.001 | B10: Upvc pipe line for Storm Water Works | C10: Lump Sum | D10: 1 | E10: 1169.356 | F10: =$D10*E10 -> 1169.356
A11: 4.002 | B11: Upvc pipe line for Sewer Works | C11: Lump Sum | D11: 1 | E11: 848.12946 | F11: =$D11*E11 -> 848.12946
B12: DI Pipelines
B13: Construct the Ductile Iron (D.I) pipeline as per the approved specifications, including tie-in connection with the existing line using polyethylene sleeves and rubber gaskets, installation of detectable warning tapes, and all necessary accessories. The scope includes supply of all materials, labor, equipment, and consumables required for the complete installation, as well as testing for pressure and leakage, flushing, disinfection, commissioning, and handing over the system in full commercial operation. The quoted rates shall cover all associated costs to deliver a fully functional and operational pipeline in compliance with relevant standards and project requirements.
A14: 4.003 | B14: DI Pipelines | C14: Lump Sum | D14: 1 | E14: 22044.479 | F14: =$D14*E14 -> 22044.479
B15: Construction of PPR Pipeline
B16: Construct PPR pipeline using butt fusion method as specified complete include installation of detectable warning tapes and other accessories as per specification. Rates shall include all costs for testing, flushing, disinfection, commissioning and handing over in full commercial operation.
A17: 4.004 | B17: PPR pipe line | C17: Lump Sum | D17: 1 | E17: 809.21339 | F17: =$D17*E17 -> 809.21339
B18: Construction of HDPE Pipeline
B19: Construct the HDPE pipeline using the butt fusion method as per the approved specifications, complete with tie-in connections, installation of detectable warning tapes, and all necessary accessories. The scope shall include supply of all materials, equipment, and labor required for the complete installation. Rates shall cover all associated costs for testing, flushing, disinfection, commissioning, and handing over the system in full commercial operation, in compliance with project and industry standards.
B20: HDPE pipeline
A21: 4.005 | B21: HDPE pipeline | C21: Lump Sum | D21: 1 | E21: 19122.374 | F21: =$D21*E21 -> 19122.374
B22: Exta over item For pipeline construction items for installation of D.I, PPR, HDPE & uPVC fittings complete (such as restrained couplings, bends, tees, reducers, reducing flanges, Lange spigot pieces, flange socket pieces, quick dismantling joints, flanged adaptors, socket connectors, tied dismantling joints, blank flanges, double flanged extension pieces, adjustable S bends, duck foot elbows, flanged pipe pieces with anchor flange, transition pieces, collars, stepped couplings, and caps, restraining glands, etc.) for the following pipes:
B23: uPVC Fittings
A24: 4.006 | B24: uPVC pipe line for Storm Water Works | C24: Lump Sum | D24: 1 | E24: 1595.5389 | F24: =$D24*E24 -> 1595.5389
A25: 4.007 | B25: uPVC pipe line for Sewerage Works | C25: Lump Sum | D25: 1 | E25: 1060.1568 | F25: =$D25*E25 -> 1060.1568
B26: DI Pipelines
A27: 4.008 | B27: DI Pipelines | C27: Lump Sum | D27: 1 | E27: 13020.02 | F27: =$D27*E27 -> 13020.02
B28: PPR Pipelines
A29: 4.009 | B29: PPR Pipelines | C29: Lump Sum | D29: 1 | E29: 1650.6371 | F29: =$D29*E29 -> 1650.6371
B30: HDPE pipeline
A31: 4.01 | B31: HDPE pipeline | C31: Lump Sum | D31: 1 | E31: 15942.714 | F31: =$D31*E31 -> 15942.714
B32: Exta over item for pipeline construction for installation of flanged valves, gate valves, flowmeters, control valves, etc. including all the accessories as per the specification.
A33: 4.011 | B33: Flow Meter Validation Unit | C33: Lump Sum | D33: 1 | E33: 37477.215 | F33: =$D33*E33 -> 37477.215
A34: 4.012 | B34: Settlement Type Electromagnetic Flow Meter | C34: Lump Sum | D34: 1 | E34: 29943.291 | F34: =$D34*E34 -> 29943.291
A35: 4.013 | B35: Control Valve | C35: Lump Sum | D35: 1 | E35: 24146.729 | F35: =$D35*E35 -> 24146.729
A36: 4.014 | B36: Air Valve | C36: Lump Sum | D36: 1 | E36: 2161.2908 | F36: =$D36*E36 -> 2161.2908
A37: 4.015 | B37: Washout Valve | C37: Lump Sum | D37: 1 | E37: 6148.6305 | F37: =$D37*E37 -> 6148.6305
A38: 4.016 | B38: Manual Butterfly Valve | C38: Lump Sum | D38: 1 | E38: 6865.1172 | F38: =$D38*E38 -> 6865.1172
A39: 4.017 | B39: Manual Check Valve | C39: Lump Sum | D39: 1 | E39: 7070.0557 | F39: =$D39*E39 -> 7070.0557
A40: 4.018 | B40: Electromagnetic Flow Meter | C40: Lump Sum | D40: 1 | E40: 160584.42 | F40: =$D40*E40 -> 160584.42
A41: 4.019 | B41: Gate Valve | C41: Lump Sum | D41: 1 | E41: 2540.7902 | F41: =$D41*E41 -> 2540.7902
B42: Service Connections
B43: Installation of Pipework for Service Connections
B44: Construct of New Tapping : Work includes Hand excavation, dewatring,and installation of new saddle strap & ferrule/pressure tapping tee with extra long outlet with all required fittings and supply of installation of moulding compound warping tap & polythene sleeve for protection of saddle & ferrule,backfilling and shutdown of distribution etc.all as per TAQA Specification.
A45: 4.02 | B45: Tapping in HDPE Main line | C45: Lump Sum | D45: 1 | E45: 8030.8318 | F45: =$D45*E45 -> 8030.8318
B46: Construct reinforced concrete encased 110 mm , 160 mm dia. Socket type uPVC DUCTS (Class 10 - minimum wall thickness 5.3 mm & 7.7 mm respectively) for the areas under car pass, for the proposed polyethylene house connection pipes, including the supply of uPVC pipe used for protection and all other materials complete with uPVC end cap at each duct end, duct end sealing, bituminous painting of concrete, excavation by hand, dewatering, backfilling and provision of 10 mm dia. pulling rope for installation of polyethylene house connection pipes etc. all as per TAQA Specification and Tender Drawings and as directed by TAQA ENGINEER :
A47: 4.021 | B47: Reinforce concrete encasement for uPVC pipes for Storm Water Works | C47: Lump Sum | D47: 1 | E47: 18738.608 | F47: =$D47*E47 -> 18738.608
B48: Total Costs for Bill No.4 excluding VAT (AED) | F48: =SUM(F10:F47) -> 380969.59

Sheet AL Dhaher-Bill 05
B5: Bill No.5, INSTRUMENTATION AND CONTROL/ SCADA
A6: Sl.No | B6: Description | C6: UNIT | D6: Quantity (Q) | E6: Unit Rate AED (A) | F6: Total Line Costs Ecxluding VAT B= AED (Q X A)
B7: TANKER CONTROL SYSTEM/WorkStation
B8: CONTROL SYSTEM
A9: 5.001 | B9: Dual system servers including but not limited to, CPU, HDD, keyboard mouse, DVDD, USB drive, software interface devices. | C9: No | D9: 1 | E9: 124949.7 | F9: =$D9*E9 -> 124949.7
A10: 5.002 | B10: Operator workstation including but not limited to, two computers each 21" LCD monitor, CPU, keyboard, mouse, interface devices, 2 GB RAM min., HDD, USB drive, DVDD etc. including one printer. | C10: No | D10: 1 | E10: 40667.798 | F10: =$D10*E10 -> 40667.798
A11: 5.003 | B11: Electronic cabinets including but not limited to, one dual redundant, PLC, communication and power supply modules, interface/signal/alarm etc. modules alongwith suitable communication equipment. | C11: No | D11: 1 | E11: 531639.39 | F11: =$D11*E11 -> 531639.39
A12: 5.004 | B12: Redundant secured communication network, bus and interfaces and other auxiliaries, as required | C12: Lump Sum | D12: 1 | E12: 147036.17 | F12: =$D12*E12 -> 147036.17
A13: 5.005 | B13: Software packages including but not limited to the original license including all application, engineering and HMI software, configuration software etc., as required. | C13: Lump Sum | D13: 1 | E13: 446271.65 | F13: =$D13*E13 -> 446271.65
A14: 5.006 | B14: Field Process Unit, which consists of flow computer with card reader, push buttons for Start / Stop, Emergency push button, lamps for indication, remote I/O module/ RTU | C14: No | D14: 8 | E14: 181627.3 | F14: =$D14*E14 -> 1453018.4
A15: 5.007 | B15: Start / Stop Panel for Manual Tanker Filling Operation as specified | C15: No | D15: 8 | E15: 3588.778 | F15: =$D15*E15 -> 28710.224
A16: 5.008 | B16: Fiscal Ticket Printers for printing the prepaid cards etc. as required showing tanker information , volume and amount. To be installed in Customer Service Unit of the office building | C16: No | D16: 2 | E16: 29513.307 | F16: =$D16*E16 -> 59026.614
A17: 5.009 | B17: Supply and Install A3 & A4 printer | C17: Lump Sum | D17: 1 | E17: 7968.9275 | F17: =$D17*E17 -> 7968.9275
A18: 5.01 | B18: Supply and Install UPS as required | C18: Lump Sum | D18: 1 | E18: 119528.89 | F18: =$D18*E18 -> 119528.89
B19: LEVEL SWITCHES
A20: 5.011 | B20: Supply of level switches of suitable type for tanker overflow detection complete with cable and other installation accessories to be installed on the filling hose. | C20: No. | D20: 8 | E20: 14221.265 | F20: =$D20*E20 -> 113770.12
A21: 5.012 | B21: ACCESS CONTROL SYSTEM
A22: 5.013 | B22: Proximity Card Reader Unit / including all accessories required for installing at the entrance of the station, complete with power supply unit, modules etc and all other accessories as required for communication to centralised loading system PLC. | C22: No | D22: 4 | E22: 99607.411 | F22: =$D22*E22 -> 398429.64
A23: 5.014 | B23: Motorised boom including warning beacons, audible alram and all other accessries, to be installed at the entrance and exit of the station as required including interfaces with the loading system PLC. | C23: No | D23: 4 | E23: 119528.89 | F23: =$D23*E23 -> 478115.57
A24: 5.015 | B24: Display units for bay identifcation and driver information including all required accessories and interfaces. | C24: No | D24: 10 | E24: 41318.63 | F24: =$D24*E24 -> 413186.3
B25: SPARE PARTS FOR ELECTRICAL EQUIPMENT
A26: 5.016 | B26: Spare parts for sub-distribution boards complete as specified. | C26: Lump Sum | D26: 1 | E26: 147566.54 | F26: =$D26*E26 -> 147566.54
B27: SPARE PARTS FOR I & C SYSTEM & F.O CABLE
B28: SPARE FOR THE FIELD INSTRUMENTS
A29: 5.017 | B29: Electromagnetic flowmeter transmitter. | C29: No | D29: 1 | E29: 64263.386 | F29: =$D29*E29 -> 64263.386
A30: 5.018 | B30: Pressure transmitter (One from each range selected) | C30: No | D30: 1 | E30: 7528.9049 | F30: =$D30*E30 -> 7528.9049
A31: 5.019 | B31: Differential pressure switch, one no. for the highest range selected. | C31: No | D31: 1 | E31: 11910.727 | F31: =$D31*E31 -> 11910.727
A32: 5.02 | B32: Pressure gauge, one no. for each range selected. | C32: No | D32: 1 | E32: 1500.7617 | F32: =$D32*E32 -> 1500.7617
A33: 5.021 | B33: Level Switches | C33: No | D33: 1 | E33: 8345.3728 | F33: =$D33*E33 -> 8345.3728
B34: SPARES FOR CONTROL AND SCADA SYSTEM
A35: 5.022 | B35: The number of spare equipment modules shall be 5% of the installed units, rounded upto the nearest integer i.e. CPU, CP, power supply modules, I/O modules of each type, bus controller, fibre optic interfaace modules, all communication device and modules etc. alongwith 10% spare hardware accessories like relays, batteries, MCB's, etc, and EPROM/EEPROM shall be 2 minimum of each type. | C35: Lump Sum | D35: 1 | E35: 250863.11 | F35: =$D35*E35 -> 250863.11
B36: SPARE FOR F.O. CABLE SYSTEM
A37: 5.023 | B37: Fibre optical splicing kit, 1 set for tap off location. | C37: Lump Sum | D37: 1 | E37: 103296.57 | F37: =$D37*E37 -> 103296.57
A38: 5.024 | B38: 10% minimum F.O. interfacing module/component of each type installed at the F.O. system cabinet/panel including interfacing module, power supply module, patch panel etc. | C38: Lump Sum | D38: 1 | E38: 44269.961 | F38: =$D38*E38 -> 44269.961
A39: 5.025 | B39: Recommended consumables for 2 years trouble free operation | C39: Lump Sum | D39: 1 | E39: 44269.961 | F39: =$D39*E39 -> 44269.961
A40: 5.026 | B40: SCADA System Integration with existing main SCADA and Customer care and Billing System ( CC&B) | C40: Lump Sum | D40: 1 | E40: 49208.528 | F40: =$D40*E40 -> 49208.528
B41: Total Costs for Bill No.5 excluding VAT (AED) | F41: =SUM(F9:F40) -> 5095343.2

Sheet Nahel-Summary 
B5: SUMMARY SHEET - NAHEL
A6: Bill No. | B6: Description | C6: Total Costs Excluding VAT (AED)
A7: 1 | B7: SUPPLY OF PIPEWORKS | C7: ='Nahel-Bill 01'!F43 -> 879340.36
A8: 2 | B8: CIVIL WORKS | C8: ='Nahel-Bill 02'!F110 -> 5703759
A9: 3 | B9: ELECTRICAL WORKS | C9: ='Nahel-Bill 03'!F86 -> 2206138.9
A10: 4 | B10: CONSTRUCTION OF PIPELINES | C10: ='Nahel-Bill 04'!F42 -> 566575.37
A11: 5 | B11: INSTRUMENTATION AND CONTROL/ SCADA | C11: ='Nahel-Bill 05'!F41 -> 5119917.6
B13: Total Costs Excluding VAT ( AED) | C13: =SUM(C7:C11) -> 14475731
B14: Total Value Added Tax (VAT/5%) (AED) | C14: =C13*0.05 -> 723786.56
B15: Total Costs Including VAT (AED) | C15: =SUM(C13:C14) -> 15199518
B18: Total Costs in Words Excluding VAT (AED): | C18: Dirhams Fourteen million, four hundred seventy-five thousand, seven hundred thirty-one and fourteen Fils
B19: VAT Amount in Words (AED): | C19: Dirhams Seven hundred twenty-three thousand, seven hundred eighty-six and fifty-six Fils
B20: Total Costs in Words Including VAT (AED): | C20: Dirhams Fifteen million, one hundred ninety-nine thousand, five hundred seventeen and seventy Fils

Sheet Nahel-Bill 01
B5: Bill No.1, SUPPLY OF PIPEWORKS
A6: Sl.No | B6: Description | C6: UNIT | D6: Quantity (Q) | E6: Unit Rate AED (A) | F6: Total Line Costs Ecxluding VAT B= AED (Q X A)
B7: Storm Water Works
A8: 1.001 | B8: Supply the following ISO standard uPVC including warning tape and all other accessories as per ADEWA standard specifications | C8: Lump Sum | D8: 1 | E8: 1033.1906 | F8: =$D8*E8 -> 1033.1906
B9: Sewerage Works
A10: 1.002 | B10: Supply the following ISO standard uPVC including warning tape and all other accessories as per ADEWA standard specifications | C10: Lump Sum | D10: 1 | E10: 3220.4542 | F10: =$D10*E10 -> 3220.4542
B11: Gully Trap
A12: 1.003 | B12: Supply the following ISO standard Gully trap including all other accessories as per ADEWA standard specifications | C12: Lump Sum | D12: 1 | E12: 225.86715 | F12: =$D12*E12 -> 225.86715
B13: Potable Water Works
B14: Ductile Iron (DI) Pipe
B15: Supply and Install DI pipe as specified complete with installation of detectable warning tapes and other accessories all in accordance with TAQA standard specification, data sheet and drawings.
A16: 1.004 | B16: DI - Standard Socket Spigot pipes | C16: Lump Sum | D16: 1 | E16: 115080.92 | F16: =$D16*E16 -> 115080.92
A17: 1.004a | B17: DI - Restrained | C17: Lump Sum | D17: 1 | E17: 115080.92 | F17: =$D17*E17 -> 115080.92
B18: Gate Valves
A19: =MAX(A12:A17)+0.001 -> 1.005 | B19: Supply of PN 16 Manual Gate Valves above ground in accordance with specification, drawings and data sheet. | C19: Lump Sum | D19: 1 | E19: 7077.1706 | F19: =$D19*E19 -> 7077.1706
B20: Air Valves
A21: =MAX(A14:A19)+0.001 -> 1.006 | B21: Supply of Air Valves in accordance with specification, drawings and data sheet. | C21: Lump Sum | D21: 1 | E21: 4111.4868 | F21: =$D21*E21 -> 4111.4868
B22: Bulk Connection Chamber Valves & Fittings
A23: =MAX(A16:A21)+0.001 -> 1.007 | B23: Supply of Manual Check Valves & Fittings in accordance with specification, drawings and data sheet. | C23: Lump Sum | D23: 1 | E23: 18387.202 | F23: =$D23*E23 -> 18387.202
A24: =MAX(A17:A22)+0.001 -> 1.007 | B24: Supply of Manual Butterfly Valves & Fittings in accordance with specification, drawings and data sheet. | C24: Lump Sum | D24: 1 | E24: 10817.711 | F24: =$D24*E24 -> 10817.711
A25: =MAX(A18:A23)+0.001 -> 1.008 | B25: Supply of Settlement Type Electromagnetic Flow Meter & Fittings on 400mm dia line in accordance with specification, drawings and data sheet. | C25: Lump Sum | D25: 1 | E25: 71090.853 | F25: =$D25*E25 -> 71090.853
A26: =MAX(A19:A24)+0.001 -> 1.008 | B26: Supply of Control Valve & Fittings in accordance with specification, drawings and data sheet. | C26: Lump Sum | D26: 1 | E26: 80331.644 | F26: =$D26*E26 -> 80331.644
B27: Wash Out Valves
A28: =MAX(A21:A26)+0.001 -> 1.009 | B28: Supply of Wash Out Valves in accordance with specification, drawings and data sheet. | C28: Lump Sum | D28: 1 | E28: 9939.3994 | F28: =$D28*E28 -> 9939.3994
B29: BIP TAP
A30: =MAX(A23:A28)+0.001 -> 1.01 | B30: Supply of BIP TAP including all fittings and accessories | C30: Lump Sum | D30: 1 | E30: 451.73429 | F30: =$D30*E30 -> 451.73429
B31: Flow Meter Validation Unit
A32: =MAX(A25:A30)+0.001 -> 1.011 | B32: Supply flow meter validation unit with validation software all as per specifications. The unit shall be supplied with power supply with rechargeable batteries and integral charger unit. | C32: Lump Sum | D32: 1 | E32: 32123.327 | F32: =$D32*E32 -> 32123.327
B33: Flow Control Valve
A34: 1.011a | B34: Supply a flow control valve for the above-ground (vertical pipeline) validation unit, complete with validation software, in full compliance with the project specifications. The unit shall include a power supply with rechargeable batteries and an integral charging unit, ensuring continuous and reliable operation. All components shall be suitable for the intended application and delivered ready for installation and commissioning. | C34: Lump Sum | D34: 1 | E34: 80473.188 | F34: =$D34*E34 -> 80473.188
B35: Electromagnetic Flow Meter
A36: =MAX(A29:A34)+0.001 -> 1.012 | B36: Supply of 6" flow meter. all in accordance with specification, data sheet and drawings. | C36: Lump Sum | D36: 1 | E36: 296240.52 | F36: =$D36*E36 -> 296240.52
B37: PPR Pipes
A38: =MAX(A31:A36)+0.001 -> 1.013 | B38: Supply , PPR 20-25mm pipes Including valves and chambers all as specified and shown on drawings. | C38: Lump Sum | D38: 1 | E38: 2679.1878 | F38: =$D38*E38 -> 2679.1878
A39: =MAX(A32:A37)+0.001 -> 1.013 | B39: Supply of PN 16 Flexible hoses of sufficient length, with one end flanged and necessary attachments including fasteners, gaskets etc. for filling bays as specified. | C39: Lump Sum | D39: 1 | E39: 17935.524 | F39: =$D39*E39 -> 17935.524
B40: Domestic water pump set
B41: Domestic water pump set for building, with single stage pumps and pressure vessel as shown on drawings, control box, skid mounted, installed, connected and tested complete with stainless steel headers, pump individual isolating ball valves, check valves, isolating butterfly valves PN 20, lug and wafer type lever operated, strainer cast iron body PN 20, flexible connections, concrete inertia pad, house pad, vibration eliminator pad, low level control float switches, pressure switch and controls all supplied from pump manufacturer diaphragm tank (s), food quality synthetic rubber membrane, steel painted body, working pressure 2 bars with isolating valve and pressure gauge, electric connections, wiring and accessories all as specified and shown on the drawings.
A42: =MAX(A35:A40)+0.001 -> 1.014 | B42: Water Pump set 1 duty + 1 standby 1.0 L/S @30m head each pump | C42: Lump Sum | D42: 1 | E42: 13040.063 | F42: =$D42*E42 -> 13040.063
B43: Total Costs for Bill No.1 excluding VAT (AED) | F43: =SUM(F8:F42) -> 879340.36

Sheet Nahel-Bill 02
B5: Bill No.2, CIVIL WORKS
A6: Sl.No | B6: Description | C6: UNIT | D6: Quantity (Q) | E6: Unit Rate AED (A) | F6: Total Line Costs Ecxluding VAT B= AED (Q X A)
B7: Trial trench and Trial pits
A8: 2.001 | B8: Trial trench and Trial pits | C8: Lump Sum | D8: 1 | E8: 8678.3177 | F8: =$D8*E8 -> 8678.3177
B9: Trenches for Pipelines
B10: Excavate, dewater and backfill trenches for pipelines including shoring, surveying, etc. for a maximum cover to pipelines of 1.2 m as per specification and as shown in drawings for the following sizes of pipelines
B11: PPR Pipelines
A12: 2.002 | B12: PPR Pipelines | C12: Lump Sum | D12: 1 | E12: 6175.6703 | F12: =$D12*E12 -> 6175.6703
B13: DI Pipelines
A14: 2.003 | B14: DI Pipelines | C14: Lump Sum | D14: 1 | E14: 192641.55 | F14: =$D14*E14 -> 192641.55
B15: uPVC Pipelines for Storm Water Works
A16: 2.004 | B16: uPVC Pipelines | C16: Lump Sum | D16: 1 | E16: 7430.4878 | F16: =$D16*E16 -> 7430.4878
B17: uPVC Pipelines for Sewerage Works
A18: 2.004a | B18: uPVC Pipelines | C18: Lump Sum | D18: 1 | E18: 41561.523 | F18: =$D18*E18 -> 41561.523
B19: E.O.I for Excavate and Backfill Trenches for Pipelines
B20: E.O.I. for excavation of every additional 500 mm excavation depth exceeding 1.2 m cover, including dewatering, shoring, backfilling and disposal of surplus material all as per specification for the following pipelines
B21: PPR Pipelines
A22: 2.005 | B22: PPR Pipelines | C22: Lump Sum | D22: 1 | E22: 4920.8528 | F22: =$D22*E22 -> 4920.8528
B23: DI Pipelines
A24: 2.006 | B24: DI Pipelines | C24: Lump Sum | D24: 1 | E24: 4920.8528 | F24: =$D24*E24 -> 4920.8528
B25: uPVC Pipelines for Storm Water Works
A26: 2.007 | B26: uPVC Pipelines | C26: Lump Sum | D26: 1 | E26: 4920.8528 | F26: =$D26*E26 -> 4920.8528
B27: uPVC Pipelines for Sewerage Works
A28: 2.007a | B28: uPVC Pipelines | C28: Lump Sum | D28: 1 | E28: 4920.8528 | F28: =$D28*E28 -> 4920.8528
A29: 2.008 | B29: E.O.I for excavation in rock using rock breaker including disposal of excavated material as per the Municipality requirements - the rock should be classified as per specs by lab test | C29: Lump Sum | D29: 1 | E29: 4920.8528 | F29: =$D29*E29 -> 4920.8528
A30: 2.009 | B30: E.O.I. for supply, place and compact aPPRoved imported bedding / fill material/gatch including disposal of surplus material as per specifications and as ordered and authorized by TAQA Engineer | C30: Lump Sum | D30: 1 | E30: 4920.8528 | F30: =$D30*E30 -> 4920.8528
A31: 2.01 | B31: General excavation for any other purpose including dewatering, backfilling as required or instructed by TAQA Engineer. | C31: Lump Sum | D31: 1 | E31: 22607.382 | F31: =$D31*E31 -> 22607.382
B32: Construction of Manholes and Facilities at Pipelines for Storm Water Works
A33: 2.011 | B33: Manholes including excavation, dewatering, shoring, backfilling, concrete works including the Removable cover slab, benching, blinding and screeds connection joints and protection coating to all internal concrete surfaces, waterproofing , tanking , heavy duty ductile cover & frame, complete in all respect as detailed on drawing and as per specification | C33: Lump Sum | D33: 1 | E33: 66775.973 | F33: =$D33*E33 -> 66775.973
A34: 2.012 | B34: Construction Storm water channels excavation, dewatering, shoring, backfilling, concrete works including the gratings complete in all respect as detailed on drawing and as per specification | C34: Lump Sum | D34: 1 | E34: 179942.71 | F34: =$D34*E34 -> 179942.71
B35: Backdrops
A36: 2.013 | B36: Construction of Backdrop complete with concrete surround as per SWS standard drawing | C36: Lump Sum | D36: 1 | E36: 21651.753 | F36: =$D36*E36 -> 21651.753
B37: Soakaway
A38: 2.014 | B38: Construction of Soakaway complete with concrete surround as per SWS standard drawing | C38: Lump Sum | D38: 1 | E38: 18374.465 | F38: =$D38*E38 -> 18374.465
B39: Proposed Road Crossing Ducts
A40: 2.014a | B40: Supply and installation of HDPE ducts for road crossing, including reinforced concrete surround and all associated works such as excavation, duct laying, concrete casting, backfilling, compaction, and testing, all as per drawings and specifications | C40: Lump Sum | D40: 1 | E40: 63577.419 | F40: =$D40*E40 -> 63577.419
B41: Construction of Chambers, and Facilities at Pipelines
B42: Construction of Concrete Chambers
B43: Construct reinforced concrete chambers, as per TAQA's standard specification with precast cover slab for chambers on pipelines including the supply of all materials complete with protection board and water proofing of outside walls from top to bottom water stop at construction joints, installation of hot dipped galvanized lifting hooks in cover slab, supports for valve spindle extension casting in of anchor flange sealing flange (water stop),access cover frame, surface box, chamber indication plate owner information plate ventilation pipes bolting of aluminum ladder excavation dewatering, backfilling, etc., all as per specification and as shown on tender drawings (for lifting hooks, ladder, vent pipes, chamber protection & water stop) all as directed and authorized by TAQA Engineer (not include supply of pipework inside chambers)
A44: 2.015 | B44: Gate Valve Chamber (s) as per Drawing | C44: Lump Sum | D44: 1 | E44: 66923.599 | F44: =$D44*E44 -> 66923.599
A45: 2.016 | B45: Air Valve Chamber (s) as per Drawing | C45: Lump Sum | D45: 1 | E45: 21651.753 | F45: =$D45*E45 -> 21651.753
A46: 2.017 | B46: Wash Out Valve Chamber (s) as per Drawing | C46: Lump Sum | D46: 1 | E46: 21651.753 | F46: =$D46*E46 -> 21651.753
A47: 2.018 | B47: Flow Meter Chamber (s) as per Drawings | C47: Lump Sum | D47: 1 | E47: 21651.753 | F47: =$D47*E47 -> 21651.753
A48: 2.019 | B48: Control Valve Chamber (s) as per Drawing | C48: Lump Sum | D48: 1 | E48: 21651.753 | F48: =$D48*E48 -> 21651.753
A49: 2.02 | B49: Bulk Connection Chamber (s) as per Drawings | C49: Lump Sum | D49: 1 | E49: 30017.202 | F49: =$D49*E49 -> 30017.202
A50: 2.021 | B50: Manual Check Valve Chamber (s) as per Drawings | C50: Lump Sum | D50: 1 | E50: 21651.753 | F50: =$D50*E50 -> 21651.753
B51: GRP Tank
A52: 2.022 | B52: Supply, GRP tank glass reinforced plastic construction, GRP panel not less than 8mm, insulation 25mm, all as specified and shown on drawings. | C52: Lump Sum | D52: 1 | E52: 13470.343 | F52: =$D52*E52 -> 13470.343
A53: 2.023 | B53: Install,test and commissioning GRP tank glass reinforced plastic construction, GRP panel not less than 8mm, insulation 25mm, all as specified and shown on drawings. | C53: Lump Sum | D53: 1 | E53: 10050.547 | F53: =$D53*E53 -> 10050.547
B54: Structural Steel Column for Ladder Support
A55: 2.024 | B55: Supply, fabrication, and installation of structural steel column for ladder support, including all required base plates, anchor bolts, connections, welding, surface treatment, and complete erection at site. Works shall be carried out as per approved drawings, specifications, and relevant standards. All associated materials, labor, equipment, and coordination are to be included to complete the item in all respects. | C55: Lump Sum | D55: 1 | E55: 125021.47 | F55: =$D55*E55 -> 125021.47
B56: Steel Ladders
A57: =MAX(A43:A56)+0.001 -> 2.025 | B57: Supply and Install Steel adjustable ladder including supporting frame, shade and hand rail as shown on drawing | C57: Lump Sum | D57: 1 | E57: 83383.045 | F57: =$D57*E57 -> 83383.045
B58: Garbage Containers
A59: =MAX(A46:A57)+0.001 -> 2.026 | B59: Garbage containers and bins with lid all as specified and shown on drawings. | C59: Lump Sum | D59: 1 | E59: 2710.4057 | F59: =$D59*E59 -> 2710.4057
B60: Car Parking Shed
A61: =MAX(A49:A60)+0.001 -> 2.027 | B61: Car Parking Shed including post, foundation and designated signages all as specified and shown on drawings. | C61: Lump Sum | D61: 1 | E61: 33461.799 | F61: =$D61*E61 -> 33461.799
B62: Road Surface Markings
B63: Surface markings
A64: =MAX(A53:A63)+0.001 -> 2.028 | B64: In accordance with Traffic Control Devices Manual on uniform traffic control devices TR-511 Surface markings including all necessary preparation works, etc.; all in accordance with Road Markings Plan drawings and specifications | C64: Lump Sum | D64: 1 | E64: 6451.4349 | F64: =$D64*E64 -> 6451.4349
B65: Traffic Signs
A66: =MAX(A55:A65)+0.001 -> 2.029 | B66: Supply In accordance with Traffic Control Devices Manual Second Edition September 2020 of Abu Dhabi City Municipality Warning and Regulatory Sign and Posts etc.; all in accordance with Traffic Device Plan drawings and Specification | C66: Lump Sum | D66: 1 | E66: 11594.513 | F66: =$D66*E66 -> 11594.513
A67: =MAX(A60:A66)+0.001 -> 2.03 | B67: Install In accordance with Traffic Control Devices Manual Second Edition September 2020 of Abu Dhabi City Municipality Warning and Regulatory Sign and Posts including all necessary civil works, etc.; all in accordance with Traffic Device Plan drawings and Specification | C67: Lump Sum | D67: 1 | E67: 7729.6756 | F67: =$D67*E67 -> 7729.6756
B68: Asphalt Works
A69: =MAX(A62:A68)+0.001 -> 2.031 | B69: Asphalt Paving including underneath layers | C69: Lump Sum | D69: 1 | E69: 1066492 | F69: =$D69*E69 -> 1066492
B70: Concrete Works
A71: =MAX(A62:A70)+0.001 -> 2.032 | B71: Reinforced concrete Coloumn including Concrete foundation, Aluminum Cladding, Steel Truss, Tension cables, 40mm mild steel painted hollow section, lighting, telephone etc as shown on drawing and as per specification. | C71: Lump Sum | D71: 1 | E71: 23423.26 | F71: =$D71*E71 -> 23423.26
A72: =MAX(A62:A71)+0.001 -> 2.033 | B72: Reinforced concrete pedestal for steel ladders as shown on drawing | C72: Lump Sum | D72: 1 | E72: 77497.527 | F72: =$D72*E72 -> 77497.527
A73: =MAX(A62:A72)+0.001 -> 2.034 | B73: Reinforced concrete foundation for LED Screen as shown on drawing | C73: Lump Sum | D73: 1 | E73: 30115.619 | F73: =$D73*E73 -> 30115.619
A74: =MAX(A63:A73)+0.001 -> 2.035 | B74: Reinforced concrete foundation for 14m light pole as shown on drawing | C74: Lump Sum | D74: 1 | E74: 146395.37 | F74: =$D74*E74 -> 146395.37
A75: =MAX(A64:A74)+0.001 -> 2.036 | B75: Concrete Paving including underneath layers all as specified and shown on drawings. | C75: Lump Sum | D75: 1 | E75: 292322.28 | F75: =$D75*E75 -> 292322.28
A76: =MAX(A65:A75)+0.001 -> 2.037 | B76: Supply of Concrete interlock concrete pedestrian paving block; Including sand bed. | C76: Lump Sum | D76: 1 | E76: 25839.201 | F76: =$D76*E76 -> 25839.201
A77: =MAX(A66:A76)+0.001 -> 2.038 | B77: Installation of Concrete interlock concrete pedestrian paving block; Including sand bed all as specified and shown on drawings. | C77: Lump Sum | D77: 1 | E77: 17226.134 | F77: =$D77*E77 -> 17226.134
A78: =MAX(A67:A77)+0.001 -> 2.039 | B78: Supply of Concrete interlock concrete vehicular paving block; Including sand bed. | C78: Lump Sum | D78: 1 | E78: 335028.74 | F78: =$D78*E78 -> 335028.74
A79: =MAX(A68:A78)+0.001 -> 2.04 | B79: Installation of Concrete interlock concrete vehicular paving block; Including sand bed all as specified and shown on drawings. | C79: Lump Sum | D79: 1 | E79: 223352.49 | F79: =$D79*E79 -> 223352.49
A80: =MAX(A69:A79)+0.001 -> 2.041 | B80: Supply of Kerbs, Wheel Stoppers all in accordance with drawing and specifications | C80: Lump Sum | D80: 1 | E80: 42825.917 | F80: =$D80*E80 -> 42825.917
A81: =MAX(A70:A80)+0.001 -> 2.042 | B81: Installation of Kerbs, Wheel stoppers complete including excavation, concrete foundation and haunching, cement mortar and backfilling (where required) etc. ; all in accordance with drawing and specifications | C81: Lump Sum | D81: 1 | E81: 28550.611 | F81: =$D81*E81 -> 28550.611
A82: =MAX(A71:A81)+0.001 -> 2.043 | B82: Supply of Chlorinated rubber based paint for kerb, colour as per specification and as directed by the Engineer. | C82: Lump Sum | D82: 1 | E82: 42173.913 | F82: =$D82*E82 -> 42173.913
A83: =MAX(A72:A82)+0.001 -> 2.044 | B83: Installation of Chlorinated rubber based quick drying paint for kerbs applied in two coats to exposed faces of concrete kerbs and road separator; colour as per specification and as directed by the Engineer. | C83: Lump Sum | D83: 1 | E83: 11714.976 | F83: =$D83*E83 -> 11714.976
B84: Buildings
B85: Construct the buildings including excavation, backfilling, disposal of surplus material, anti-termite treatment, waterproofings, shoring works, plain cement concrete works, screed, reinforced concrete works, masonry works, metal works, internal finishes, external finishes, doors and windows, all necessary complete all as specified, as shown on the drawings and as per Engineer's approval.
A86: =MAX(A75:A85)+0.001 -> 2.045 | B86: Office, Guard Room, Operator Room & drivers toilet | C86: Lump Sum | D86: 1 | E86: 1528912.7 | F86: =$D86*E86 -> 1528912.7
B87: Gates, Fences and Barbed Wires
A88: =MAX(A77:A87)+0.001 -> 2.046 | B88: Supply Automatic Gate Barrier with Arm | C88: Lump Sum | D88: 1 | E88: 133010.65 | F88: =$D88*E88 -> 133010.65
A89: =MAX(A78:A88)+0.001 -> 2.047 | B89: Install Automatic Gate Barrier with Arm | C89: Lump Sum | D89: 1 | E89: 26769.439 | F89: =$D89*E89 -> 26769.439
B90: Boundary Wall
A91: =MAX(A80:A90)+0.001 -> 2.048 | B91: Boundary wall including excavation, preparation of surfaces, disposal of surplus materials, upholding sides of excavation, backfilling, removal of existing services, concrete, formworks and reinforcement, foundation works, coloumns, wall panels complete all as specified, as shown on drawings and as per Engineer approval. | C91: Lump Sum | D91: 1 | E91: 308383.94 | F91: =$D91*E91 -> 308383.94
B92: Removal, Refurbishment and Demolishing of Miscellaneous Objects
B93: Demolition
A94: =MAX(A83:A93)+0.001 -> 2.049 | B94: Removal of existing 2.35 high Chain link fence and hand over to Client Store | C94: Lump Sum | D94: 1 | E94: 24112.179 | F94: =$D94*E94 -> 24112.179
A95: =MAX(A84:A94)+0.001 -> 2.05 | B95: Removal of existing Interlocking tiles including underneath layers and handover tiles to Client Store | C95: Lump Sum | D95: 1 | E95: 43299.568 | F95: =$D95*E95 -> 43299.568
A96: =MAX(A85:A95)+0.001 -> 2.051 | B96: Removal of the existing Prefab structures and hand over to Client store | C96: Lump Sum | D96: 1 | E96: 6023.1239 | F96: =$D96*E96 -> 6023.1239
A97: =MAX(A86:A96)+0.001 -> 2.052 | B97: Removal and relocation of existing Parking Shades including,supply and install additional posts, foundation, shade and designated signages. | C97: Lump Sum | D97: 1 | E97: 30115.619 | F97: =$D97*E97 -> 30115.619
A98: =MAX(A87:A97)+0.001 -> 2.053 | B98: Removal of existing Tanker Filling Bays and handover to Client store | C98: Lump Sum | D98: 1 | E98: 18738.608 | F98: =$D98*E98 -> 18738.608
A99: =MAX(A88:A98)+0.001 -> 2.054 | B99: Removal and handover of existing gates to Client store or disposal to approved tip as directed by the Engineer | C99: Lump Sum | D99: 1 | E99: 7233.6537 | F99: =$D99*E99 -> 7233.6537
A100: =MAX(A89:A99)+0.001 -> 2.055 | B100: Demolition of existing Storm water channels and dispose to aPPRoved tip. | C100: Lump Sum | D100: 1 | E100: 10038.54 | F100: =$D100*E100 -> 10038.54
A101: =MAX(A90:A100)+0.001 -> 2.056 | B101: Removal of existing water cooler and hand over to client store | C101: Lump Sum | D101: 1 | E101: 1171.163 | F101: =$D101*E101 -> 1171.163
A102: =MAX(A91:A101)+0.001 -> 2.057 | B102: Refurbishment of Existing guard room | C102: Lump Sum | D102: 1 | E102: 12046.248 | F102: =$D102*E102 -> 12046.248
B103: Miscellaneous Items
A104: =MAX(A93:A103)+0.001 -> 2.058 | B104: Supply new water cooler | C104: Lump Sum | D104: 1 | E104: 7932.4148 | F104: =$D104*E104 -> 7932.4148
...

Sheet Nahel-Bill 03
B5: Bill No.3, Electrical Works
A6: Sl.No | B6: Description | C6: UNIT | D6: Quantity (Q) | E6: Unit Rate AED (A) | F6: Total Line Costs Ecxluding VAT B= AED (Q X A)
B7: Electrical
B8: LV Cable
A9: 3.001 | B9: Supply of LV Cables as per drawings and required specifications | C9: Lump Sum | D9: 1 | E9: 26342.802 | F9: =$D9*E9 -> 26342.802
A10: 3.002 | B10: Installation of LV Cables as per drawings and required specifications | C10: Lump Sum | D10: 1 | E10: 15805.681 | F10: =$D10*E10 -> 15805.681
A11: 3.003 | B11: Supply of CAT 6 Cables as per drawings and required specifications | C11: Lump Sum | D11: 1 | E11: 14762.559 | F11: =$D11*E11 -> 14762.559
A12: 3.004 | B12: Installation OF CAT 6 Cables as per drawings and required specifications | C12: Lump Sum | D12: 1 | E12: 3802.5989 | F12: =$D12*E12 -> 3802.5989
B13: FOC Cables
A14: 3.005 | B14: Supply of FOC Cables as per drawings and required specifications | C14: Lump Sum | D14: 1 | E14: 24604.264 | F14: =$D14*E14 -> 24604.264
A15: 3.006 | B15: Installation OF FOC Cables as per drawings and required specifications | C15: Lump Sum | D15: 1 | E15: 9841.7057 | F15: =$D15*E15 -> 9841.7057
B16: uPVC Ducts
A17: 3.007 | B17: Supply of uPVC ducts including , end caps, draw ropes, aluminium duct marker, warning tapes, cable tiles etc;complete; as per drawings, specification and authority requirement | C17: Lump Sum | D17: 1 | E17: 6337.6648 | F17: =$D17*E17 -> 6337.6648
A18: 3.008 | B18: Installation of uPVC ducts including excavation, shuttering, reinforcement, concrete encasement, back filling, reinstatement, end caps, draw ropes, aluminium duct marker, warning tapes, cable tiles etc;complete; as per drawings, specification and authority requirement | C18: Lump Sum | D18: 1 | E18: 3802.5989 | F18: =$D18*E18 -> 3802.5989
B19: Road Crossing uPVC Ducts for LV, FOC & CAT Cables
A20: 3.009 | B20: Supply of uPVC ducts complete; as per drawings, specification and authority requirement | C20: Lump Sum | D20: 1 | E20: 6337.6648 | F20: =$D20*E20 -> 6337.6648
A21: 3.01 | B21: Installation of uPVC ducts including excavation, shuttering, reinforcement, concrete encasement, back filling, reinstatement, end caps, draw ropes, aluminium duct marker, warning tapes, cable tiles etc;complete; as per drawings, specification and authority requirement | C21: Lump Sum | D21: 1 | E21: 3802.5989 | F21: =$D21*E21 -> 3802.5989
B22: Manholes
A23: 3.011 | B23: Manholes including excavation, backfilling, concrete works, blinding and screeds connection joints and protection coating to all internal concrete surfaces, waterproofing, cover & frame, complete in all respect as detailed on drawing and as per specification | C23: Lump Sum | D23: 1 | E23: 108545.06 | F23: =$D23*E23 -> 108545.06
B24: Main Distribution Board (MDB)
A25: 3.012 | B25: Supply, Main Distribution Board(MDB) complete including enclosure, bus bars, circuit breakers, and insulators, complete all as specified and as shown on drawings. | C25: Lump Sum | D25: 1 | E25: 541293.81 | F25: =$D25*E25 -> 541293.81
A26: 3.013 | B26: Installed, connected, and tested, complete including enclosure, bus bars, circuit breakers, and insulators,complete all as specified and as shown on drawings. | C26: Lump Sum | D26: 1 | E26: 49208.528 | F26: =$D26*E26 -> 49208.528
B27: Distribution Board(DB)
A28: 3.014 | B28: Supply, Distribution board complete including enclosure, bus bars, circuit breakers, and insulators, complete all as specified and as shown on drawings. | C28: Lump Sum | D28: 1 | E28: 24604.264 | F28: =$D28*E28 -> 24604.264
A29: 3.015 | B29: Install, Distribution board connected, and tested, complete including enclosure, bus bars, circuit breakers, and insulators,complete all as specified and as shown on drawings. | C29: Lump Sum | D29: 1 | E29: 7381.2793 | F29: =$D29*E29 -> 7381.2793
B30: Single Pole and Neutral (SPN) Isolator 20A
A31: 3.016 | B31: Supply, Single Pole and Neutral (SPN) Isolator 20A complete all as specified and as shown on drawings. | C31: Lump Sum | D31: 1 | E31: 9841.7057 | F31: =$D31*E31 -> 9841.7057
A32: 3.017 | B32: Install, connected, and tested, Single Pole and Neutral (SPN) Isolator 20A complete all as specified and as shown on drawings. | C32: Lump Sum | D32: 1 | E32: 2460.4264 | F32: =$D32*E32 -> 2460.4264
B33: Capacitor Bank 12.5 KVAR
A34: 3.018 | B34: Supply, Capacitor Bank 12.5 KVAR complete all as specified and as shown on drawings. | C34: Lump Sum | D34: 1 | E34: 49208.528 | F34: =$D34*E34 -> 49208.528
A35: 3.019 | B35: Install, connected, and tested, Capacitor Bank 12.5 KVAR complete all as specified and as shown on drawings. | C35: Lump Sum | D35: 1 | E35: 9841.7057 | F35: =$D35*E35 -> 9841.7057
B36: Electrical Meter IP55 Metal Case Meter Enclosure Recessed on wall
A37: 3.02 | B37: Supply, Electrical Meter 83A IP55 Metal Case Meter Enclosure Recessed on wall complete all as specified and as shown on drawings. | C37: Lump Sum | D37: 1 | E37: 9841.7057 | F37: =$D37*E37 -> 9841.7057
A38: 3.021 | B38: Install, connected, and tested, Electrical Meter 83A IP55 Metal Case Meter Enclosure Recessed on wall complete all as specified and as shown on drawings. | C38: Lump Sum | D38: 1 | E38: 2460.4264 | F38: =$D38*E38 -> 2460.4264
B39: LED SCREEN including Foundation
A40: 3.022 | B40: Supply, LED SCREEN complete all as specified and as shown on drawings. | C40: Lump Sum | D40: 1 | E40: 9841.7057 | F40: =$D40*E40 -> 9841.7057
A41: 3.023 | B41: Install, connected, and tested, LED SCREEN complete all as specified and as shown on drawings. | C41: Lump Sum | D41: 1 | E41: 1279.9138 | F41: =$D41*E41 -> 1279.9138
B42: Telecommunication System
A43: 3.024 | B43: Supply UPVC ducts complete; as per drawings, specification and authority requirement | C43: Lump Sum | D43: 1 | E43: 8173.0445 | F43: =$D43*E43 -> 8173.0445
A44: 3.025 | B44: Installation of upvc ducts including excavation, back filling, reinstatement, end caps, draw ropes, aluminium duct marker, warning tapes etc;complete; as per drawings, specification and authority requirement | C44: Lump Sum | D44: 1 | E44: 4903.8267 | F44: =$D44*E44 -> 4903.8267
B45: Manholes / Joint Boxes
A46: 3.026 | B46: Construct Reinforced concrete Manholes complete including excavation, filling, Manhole concrete, formwork, water proofing, cover & frame etc. in accordance with drawings, specifications and authority requirements. | C46: Lump Sum | D46: 1 | E46: 31428.995 | F46: =$D46*E46 -> 31428.995
B47: Telecom Box
A48: 3.027 | B48: Supply, Telecom Box complete all as specified and as shown on drawings. | C48: Lump Sum | D48: 1 | E48: 81563.136 | F48: =$D48*E48 -> 81563.136
A49: 3.028 | B49: Install, connected, and tested, Telecom Box including Foundation complete all as specified and as shown on drawings. | C49: Lump Sum | D49: 1 | E49: 48937.882 | F49: =$D49*E49 -> 48937.882
B50: Main Distribution Frame (MDF)
A51: 3.029 | B51: Supply, Main Distribution Frame (MDF) complete all as specified and as shown on drawings. | C51: Lump Sum | D51: 1 | E51: 37644.524 | F51: =$D51*E51 -> 37644.524
A52: 3.03 | B52: Install, connected, and tested, Main Distribution Frame (MDF) including Foundation complete all as specified and as shown on drawings. | C52: Lump Sum | D52: 1 | E52: 22586.715 | F52: =$D52*E52 -> 22586.715
A53: 3.031 | B53: Supply, ANPR Camera ( Part of Tanker Management System) ( Mounted Height 3M ) complete all as specified and as shown on drawings. | C53: Lump Sum | D53: 1 | E53: 30078.811 | F53: =$D53*E53 -> 30078.811
A54: 3.032 | B54: Install, ANPR Camera ( Part of Tanker Management System) ( Mounted Height 3M ) complete all as specified and as shown on drawings. | C54: Lump Sum | D54: 1 | E54: 18047.287 | F54: =$D54*E54 -> 18047.287
B55: ANPR Camera Pole 3M Height
A56: 3.033 | B56: Supply, Camera Pole 3M Height complete all as specified and as shown on drawings. | C56: Lump Sum | D56: 1 | E56: 2927.9074 | F56: =$D56*E56 -> 2927.9074
A57: 3.034 | B57: Install, Camera Pole 3M Height including Foundation complete all as specified and as shown on drawings. | C57: Lump Sum | D57: 1 | E57: 1756.7445 | F57: =$D57*E57 -> 1756.7445
B58: Pull Boxes
A59: 3.035 | B59: Supply pull box complete as shown on drawings, as specified and as per project requirement. | C59: Lump Sum | D59: 1 | E59: 24853.751 | F59: =$D59*E59 -> 24853.751
A60: 3.036 | B60: Supply and install pull box complete as shown on drawings, as specified and as per project requirement. | C60: Lump Sum | D60: 1 | E60: 14912.251 | F60: =$D60*E60 -> 14912.251
B61: Road Crossing uPVC Ducts for Telecommunication Network
A62: 3.037 | B62: Supply of uPVC ducts complete; as per drawings, specification and authority requirement | C62: Lump Sum | D62: 1 | E62: 11525.917 | F62: =$D62*E62 -> 11525.917
A63: 3.038 | B63: Installation of uPVC ducts including excavation, shuttering, reinforcement, concrete encasement, back filling, reinstatement, end caps, draw ropes, aluminium duct marker, warning tapes, cable tiles etc;complete; as per drawings, specification and authority requirement | C63: Lump Sum | D63: 1 | E63: 6915.5501 | F63: =$D63*E63 -> 6915.5501
B64: Area Lighting
A65: 3.039 | B65: Supply, Flood Light complete all as specified and as shown on drawings. | C65: Lump Sum | D65: 1 | E65: 24564.307 | F65: =$D65*E65 -> 24564.307
A66: 3.04 | B66: Install, connect, test Flood Light including complete all as specified and as shown on drawings. | C66: Lump Sum | D66: 1 | E66: 14738.584 | F66: =$D66*E66 -> 14738.584
A67: 3.041 | B67: Supply, Landscape Lighting Pull Box complete all as specified and as shown on drawings. | C67: Lump Sum | D67: 1 | E67: 19829.462 | F67: =$D67*E67 -> 19829.462
A68: 3.042 | B68: Install, connected, and tested, Landscape Lighting Pull Box complete all as specified and as shown on drawings. | C68: Lump Sum | D68: 1 | E68: 11897.677 | F68: =$D68*E68 -> 11897.677
A69: 3.043 | B69: Supply, Lighting Pole of height 14M including luminaries complete all as specified and as shown on drawings. | C69: Lump Sum | D69: 1 | E69: 90723.303 | F69: =$D69*E69 -> 90723.303
A70: 3.044 | B70: Install, connect and test Lighting Pole Height 14M including luminaries including foundation complete all as specified and as shown on drawings. | C70: Lump Sum | D70: 1 | E70: 54433.982 | F70: =$D70*E70 -> 54433.982
B71: Road Crossing for Area lighting Cables
A72: 3.045 | B72: Supply UPVC ducts complete; as per drawings, specification and authority requirement | C72: Lump Sum | D72: 1 | E72: 71194.997 | F72: =$D72*E72 -> 71194.997
A73: 3.046 | B73: Installation of uPVC ducts including excavation, shuttering, reinforcement, concrete encasement, back filling, reinstatement, end caps, draw ropes, aluminium duct marker, warning tapes, cable tiles etc;complete; as per drawings, specification and authority requirement | C73: Lump Sum | D73: 1 | E73: 42716.998 | F73: =$D73*E73 -> 42716.998
B74: Distribution Board (Area Lighting)
A75: 3.047 | B75: Supply,DB complete all as specified and as shown on drawings. | C75: Lump Sum | D75: 1 | E75: 7381.2793 | F75: =$D75*E75 -> 7381.2793
A76: 3.048 | B76: Installed, connected, and tested, DB complete including enclosure, bus bars, circuit breakers, and insulators, etc... complete all as specified and as shown on drawings. | C76: Lump Sum | D76: 1 | E76: 2460.4264 | F76: =$D76*E76 -> 2460.4264
B77: Earthing
A78: 3.049 | B78: Supply Earthing to Control Cabinet and poles including earth electrodes, earth pits and earthing cable from LCC or light pole to earth pit, complete as shown on drawing and as per specification | C78: Lump Sum | D78: 1 | E78: 41827.249 | F78: =$D78*E78 -> 41827.249
A79: 3.05 | B79: Install Earthing to Control Cabinet and poles including earth electrodes, earth pits and earthing cable from LCC or light pole to earth pit, complete as shown on drawing and as per specification | C79: Lump Sum | D79: 1 | E79: 25096.35 | F79: =$D79*E79 -> 25096.35
B80: Buildings
A81: 3.051 | B81: MEP works for building includes Power, lighting, fire alarm, fire extinguishers, Emrgency Lighting, Earthing, HVAC & Drainage system; complete all as specified, as shown on the drawings and as per Engineer's approval. | C81: Lump Sum | D81: 1 | E81: 344459.7 | F81: =$D81*E81 -> 344459.7
B82: SPARE PARTS FOR ELECTRICAL EQUIPMENT
A83: 3.052 | B83: Spare parts for sub-distribution boards complete as specified. | C83: Lump Sum | D83: 1 | E83: 41827.249 | F83: =$D83*E83 -> 41827.249
B84: Temporary power supply
A85: 3.053 | B85: Provision of temporary power supply including all necessary equipment, cables, connections, and distribution boards as required for the site. Contractor shall coordinate with TAQA/TAQA for all connection requirements, approvals, and inspections to ensure compliance with utility regulations. | C85: Lump Sum | D85: 1 | E85: 125481.75 | F85: =$D85*E85 -> 125481.75
B86: Total Costs for Bill No.3 excluding VAT (AED) | F86: =SUM(F9:F85) -> 2206138.9

Sheet Nahel-Bill 04
B5: Bill No.4, CONSTRUCTION OF PIPELINES
A6: Sl.No | B6: Description | C6: UNIT | D6: Quantity (Q) | E6: Unit Rate AED (A) | F6: Total Line Costs Ecxluding VAT B= AED (Q X A)
B7: A- Construction of uPVC Pipeline
B8: Construct Upvc pipeline as specified complete include installation of detectable warning tapes and other accessories as per specification. Rates shall include all costs for commissioning and handing over in full commercial operation. For the following pipelines
B9: Upvc pipe line
A10: 4.001 | B10: Upvc pipe line for Storm Water Works | C10: Lump Sum | D10: 1 | E10: 1739.3042 | F10: =$D10*E10 -> 1739.3042
A11: 4.002 | B11: Upvc pipe line for Sewer Works | C11: Lump Sum | D11: 1 | E11: 2342.326 | F11: =$D11*E11 -> 2342.326
B12: DI Pipelines
B13: Construct the Ductile Iron (D.I) pipeline as per the approved specifications, including tie-in connection with the existing line using polyethylene sleeves and rubber gaskets, installation of detectable warning tapes, and all necessary accessories. The scope includes supply of all materials, labor, equipment, and consumables required for the complete installation, as well as testing for pressure and leakage, flushing, disinfection, commissioning, and handing over the system in full commercial operation. The quoted rates shall cover all associated costs to deliver a fully functional and operational pipeline in compliance with relevant standards and project requirements.
A14: 4.003 | B14: DI Pipelines | C14: Lump Sum | D14: 1 | E14: 77938.4 | F14: =$D14*E14 -> 77938.4
B15: Construction of PPR Pipeline
B16: Construct PPR pipeline using butt fusion method as specified complete include installation of detectable warning tapes and other accessories as per specification. Rates shall include all costs for testing, flushing, disinfection, commissioning and handing over in full commercial operation.
A17: 4.004 | B17: PPR pipe line | C17: Lump Sum | D17: 1 | E17: 2455.3599 | F17: =$D17*E17 -> 2455.3599
B18: Exta over item For pipeline construction items for installation of D.I, PPR, HDPE & uPVC fittings complete (such as restrained couplings, bends, tees, reducers, reducing flanges, Lange spigot pieces, flange socket pieces, quick dismantling joints, flanged adaptors, socket connectors, tied dismantling joints, blank flanges, double flanged extension pieces, adjustable S bends, duck foot elbows, flanged pipe pieces with anchor flange, transition pieces, collars, stepped couplings, and caps, restraining glands, etc.) for the following pipes:
B19: uPVC Fittings
A20: 4.005 | B20: uPVC pipe line for Storm Water Works | C20: Lump Sum | D20: 1 | E20: 2119.7514 | F20: =$D20*E20 -> 2119.7514
A21: 4.006 | B21: uPVC pipe line for Sewerage Works | C21: Lump Sum | D21: 1 | E21: 3346.1799 | F21: =$D21*E21 -> 3346.1799
B22: DI Pipelines
A23: 4.007 | B23: DI Pipelines | C23: Lump Sum | D23: 1 | E23: 75502.823 | F23: =$D23*E23 -> 75502.823
B24: PPR Pipelines
A25: 4.008 | B25: PPR Pipelines | C25: Lump Sum | D25: 1 | E25: 2050.3517 | F25: =$D25*E25 -> 2050.3517
B26: Exta over item pipeline construction for installation of flanged valves, gate valves, flowmeters, control valves, etc. including all the accessories as per the specification.
A27: 4.009 | B27: Flow Meter Validation Unit | C27: Lump Sum | D27: 1 | E27: 37477.215 | F27: =$D27*E27 -> 37477.215
A28: 4.01 | B28: Settlement Type Electromagnetic Flow Meter | C28: Lump Sum | D28: 1 | E28: 37606.324 | F28: =$D28*E28 -> 37606.324
A29: 4.011 | B29: Control Valve Chamber | C29: Lump Sum | D29: 1 | E29: 53554.432 | F29: =$D29*E29 -> 53554.432
A30: 4.012 | B30: Air Valve | C30: Lump Sum | D30: 1 | E30: 2740.9898 | F30: =$D30*E30 -> 2740.9898
A31: 4.013 | B31: Washout Valve | C31: Lump Sum | D31: 1 | E31: 6626.2661 | F31: =$D31*E31 -> 6626.2661
A32: 4.014 | B32: Manual Butterfly Valve | C32: Lump Sum | D32: 1 | E32: 7211.8075 | F32: =$D32*E32 -> 7211.8075
A33: 4.015 | B33: Manual Check Valve | C33: Lump Sum | D33: 1 | E33: 12258.135 | F33: =$D33*E33 -> 12258.135
A34: 4.016 | B34: Electromagnetic Flow Meter | C34: Lump Sum | D34: 1 | E34: 210118.16 | F34: =$D34*E34 -> 210118.16
A35: 4.017 | B35: Gate Valve | C35: Lump Sum | D35: 1 | E35: 4718.1137 | F35: =$D35*E35 -> 4718.1137
B36: Service Connections
B37: Installation of Pipework for Service Connections
B38: Construct of New Tapping : Work includes Hand excavation, dewatring,and installation of new saddle strap & ferrule/pressure tapping tee with extra long outlet with all required fittings and supply of installation of moulding compound warping tap & polythene sleeve for protection of saddle & ferrule,backfilling and shutdown of distribution etc.all as per TAQA Specification.
A39: 4.018 | B39: Tapping in 400 DI Main line | C39: Lump Sum | D39: 1 | E39: 8030.8318 | F39: =$D39*E39 -> 8030.8318
B40: Construct reinforced concrete encased Socket type uPVC DUCTS for the areas under car pass, for the proposed polyethylene house connection pipes, including the supply of uPVC pipe used for protection and all other materials complete with uPVC end cap at each duct end, duct end sealing, bituminous painting of concrete, excavation by hand, dewatering, backfilling and provision of 10 mm dia. pulling rope for installation of polyethylene house connection pipes etc. all as per TAQA Specification and Tender Drawings and as directed by TAQA/ENGINEER :
A41: 4.019 | B41: Reinforce concrete encasement for uPVC pipes for Storm Water Works | C41: Lump Sum | D41: 1 | E41: 18738.608 | F41: =$D41*E41 -> 18738.608
B42: Total Costs for Bill No.4 excluding VAT (AED) | F42: =SUM(F10:F41) -> 566575.37

Sheet Nahel-Bill 05
B5: Bill No.5, INSTRUMENTATION AND CONTROL/ SCADA
A6: Sl.No | B6: Description | C6: UNIT | D6: Quantity (Q) | E6: Unit Rate AED (A) | F6: Total Line Costs Ecxluding VAT B= AED (Q X A)
B7: TANKER CONTROL SYSTEM/WorkStation
B8: CONTROL SYSTEM
A9: 5.001 | B9: Dual system servers including but not limited to, CPU, HDD, keyboard mouse, DVDD, USB drive, software interface devices. | C9: No | D9: 1 | E9: 124949.7 | F9: =$D9*E9 -> 124949.7
A10: 5.002 | B10: Operator workstation including but not limited to, two computers each 21" LCD monitor, CPU, keyboard, mouse, interface devices, 2 GB RAM min., HDD, USB drive, DVDD etc. including one printer. | C10: No | D10: 1 | E10: 40667.798 | F10: =$D10*E10 -> 40667.798
A11: 5.003 | B11: Electronic cabinets including but not limited to, one dual redundant, PLC, communication and power supply modules, interface/signal/alarm etc. modules alongwith suitable communication equipment. | C11: No | D11: 1 | E11: 531639.39 | F11: =$D11*E11 -> 531639.39
A12: 5.004 | B12: Redundant secured communication network, bus and interfaces and other auxiliaries, as required | C12: Lump Sum | D12: 1 | E12: 147036.17 | F12: =$D12*E12 -> 147036.17
A13: 5.005 | B13: Software packages including but not limited to the original license including all application, engineering and HMI software, configuration software etc., as required. | C13: Lump Sum | D13: 1 | E13: 446271.65 | F13: =$D13*E13 -> 446271.65
A14: 5.006 | B14: Field Process Unit, which consists of flow computer with card reader, push buttons for Start / Stop, Emergency push button, lamps for indication, remote I/O module/ RTU | C14: No | D14: 8 | E14: 184262.42 | F14: =$D14*E14 -> 1474099.3
A15: 5.007 | B15: Start / Stop Panel for Manual Tanker Filling Operation as specified | C15: No | D15: 8 | E15: 3588.778 | F15: =$D15*E15 -> 28710.224
A16: 5.008 | B16: Fiscal Ticket Printers for printing the prepaid cards etc. as required showing tanker information , volume and amount. To be installed in Customer Service Unit of the office building | C16: No | D16: 2 | E16: 29212.151 | F16: =$D16*E16 -> 58424.302
A17: 5.009 | B17: Supply and Install A3 & A4 printer | C17: Lump Sum | D17: 1 | E17: 7968.9275 | F17: =$D17*E17 -> 7968.9275
A18: 5.01 | B18: Supply and Install UPS as required | C18: Lump Sum | D18: 1 | E18: 119528.89 | F18: =$D18*E18 -> 119528.89
B19: LEVEL SWITCHES
A20: 5.011 | B20: Supply of level switches of suitable type for tanker overflow detection complete with cable and other installation accessories to be installed on the filling hose. | C20: No. | D20: 8 | E20: 14221.265 | F20: =$D20*E20 -> 113770.12
A21: 5.012 | B21: ACCESS CONTROL SYSTEM
A22: 5.013 | B22: Proximity Card Reader Unit / including all accessories required for installing at the entrance of the station, complete with power supply unit, modules etc and all other accessories as required for communication to centralised loading system PLC. | C22: No | D22: 4 | E22: 99607.411 | F22: =$D22*E22 -> 398429.64
A23: 5.014 | B23: Motorised boom including warning beacons, audible alram and all other accessries, to be installed at the entrance and exit of the station as required including interfaces with the loading system PLC. | C23: No | D23: 4 | E23: 119528.89 | F23: =$D23*E23 -> 478115.57
A24: 5.015 | B24: Display units for bay identifcation and driver information including all required accessories and interfaces. | C24: No | D24: 10 | E24: 41318.63 | F24: =$D24*E24 -> 413186.3
B25: SPARE PARTS FOR ELECTRICAL EQUIPMENT
A26: 5.016 | B26: Spare parts for sub-distribution boards complete as specified. | C26: Lump Sum | D26: 1 | E26: 147566.54 | F26: =$D26*E26 -> 147566.54
B27: SPARE PARTS FOR I & C SYSTEM & F.O CABLE
B28: SPARE FOR THE FIELD INSTRUMENTS
A29: 5.017 | B29: Electromagnetic flowmeter transmitter. | C29: No | D29: 1 | E29: 68434.399 | F29: =$D29*E29 -> 68434.399
A30: 5.018 | B30: Pressure transmitter (One from each range selected) | C30: No | D30: 1 | E30: 7528.9049 | F30: =$D30*E30 -> 7528.9049
A31: 5.019 | B31: Differential pressure switch, one no. for the highest range selected. | C31: No | D31: 1 | E31: 11910.727 | F31: =$D31*E31 -> 11910.727
A32: 5.02 | B32: Pressure gauge, one no. for each range selected. | C32: No | D32: 1 | E32: 1425.4727 | F32: =$D32*E32 -> 1425.4727
A33: 5.021 | B33: Level Switches | C33: No | D33: 1 | E33: 8345.3728 | F33: =$D33*E33 -> 8345.3728
B34: SPARES FOR CONTROL AND SCADA SYSTEM
A35: 5.022 | B35: The number of spare equipment modules shall be 5% of the installed units, rounded upto the nearest integer i.e. CPU, CP, power supply modules, I/O modules of each type, bus controller, fibre optic interfaace modules, all communication device and modules etc. alongwith 10% spare hardware accessories like relays, batteries, MCB's, etc, and EPROM/EEPROM shall be 2 minimum of each type. | C35: Lump Sum | D35: 1 | E35: 250863.11 | F35: =$D35*E35 -> 250863.11
B36: SPARE FOR F.O. CABLE SYSTEM
A37: 5.023 | B37: Fibre optical splicing kit, 1 set for tap off location. | C37: Lump Sum | D37: 1 | E37: 103296.57 | F37: =$D37*E37 -> 103296.57
A38: 5.024 | B38: 10% minimum F.O. interfacing module/component of each type installed at the F.O. system cabinet/panel including interfacing module, power supply module, patch panel etc. | C38: Lump Sum | D38: 1 | E38: 44269.961 | F38: =$D38*E38 -> 44269.961
A39: 5.025 | B39: Recommended consumables for 2 years trouble free operation | C39: Lump Sum | D39: 1 | E39: 44269.961 | F39: =$D39*E39 -> 44269.961
A40: 5.026 | B40: SCADA System Integration with existing main SCADA and Customer care and Billing System ( CC&B) | C40: Lump Sum | D40: 1 | E40: 49208.528 | F40: =$D40*E40 -> 49208.528
B41: Total Costs for Bill No.5 excluding VAT (AED) | F41: =SUM(F9:F40) -> 5119917.6

Sheet AL SAAD-Summary 
B5: SUMMARY SHEET - AL SAAD
A6: Bill No. | B6: Description | C6: Total Costs Excluding VAT (AED)
A7: 1 | B7: SUPPLY OF PIPEWORKS | C7: ='AL SAAD-Bill 01'!F63 -> 939505.77
A8: 2 | B8: CIVIL WORKS | C8: ='AL SAAD- Bill 02'!F141 -> 7924905.6
A9: 3 | B9: ELECTRICAL WORKS | C9: ='AL SAAD-Bill 03'!F119 -> 2611404.6
A10: 4 | B10: CONSTRUCTION OF PIPELINES | C10: ='AL SAAD-Bill 04'!F55 -> 417097.81
A11: 5 | B11: INSTRUMENTATION AND CONTROL/ SCADA | C11: ='AL SAAD- Bill 05'!F44 -> 3928316.1
B13: Total Costs Excluding VAT ( AED) | C13: =SUM(C7:C11) -> 15821230
B14: Total Value Added Tax (VAT/5%) (AED) | C14: =C13*0.05 -> 791061.49
B15: Total Costs Including VAT (AED) | C15: =SUM(C13:C14) -> 16612291
B18: Total Costs in Words Excluding VAT (AED): | C18: Dirhams Fifteen million, eight hundred twenty-one thousand, two hundred twenty-nine and eighty-eight Fils
B19: VAT Amount in Words (AED): | C19: Dirhams Seven hundred ninety-one thousand, sixty-one and forty-nine Fils
B20: Total Costs in Words Including VAT (AED): | C20: Dirhams Sixteen million, six hundred twelve thousand, two hundred ninety-one and thirty-eight Fils

Sheet AL SAAD-Bill 01
B5: Bill No.1, SUPPLY OF PIPEWORKS
A6: Sl.No | B6: Description | C6: UNIT | D6: Quantity (Q) | E6: Unit Rate AED (A) | F6: Total Line Costs Ecxluding VAT B= AED (Q X A)
B7: Storm Water Works
A8: 1.001 | B8: Supply the following ISO standard uPVC including warning tape and all other accessories as per ADEWA standard specifications | C8: Lump Sum | D8: 1 | E8: 6726.1743 | F8: =$D8*E8 -> 6726.1743
B9: Sewerage Works
A10: 1.002 | B10: Supply the following ISO standard uPVC including warning tape and all other accessories as per ADEWA standard specifications | C10: Lump Sum | D10: 1 | E10: 2718.8042 | F10: =$D10*E10 -> 2718.8042
B11: Gully Trap
A12: =MAX(A7:A11)+0.001 -> 1.003 | B12: Supply the following ISO standard Gully trap including all other accessories as per ADEWA standard specifications | C12: Lump Sum | D12: 1 | E12: 225.86715 | F12: =$D12*E12 -> 225.86715
B13: Potable Water Works
B14: Ductile Iron (DI) Pipe
B15: Supply and Install DI pipe as specified complete with installation of detectable warning tapes and other accessories all in accordance with TAQA standard specification, data sheet and drawings.
A16: =MAX(A11:A15)+0.001 -> 1.004 | B16: DI - Standard Socket Spigot pipes | C16: Lump Sum | D16: 1 | E16: 119125.14 | F16: =$D16*E16 -> 119125.14
A17: 1.004a | B17: DI - Restrained | C17: Lump Sum | D17: 1 | E17: 119125.14 | F17: =$D17*E17 -> 119125.14
B18: Gate Valves
A19: =MAX(A14:A18)+0.001 -> 1.005 | B19: Supply of PN 16 Manual Gate Valves above ground in inaccordance with specification, drawings and data sheet. | C19: Lump Sum | D19: 1 | E19: 4517.8984 | F19: =$D19*E19 -> 4517.8984
B20: CHECK VALVES
A21: =MAX(A16:A20)+0.001 -> 1.006 | B21: Supply of Check Valves above ground in inaccordance with specification, drawings and data sheet. | C21: Lump Sum | D21: 1 | E21: 6584.953 | F21: =$D21*E21 -> 6584.953
B22: Air Valves
A23: =MAX(A18:A22)+0.001 -> 1.007 | B23: Supply of Air Valves in accordance with specification, drawings and data sheet. | C23: Lump Sum | D23: 1 | E23: 8326.4106 | F23: =$D23*E23 -> 8326.4106
B24: Bulk Connection Chamber Valves & Fittings
A25: =MAX(A20:A24)+0.001 -> 1.008 | B25: Supply of Manual Check Valves & Fittings in accordance with specification, drawings and data sheet. | C25: Lump Sum | D25: 1 | E25: 8268.115 | F25: =$D25*E25 -> 8268.115
A26: =MAX(A21:A25)+0.001 -> 1.009 | B26: Supply of Manual Butterfly Valves & Fittings in accordance with specification, drawings and data sheet. | C26: Lump Sum | D26: 1 | E26: 5586.8172 | F26: =$D26*E26 -> 5586.8172
A27: =MAX(A22:A26)+0.001 -> 1.01 | B27: Supply of Settlement Type Electromagnetic Flow Meter & Fittings on 300mm dia line in accordance with specification, drawings and data sheet. | C27: Lump Sum | D27: 1 | E27: 60811.993 | F27: =$D27*E27 -> 60811.993
A28: =MAX(A23:A27)+0.001 -> 1.011 | B28: Supply of Control Valve & Fittings in accordance with specification, drawings and data sheet. | C28: Lump Sum | D28: 1 | E28: 39941.6 | F28: =$D28*E28 -> 39941.6
B29: Wash Out Valves
A30: =MAX(A25:A29)+0.001 -> 1.012 | B30: Supply of Wash Out Valves in accordance with specification, drawings and data sheet. | C30: Lump Sum | D30: 1 | E30: 4267.9247 | F30: =$D30*E30 -> 4267.9247
B31: Bip Tap
A32: =MAX(A27:A31)+0.001 -> 1.013 | B32: Supply of BIP TAP including all fittings and accessories | C32: Lump Sum | D32: 1 | E32: 451.73429 | F32: =$D32*E32 -> 451.73429
B33: Flow Meter Validation Unit
A34: =MAX(A29:A33)+0.001 -> 1.014 | B34: Supply flow meter validation unit with validation software all as per specifications. The unit shall be supplied with power supply with rechargeable batteries and integral charger unit. | C34: Lump Sum | D34: 1 | E34: 32123.327 | F34: =$D34*E34 -> 32123.327
B35: Flow Control Valve
A36: 1.014a | B36: Supply flow control valve for the above ground(Vertical pipeline) validation unit with validation software all as per specifications. The unit shall be supplied with power supply with rechargeable batteries and integral charger unit. | C36: Lump Sum | D36: 1 | E36: 40236.594 | F36: =$D36*E36 -> 40236.594
B37: Electromagnetic Flow Meter
A38: =MAX(A33:A37)+0.001 -> 1.015 | B38: Supply of 6" flow meter. all in accordance with specification, data sheet and drawings. | C38: Lump Sum | D38: 1 | E38: 148120.26 | F38: =$D38*E38 -> 148120.26
B39: PPR Pipes
A40: =MAX(A35:A39)+0.001 -> 1.016 | B40: Supply , PPR 20-25mm pipes Including valves and chambers all as specified and shown on drawings. | C40: Lump Sum | D40: 1 | E40: 1349.7369 | F40: =$D40*E40 -> 1349.7369
B41: Flexible hoses
A42: =MAX(A37:A41)+0.001 -> 1.017 | B42: Supply of PN 16 Flexible hoses of sufficient length, with one end flanged and necessary attachments including fasteners, gaskets etc. for filling bays as specified. | C42: Lump Sum | D42: 1 | E42: 17935.524 | F42: =$D42*E42 -> 17935.524
B43: HDPE Pipes
A44: =MAX(A39:A43)+0.001 -> 1.018 | B44: Supply of HDPE pipes including all fittings all as specified and as shown on drawings. | C44: Lump Sum | D44: 1 | E44: 33311.027 | F44: =$D44*E44 -> 33311.027
B45: Water booster set
B46: Water booster set, with two or three vertical multi-stage pumps as shown on drawings, control box, skid mounted, installed, connected and tested complete with stainless steel headers, pump individual isolating ball valves, check valves, isolating butterfly valves PN 20, lug and wafer type lever operated, strainer cast iron body PN 20, flexible connections, concrete inertia pad, house pad, vibration eliminator pad, low level control float switches, pressure switch and controls all supplied from pump manufacturer diaphragm tank (s), food quality synthetic rubber membrane, steel painted body, working pressure 10 bars with isolating valve and pressure gauge, electric connections, wiring and accessories all as specified and shown on the drawings.
A47: =MAX(A42:A46)+0.001 -> 1.019 | B47: Pump Capacity 51 l/s @ 2Bar(1 Duty + 1 Standby) | C47: Lump Sum | D47: 1 | E47: 159990.15 | F47: =$D47*E47 -> 159990.15
B48: Domestic water pump set
B49: Domestic water pump set for building, with single stage pumps and pressure vessel as shown on drawings, control box, skid mounted, installed, connected and tested complete with stainless steel headers, pump individual isolating ball valves, check valves, isolating butterfly valves PN 20, lug and wafer type lever operated, strainer cast iron body PN 20, flexible connections, concrete inertia pad, house pad, vibration eliminator pad, low level control float switches, pressure switch and controls all supplied from pump manufacturer diaphragm tank (s), food quality synthetic rubber membrane, steel painted body, working pressure 2 bars with isolating valve and pressure gauge, electric connections, wiring and accessories all as specified and shown on the drawings.
A50: =MAX(A45:A49)+0.001 -> 1.02 | B50: Water pump set 1 duty + I standby 1.0 L/S @30m head each pump | C50: Lump Sum | D50: 1 | E50: 13040.063 | F50: =$D50*E50 -> 13040.063
B51: Tie in connection with existing network
B52: Gate Valves
A53: =MAX(A48:A52)+0.001 -> 1.021 | B53: Supply of PN 16 Manual Gate Valves above ground on 200mm dia line in accordance with specification, drawings and data sheet. | C53: Lump Sum | D53: 1 | E53: 24057.543 | F53: =$D53*E53 -> 24057.543
B54: Wash Out Valves
A55: =MAX(A50:A54)+0.001 -> 1.022 | B55: Supply of PN 16 Washout Valves above ground on 200mm dia line in accordance with specification, drawings and data sheet. | C55: Lump Sum | D55: 1 | E55: 3812.7437 | F55: =$D55*E55 -> 3812.7437
B56: Air Valves
A57: =MAX(A52:A56)+0.001 -> 1.023 | B57: Supply of PN 16 Air Valves above ground on 200mm dia line in accordance with specification, drawings and data sheet. | C57: Lump Sum | D57: 1 | E57: 8326.4106 | F57: =$D57*E57 -> 8326.4106
B58: Bulk Connection Chamber Valves & Fittings
A59: =MAX(A54:A58)+0.001 -> 1.024 | B59: Supply of Manual Check Valves & Fittings on 200mm pipe in accordance with specification, drawings and data sheet. | C59: Lump Sum | D59: 1 | E59: 5244.2834 | F59: =$D59*E59 -> 5244.2834
A60: =MAX(A55:A59)+0.001 -> 1.025 | B60: Supply of Manual Butterfly Valves & Fittings on 200mm in accordance with specification, drawings and data sheet. | C60: Lump Sum | D60: 1 | E60: 4772.4141 | F60: =$D60*E60 -> 4772.4141
A61: =MAX(A56:A60)+0.001 -> 1.026 | B61: Supply of Settlement Type Electromagnetic Flow Meter & Fittings on 200mm dia line in accordance with specification, drawings and data sheet. | C61: Lump Sum | D61: 1 | E61: 34549.101 | F61: =$D61*E61 -> 34549.101
A62: =MAX(A57:A61)+0.001 -> 1.027 | B62: Supply of Control Valve & Fittings on 200mm dia pipe in accordance with specification, drawings and data sheet. | C62: Lump Sum | D62: 1 | E62: 25958.015 | F62: =$D62*E62 -> 25958.015
B63: Total Costs for Bill No.1 excluding VAT (AED) | F63: =SUM(F8:F62) -> 939505.77

Sheet AL SAAD- Bill 02
B5: Bill No.2, CIVIL WORKS
A6: Sl.No | B6: Description | C6: UNIT | D6: Quantity (Q) | E6: Unit Rate AED (A) | F6: Total Line Costs Ecxluding VAT B= AED (Q X A)
B7: Trial trench and Trial pits
A8: 2.001 | B8: Trial trench and Trial pits | C8: Lump Sum | D8: 1 | E8: 6512.0008 | F8: =$D8*E8 -> 6512.0008
B9: Trenches for Pipelines
B10: Excavate and Backfill Trenches for Pipelines
B11: Excavate, dewater and backfill trenches for pipelines including shoring, surveying, etc. for a maximum cover to pipelines of 1.2 m as per specification and as shown in drawings for the following sizes of pipelines
B12: PPR Pipelines
A13: 2.002 | B13: PPR Pipelines | C13: Lump Sum | D13: 1 | E13: 52997.585 | F13: =$D13*E13 -> 52997.585
B14: HDPE Pipelines
A15: 2.003 | B15: HDPE Pipelines | C15: Lump Sum | D15: 1 | E15: 137321.32 | F15: =$D15*E15 -> 137321.32
B16: DI Pipelines
A17: 2.004 | B17: DI Pipelines | C17: Lump Sum | D17: 1 | E17: 164174.41 | F17: =$D17*E17 -> 164174.41
B18: uPVC Pipelines for Storm Water Works
A19: 2.005 | B19: uPVC Pipelines | C19: Lump Sum | D19: 1 | E19: 22129.075 | F19: =$D19*E19 -> 22129.075
B20: uPVC Pipelines for Sewerage Works
A21: 2.006 | B21: uPVC Pipelines | C21: Lump Sum | D21: 1 | E21: 30541.372 | F21: =$D21*E21 -> 30541.372
B22: E.O.I for Excavate and Backfill Trenches for Pipelines
B23: E.O.I. for excavation of every additional 500 mm excavation depth exceeding 1.2 m cover, including dewatering, shoring, backfilling and disposal of surplus material all as per specification for the following pipelines
B24: PPR Pipelines
A25: 2.007 | B25: PPR Pipelines | C25: Lump Sum | D25: 1 | E25: 4920.8528 | F25: =$D25*E25 -> 4920.8528
B26: DI Pipelines
A27: 2.008 | B27: DI Pipelines | C27: Lump Sum | D27: 1 | E27: 4920.8528 | F27: =$D27*E27 -> 4920.8528
B28: HDPE Pipelines
A29: 2.009 | B29: HDPE Pipelines | C29: Lump Sum | D29: 1 | E29: 4920.8528 | F29: =$D29*E29 -> 4920.8528
B30: uPVC Pipelines for Storm Water Works
A31: 2.01 | B31: uPVC Pipelines | C31: Lump Sum | D31: 1 | E31: 4920.8528 | F31: =$D31*E31 -> 4920.8528
B32: uPVC Pipelines for Sewerage Works
A33: 2.011 | B33: uPVC Pipelines | C33: Lump Sum | D33: 1 | E33: 4920.8528 | F33: =$D33*E33 -> 4920.8528
A34: 2.012 | B34: E.O.I for excavation in rock using rock breaker including disposal of excavated material as per the Municipality requirements - the rock should be classified as per specs by lab test | C34: Lump Sum | D34: 1 | E34: 4920.8528 | F34: =$D34*E34 -> 4920.8528
A35: 2.013 | B35: E.O.I. for supply, place and compact approved imported bedding / fill material/gatch including disposal of surplus material as per specifications and as ordered and authorized by TAQA Engineer | C35: Lump Sum | D35: 1 | E35: 4920.8528 | F35: =$D35*E35 -> 4920.8528
A36: 2.014 | B36: General excavation for any other purpose including dewatering, backfilling as required or instructed by TAQA Engineer. | C36: Lump Sum | D36: 1 | E36: 23699.654 | F36: =$D36*E36 -> 23699.654
B37: Construction of Manholes and Facilities at Pipelines for Storm Water Works
A38: 2.015 | B38: Manholes including excavation, dewatering, shoring, backfilling, concrete works including the Removable cover slab, benching, blinding and screeds connection joints and protection coating to all internal concrete surfaces, waterproofing , tanking , heavy duty ductile cover & frame, complete in all respect as detailed on drawing and as per specification | C38: Lump Sum | D38: 1 | E38: 86557.802 | F38: =$D38*E38 -> 86557.802
B39: Construction of Manholes and Facilities at Pipelines for Sewer Works
A40: 2.016 | B40: Manholes including excavation, dewatering, shoring, backfilling, concrete works including the Removable cover slab, benching, blinding and screeds connection joints and protection coating to all internal concrete surfaces, waterproofing , tanking , heavy duty ductile cover & frame, complete in all respect as detailed on drawing and as per specification | C40: Lump Sum | D40: 1 | E40: 151808.31 | F40: =$D40*E40 -> 151808.31
A41: 2.017 | B41: Construction Storm water channels excavation, dewatering, shoring, backfilling, concrete works including the gratings complete in all respect as detailed on drawing and as per specification | C41: Lump Sum | D41: 1 | E41: 51929.407 | F41: =$D41*E41 -> 51929.407
A42: 2.018 | B42: Construction of Concrete support (thrust blocks) for fittngs including reinforcement, formwork, backfilling etc. as per authority requirements, specifications and drawings | C42: Lump Sum | D42: 1 | E42: 15353.061 | F42: =$D42*E42 -> 15353.061
A43: 2.019 | B43: Construct reinforced concrete encased socket type GRP DUCTS for the proposed road crossing pipes, including the supply of all material complete with GRP end cap at each duct end, duct end sealing, bituminous painting of concrete, excavation, dewatering, backfilling and provision of 10 mm dia. pulling rope for installation of HDPE distribution pipes etc. all as per the specification and tender drawings, as per TAQA standards and as directed by Engineer. | C43: Lump Sum | D43: 1 | E43: 63577.419 | F43: =$D43*E43 -> 63577.419
B44: Soakaway
A45: 2.02 | B45: Costruction of Soakway | C45: Lump Sum | D45: 1 | E45: 15766.413 | F45: =$D45*E45 -> 15766.413
B46: Backdrops
A47: 2.021 | B47: Construction of Backdrop complete with concrete surround as per SWS standard drawing | C47: Lump Sum | D47: 1 | E47: 27064.691 | F47: =$D47*E47 -> 27064.691
B48: Construction of Chambers, and Facilities at Pipelines
B49: Construction of Concrete Chambers
B50: Construct reinforced concrete chambers, as per TAQA's standard specification with precast cover slab for chambers on pipelines including the supply of all materials complete with protection board and water proofing of outside walls from top to bottom water stop at construction joints, installation of hot dipped galvanized lifting hooks in cover slab, supports for valve spindle extension casting in of anchor flange sealing flange (water stop),access cover frame, surface box, chamber indication plate owner information plate ventilation pipes bolting of aluminum ladder excavation dewatering, backfilling, etc., all as per specification and as shown on tender drawings (for lifting hooks, ladder, vent pipes, chamber protection & water stop) all as directed and authorized by TAQA Engineer (not include supply of pipework inside chambers)
A51: 2.022 | B51: Gate Valve Chamber (s) as per Drawing | C51: Lump Sum | D51: 1 | E51: 21651.753 | F51: =$D51*E51 -> 21651.753
A52: 2.023 | B52: Flow Meter Chamber (s) as per Drawings | C52: Lump Sum | D52: 1 | E52: 21651.753 | F52: =$D52*E52 -> 21651.753
A53: 2.024 | B53: Control Valve Chamber (s) as per Drawing | C53: Lump Sum | D53: 1 | E53: 30017.202 | F53: =$D53*E53 -> 30017.202
A54: 2.025 | B54: Bulk Connection Chamber (s) as per Drawings | C54: Lump Sum | D54: 1 | E54: 21651.753 | F54: =$D54*E54 -> 21651.753
A55: 2.026 | B55: Check Valve Chamber (s) as per Drawings | C55: Lump Sum | D55: 1 | E55: 21651.753 | F55: =$D55*E55 -> 21651.753
A56: 2.027 | B56: Washout Valve Chamber (s) as per Drawings | C56: Lump Sum | D56: 1 | E56: 21651.753 | F56: =$D56*E56 -> 21651.753
A57: 2.028 | B57: Air Release Valve Chamber (s) as per Drawings | C57: Lump Sum | D57: 1 | E57: 21651.753 | F57: =$D57*E57 -> 21651.753
A58: 2.029 | B58: Manual Check Valve Chamber (s) as per Drawings | C58: Lump Sum | D58: 1 | E58: 21651.753 | F58: =$D58*E58 -> 21651.753
B59: GRP Tank
A60: 2.03 | B60: Supply 6m3 GRP tank including GRP panel not less than 8mm, insulation 25mm, all as specified and shown on drawings. | C60: Lump Sum | D60: 1 | E60: 11778.16 | F60: =$D60*E60 -> 11778.16
A61: 2.031 | B61: Install,test and commissioning 6m3 GRP tank including GRP panel not less than 8mm, insulation 25mm, all as specified and shown on drawings. | C61: Lump Sum | D61: 1 | E61: 7852.1065 | F61: =$D61*E61 -> 7852.1065
A62: 2.031 | B62: Supply 1400m3 GRP tank including GRP panel not less than 8mm, insulation 25mm, all as specified and shown on drawings. | C62: Lump Sum | D62: 1 | E62: 1340873.3 | F62: =$D62*E62 -> 1340873.3
A63: 2.032 | B63: Install,test and commissioning 1400m3 GRP tank including GRP panel not less than 8mm, insulation 25mm, all as specified and shown on drawings. | C63: Lump Sum | D63: 1 | E63: 701674.25 | F63: =$D63*E63 -> 701674.25
B64: Structural Steel Column for Ladder Support
A65: 2.033 | B65: Supply, fabrication, and installation of structural steel column for ladder support, including all required base plates, anchor bolts, connections, welding, surface treatment, and complete erection at site. Works shall be carried out as per approved drawings, specifications, and relevant standards. All associated materials, labor, equipment, and coordination are to be included to complete the item in all respects. | C65: Lump Sum | D65: 1 | E65: 58045.68 | F65: =$D65*E65 -> 58045.68
B66: Steel Ladders
A67: 2.034 | B67: Supply and Install Steel adjustable ladder including supporting frame, shade and hand rail as shown on drawing | C67: Lump Sum | D67: 1 | E67: 89301.046 | F67: =$D67*E67 -> 89301.046
B68: Car Parking Shed
A69: 2.035 | B69: Car Parking Shed including post, foundation and designated signages all as specified and shown on drawings. | C69: Lump Sum | D69: 1 | E69: 33461.799 | F69: =$D69*E69 -> 33461.799
B70: Garbage Containers
A71: 2.036 | B71: Garbage containers and bins with lid all as specified and shown on drawings. | C71: Lump Sum | D71: 1 | E71: 2710.4057 | F71: =$D71*E71 -> 2710.4057
B72: Asphalt Works
A73: 2.037 | B73: Asphalt Paving including underneath layers | C73: Lump Sum | D73: 1 | E73: 449460.56 | F73: =$D73*E73 -> 449460.56
B74: Road Surface Markings
B75: Surface markings
A76: 2.038 | B76: In accordance with Traffic Control Devices Manual on uniform traffic control devices TR-511 Surface markings including all necessary preparation works, etc.; all in accordance with Road Markings Plan drawings and specifications | C76: Lump Sum | D76: 1 | E76: 6451.4349 | F76: =$D76*E76 -> 6451.4349
B77: Traffic Signs
A78: 2.039 | B78: Supply In accordance with Traffic Control Devices Manual Second Edition September 2020 of Abu Dhabi City Municipality Warning and Regulatory Sign and Posts etc.; all in accordance with Traffic Device Plan drawings and Specification | C78: Lump Sum | D78: 1 | E78: 13250.873 | F78: =$D78*E78 -> 13250.873
A79: 2.04 | B79: Install In accordance with Traffic Control Devices Manual Second Edition September 2020 of Abu Dhabi City Municipality Warning and Regulatory Sign and Posts including all necessary civil works, etc.; all in accordance with Traffic Device Plan drawings and Specification | C79: Lump Sum | D79: 1 | E79: 8833.915 | F79: =$D79*E79 -> 8833.915
B80: Concrete Works
A81: 2.041 | B81: Construct reinforced foundation for GRP Tank including all works | C81: Lump Sum | D81: 1 | E81: 360617.48 | F81: =$D81*E81 -> 360617.48
A82: 2.042 | B82: Reinforced concrete Coloumn including Concrete foundation, Aluminum Cladding, Steel Truss, Tension cables, 40mm mild steel painted hollow section, lighting, telephone etc as shown on drawing and as per specification. | C82: Lump Sum | D82: 1 | E82: 406887.11 | F82: =$D82*E82 -> 406887.11
A83: 2.043 | B83: Reinforced concrete pedestal for steel ladders as shown on drawing | C83: Lump Sum | D83: 1 | E83: 23456.377 | F83: =$D83*E83 -> 23456.377
A84: 2.044 | B84: Reinforced concrete foundation for LED Screen as shown on drawing | C84: Lump Sum | D84: 1 | E84: 30115.619 | F84: =$D84*E84 -> 30115.619
A85: 2.045 | B85: Reinforced concrete foundation for 14m light pole as shown on drawing | C85: Lump Sum | D85: 1 | E85: 100407.98 | F85: =$D85*E85 -> 100407.98
A86: 2.046 | B86: Concrete Paving including underneath layers all as specified and shown on drawings. | C86: Lump Sum | D86: 1 | E86: 35887.78 | F86: =$D86*E86 -> 35887.78
A87: 2.047 | B87: Concrete encasement for road crossing ducts for seweage pipes including all works and accroding to drawing | C87: Lump Sum | D87: 1 | E87: 3011.5619 | F87: =$D87*E87 -> 3011.5619
A88: 2.048 | B88: Supply of Concrete interlock concrete pedestrian paving block; Including sand bed. | C88: Lump Sum | D88: 1 | E88: 21919.152 | F88: =$D88*E88 -> 21919.152
A89: 2.049 | B89: Installation of Concrete interlock concrete pedestrian paving block; Including sand bed all as specified and shown on drawings. | C89: Lump Sum | D89: 1 | E89: 14612.768 | F89: =$D89*E89 -> 14612.768
A90: 2.05 | B90: Supply of Concrete interlock concrete vehicular paving block; Including sand bed. | C90: Lump Sum | D90: 1 | E90: 110730.11 | F90: =$D90*E90 -> 110730.11
A91: 2.051 | B91: Installation of Concrete interlock concrete vehicular paving block; Including sand bed all as specified and shown on drawings. | C91: Lump Sum | D91: 1 | E91: 73820.076 | F91: =$D91*E91 -> 73820.076
A92: 2.052 | B92: Supply of Kerbs, Wheel Stoppers all in accordance with drawing and specifications | C92: Lump Sum | D92: 1 | E92: 24134.657 | F92: =$D92*E92 -> 24134.657
... A95: 2.055 | B95: Installation of Chlorinated rubber based quick drying paint for kerbs applied in two coats to exposed faces of concrete kerbs and road separator; colour as per specification and as directed by the Engineer. | C95: Lump Sum | D95: 1 | E95: 12782.407 | F95: =$D95*E95 -> 12782.407
B96: NDRC
A97: 2.056 | B97: Supply and installation of Non-Destructive Road Crossing for potable water pipelines, including all necessary materials, equipment, and labor. The scope includes trenchless installation of ducts beneath existing roads or pavements without excavation, ensuring minimal disruption to traffic and surface conditions. Works involve laying, jointing, and pressure testing of ducts in compliance with potable water standards, project specifications, and safety regulations. | C97: Lump Sum | D97: 1 | E97: 16730.9 | F97: =$D97*E97 -> 16730.9
B98: Buildings
B99: Construct the buildings including excavation, backfilling, disposal of surplus material, anti-termite treatment, waterproofings, shoring works, plain cement concrete works, screed, reinforced concrete works, masonry works, metal works, internal finishes, external finishes, doors and windows, all necessary complete all as specified, as shown on the drawings and as per Engineer's approval.
A100: 2.057 | B100: Office Building | C100: Lump Sum | D100: 1 | E100: 1140740.3 | F100: =$D100*E100 -> 1140740.3
A101: 2.058 | B101: Guard Room, Operator Room & drivers toilet | C101: Lump Sum | D101: 1 | E101: 582687.88 | F101: =$D101*E101 -> 582687.88
A102: 2.059 | B102: Pump Room and MCC Room | C102: Lump Sum | D102: 1 | E102: 460466.98 | F102: =$D102*E102 -> 460466.98
B103: Gates, Fences and Barbed Wires
A104: 2.06 | B104: Supply Automatic Gate Barrier with Arm | C104: Lump Sum | D104: 1 | E104: 54208.115 | F104: =$D104*E104 -> 54208.115
A105: 2.061 | B105: Install Automatic Gate Barrier with Arm | C105: Lump Sum | D105: 1 | E105: 10038.54 | F105: =$D105*E105 -> 10038.54
B106: Removal, Refurbishment and Demolishing of Miscellaneous Objects
...

Sheet AL SAAD-Bill 03
B5: Bill No.3, Electrical Works
A6: Sl.No | B6: Description | C6: UNIT | D6: Quantity (Q) | E6: Unit Rate AED (A) | F6: Total Line Costs Ecxluding VAT B= AED (Q X A)
B7: Electrical
B8: LV Cable
A9: 3.001 | B9: Supply of LV Cables as per drawings and specifications | C9: Lump Sum | D9: 1 | E9: 52583.611 | F9: =$D9*E9 -> 52583.611
A10: 3.002 | B10: Installation of LV Cables as per drawings and specifications | C10: Lump Sum | D10: 1 | E10: 31550.167 | F10: =$D10*E10 -> 31550.167
B11: CAT 6 Cables
A12: 3.003 | B12: Supply of CAT 6 Cables as per drawings and specifications | C12: Lump Sum | D12: 1 | E12: 9841.7057 | F12: =$D12*E12 -> 9841.7057
A13: 3.004 | B13: Installation OF CAT 6 Cables as per drawings and specifications | C13: Lump Sum | D13: 1 | E13: 2206.471 | F13: =$D13*E13 -> 2206.471
B14: Ultrasonic Level Detectors
A15: 3.005 | B15: Supply of ultrasonic level detectors as per drawings and specifications | C15: Lump Sum | D15: 1 | E15: 20507.934 | F15: =$D15*E15 -> 20507.934
A16: 3.006 | B16: Installtion of ultrasonic level detectors as per drawings and specifications | C16: Lump Sum | D16: 1 | E16: 12304.76 | F16: =$D16*E16 -> 12304.76
B17: Induction Loop Cables
A18: 3.007 | B18: Supply of Induction Loop cables as per drawings and specifications | C18: Lump Sum | D18: 1 | E18: 8365.4498 | F18: =$D18*E18 -> 8365.4498
A19: 3.008 | B19: Installtion of Induction Loop cables as per drawings and specifications | C19: Lump Sum | D19: 1 | E19: 5019.2699 | F19: =$D19*E19 -> 5019.2699
B20: FOC Cables
A21: 3.009 | B21: Supply of FOC Cables as per drawings and specifications | C21: Lump Sum | D21: 1 | E21: 21331.897 | F21: =$D21*E21 -> 21331.897
A22: 3.01 | B22: Installation OF FOC Cables as per drawings and specifications | C22: Lump Sum | D22: 1 | E22: 12799.138 | F22: =$D22*E22 -> 12799.138
B23: uPVC Ducts
A24: 3.011 | B24: Supply of uPVC ducts including , end caps, draw ropes, aluminium duct marker, warning tapes, cable tiles etc;complete; as per drawings, specification and authority requirement | C24: Lump Sum | D24: 1 | E24: 29279.074 | F24: =$D24*E24 -> 29279.074
A25: 3.012 | B25: Installation of uPVC ducts including excavation, shuttering, reinforcement, concrete encasement, back filling, reinstatement, end caps, draw ropes, aluminium duct marker, warning tapes, cable tiles etc;complete; as per drawings, specification and authority requirement | C25: Lump Sum | D25: 1 | E25: 17567.445 | F25: =$D25*E25 -> 17567.445
B26: Road Crossing uPVC Ducts for LV, FOC & CAT Cables
A27: 3.013 | B27: Supply of uPVC ducts complete; as per drawings, specification and authority requirement | C27: Lump Sum | D27: 1 | E27: 20913.625 | F27: =$D27*E27 -> 20913.625
A28: 3.014 | B28: Installation of uPVC ducts including excavation, shuttering, reinforcement, concrete encasement, back filling, reinstatement, end caps, draw ropes, aluminium duct marker, warning tapes, cable tiles etc;complete; as per drawings, specification and authority requirement | C28: Lump Sum | D28: 1 | E28: 12548.175 | F28: =$D28*E28 -> 12548.175
B29: Manholes
A30: 3.015 | B30: Manholes including excavation, backfilling, concrete works, blinding and screeds connection joints and protection coating to all internal concrete surfaces, waterproofing, cover & frame, complete in all respect as detailed on drawing and as per specification | C30: Lump Sum | D30: 1 | E30: 88422.805 | F30: =$D30*E30 -> 88422.805
B31: Main Distribution Board (MDB)
A32: 3.016 | B32: Supply, Main Distribution Board(MDB) complete including enclosure, bus bars, circuit breakers, and insulators, complete all as specified and as shown on drawings. | C32: Lump Sum | D32: 1 | E32: 467481.02 | F32: =$D32*E32 -> 467481.02
A33: 3.017 | B33: Installed, connected, and tested, complete including enclosure, bus bars, circuit breakers, and insulators,complete all as specified and as shown on drawings. | C33: Lump Sum | D33: 1 | E33: 24604.264 | F33: =$D33*E33 -> 24604.264
B34: Distribution Board(DB)
A35: 3.018 | B35: Supply, Distribution board complete including enclosure, bus bars, circuit breakers, and insulators, complete all as specified and as shown on drawings. | C35: Lump Sum | D35: 1 | E35: 14762.559 | F35: =$D35*E35 -> 14762.559
A36: 3.019 | B36: Install, Distribution board connected, and tested, complete including enclosure, bus bars, circuit breakers, and insulators,complete all as specified and as shown on drawings. | C36: Lump Sum | D36: 1 | E36: 4173.021 | F36: =$D36*E36 -> 4173.021
B37: Single Pole and Neutral (SPN) Isolator 20A
A38: 3.02 | B38: Supply, Single Pole and Neutral (SPN) Isolator 20A complete all as specified and as shown on drawings. | C38: Lump Sum | D38: 1 | E38: 2509.635 | F38: =$D38*E38 -> 2509.635
A39: 3.021 | B39: Install, connected, and tested, Single Pole and Neutral (SPN) Isolator 20A complete all as specified and as shown on drawings. | C39: Lump Sum | D39: 1 | E39: 1505.781 | F39: =$D39*E39 -> 1505.781
B40: Capacitor Bank 20 KVAR
A41: 3.022 | B41: Supply, Capacitor Bank 20 KVAR complete all as specified and as shown on drawings. | C41: Lump Sum | D41: 1 | E41: 24604.264 | F41: =$D41*E41 -> 24604.264
A42: 3.023 | B42: Install, connected, and tested, Capacitor Bank 20 KVAR complete all as specified and as shown on drawings. | C42: Lump Sum | D42: 1 | E42: 9841.7057 | F42: =$D42*E42 -> 9841.7057
B43: Electrical Meter IP55 Metal Case Meter Enclosure Recessed on wall
A44: 3.024 | B44: Supply, Electrical Meter 83A IP55 Metal Case Meter Enclosure Recessed on wall complete all as specified and as shown on drawings. | C44: Lump Sum | D44: 1 | E44: 7381.2793 | F44: =$D44*E44 -> 7381.2793
A45: 3.025 | B45: Install, connected, and tested, Electrical Meter 83A IP55 Metal Case Meter Enclosure Recessed on wall complete all as specified and as shown on drawings. | C45: Lump Sum | D45: 1 | E45: 1455.5883 | F45: =$D45*E45 -> 1455.5883
B46: LED SCREEN including Foundation
A47: 3.026 | B47: Supply, LED SCREEN complete all as specified and as shown on drawings. | C47: Lump Sum | D47: 1 | E47: 9841.7057 | F47: =$D47*E47 -> 9841.7057
A48: 3.027 | B48: Install, connected, and tested, LED SCREEN complete all as specified and as shown on drawings. | C48: Lump Sum | D48: 1 | E48: 1279.9138 | F48: =$D48*E48 -> 1279.9138
B49: Telecommunication System
A50: 3.028 | B50: Supply UPVC ducts complete; as per drawings, specification and authority requirement | C50: Lump Sum | D50: 1 | E50: 3828.0298 | F50: =$D50*E50 -> 3828.0298
A51: 3.029 | B51: Installation of upvc ducts including excavation, back filling, reinstatement, end caps, draw ropes, aluminium duct marker, warning tapes etc;complete; as per drawings, specification and authority requirement | C51: Lump Sum | D51: 1 | E51: 2296.8179 | F51: =$D51*E51 -> 2296.8179
B52: Manholes / Joint Boxes
A53: 3.03 | B53: Construct Reinforced concrete Manholes complete including excavation, filling, Manhole concrete, formwork, water proofing, cover & frame etc. in accordance with drawings, specifications and authority requirements. | C53: Lump Sum | D53: 1 | E53: 88422.805 | F53: =$D53*E53 -> 88422.805
B54: Telecom Box
A55: 3.031 | B55: Supply, Telecom Box complete all as specified and as shown on drawings. | C55: Lump Sum | D55: 1 | E55: 33846.61 | F55: =$D55*E55 -> 33846.61
A56: 3.032 | B56: Install, connected, and tested, Telecom Box including Foundation complete all as specified and as shown on drawings. | C56: Lump Sum | D56: 1 | E56: 20307.966 | F56: =$D56*E56 -> 20307.966
B57: Main Distribution Frame (MDF)
A58: 3.033 | B58: Supply, Main Distribution Frame (MDF) complete all as specified and as shown on drawings. | C58: Lump Sum | D58: 1 | E58: 37644.524 | F58: =$D58*E58 -> 37644.524
A59: 3.034 | B59: Install, connected, and tested, Main Distribution Frame (MDF) including Foundation complete all as specified and as shown on drawings. | C59: Lump Sum | D59: 1 | E59: 22586.715 | F59: =$D59*E59 -> 22586.715
B60: ANPR Camera ( Part of Tanker Management System) ( Mounted Height 3M )
A61: 3.035 | B61: Supply, ANPR Camera ( Part of Tanker Management System) ( Mounted Height 3M ) complete all as specified and as shown on drawings. | C61: Lump Sum | D61: 1 | E61: 30078.811 | F61: =$D61*E61 -> 30078.811
A62: 3.036 | B62: Install, ANPR Camera ( Part of Tanker Management System) ( Mounted Height 3M ) complete all as specified and as shown on drawings. | C62: Lump Sum | D62: 1 | E62: 18047.287 | F62: =$D62*E62 -> 18047.287
B63: ANPR Camera Pole 3M Height
A64: 3.037 | B64: Supply, Camera Pole 3M Height complete all as specified and as shown on drawings. | C64: Lump Sum | D64: 1 | E64: 2927.9074 | F64: =$D64*E64 -> 2927.9074
A65: 3.038 | B65: Install, Camera Pole 3M Height including Foundation complete all as specified and as shown on drawings. | C65: Lump Sum | D65: 1 | E65: 1756.7445 | F65: =$D65*E65 -> 1756.7445
B66: Road Crossing uPVC Ducts for Telecommunication Network
A67: 3.039 | B67: Supply of uPVC ducts complete; as per drawings, specification and authority requirement | C67: Lump Sum | D67: 1 | E67: 24741.654 | F67: =$D67*E67 -> 24741.654
A68: 3.04 | B68: Installation of uPVC ducts including excavation, shuttering, reinforcement, concrete encasement, back filling, reinstatement, end caps, draw ropes, aluminium duct marker, warning tapes, cable tiles etc;complete; as per drawings, specification and authority requirement | C68: Lump Sum | D68: 1 | E68: 14844.993 | F68: =$D68*E68 -> 14844.993
B69: Area Lighting
A70: 3.041 | B70: Supply, Flood Light complete all as specified and as shown on drawings. | C70: Lump Sum | D70: 1 | E70: 23004.987 | F70: =$D70*E70 -> 23004.987
A71: 3.042 | B71: Install, connect, test Flood Light including complete all as specified and as shown on drawings. | C71: Lump Sum | D71: 1 | E71: 13802.992 | F71: =$D71*E71 -> 13802.992
A72: 3.043 | B72: Supply, Landscape Lighting Pull Box complete all as specified and as shown on drawings. | C72: Lump Sum | D72: 1 | E72: 8365.4498 | F72: =$D72*E72 -> 8365.4498
A73: 3.044 | B73: Install, connected, and tested, Landscape Lighting Pull Box complete all as specified and as shown on drawings. | C73: Lump Sum | D73: 1 | E73: 5019.2699 | F73: =$D73*E73 -> 5019.2699
A74: 3.045 | B74: Supply, Lighting Pole of height 14M including luminaries complete all as specified and as shown on drawings. | C74: Lump Sum | D74: 1 | E74: 60231.239 | F74: =$D74*E74 -> 60231.239
A75: 3.046 | B75: Install, connect and test Lighting Pole Height 14M including luminaries including foundation complete all as specified and as shown on drawings. | C75: Lump Sum | D75: 1 | E75: 36138.743 | F75: =$D75*E75 -> 36138.743
B76: Distribution Board (Area Lighting)
A77: 3.047 | B77: Supply,DB complete all as specified and as shown on drawings. | C77: Lump Sum | D77: 1 | E77: 2857.6377 | F77: =$D77*E77 -> 2857.6377
A78: 3.048 | B78: Installed, connected, and tested, DB complete including enclosure, bus bars, circuit breakers, and insulators, etc... complete all as specified and as shown on drawings. | C78: Lump Sum | D78: 1 | E78: 1714.5826 | F78: =$D78*E78 -> 1714.5826
B79: Road Crossing for Area lighting Cables
A80: 3.049 | B80: Supply UPVC ducts complete; as per drawings, specification and authority requirement | C80: Lump Sum | D80: 1 | E80: 7172.5367 | F80: =$D80*E80 -> 7172.5367
A81: 3.05 | B81: Installation of uPVC ducts including excavation, shuttering, reinforcement, concrete encasement, back filling, reinstatement, end caps, draw ropes, aluminium duct marker, warning tapes, cable tiles etc;complete; as per drawings, specification and authority requirement | C81: Lump Sum | D81: 1 | E81: 4303.522 | F81: =$D81*E81 -> 4303.522
B82: Buildings
A83: 3.051 | B83: MEP works for building includes Power, lighting, fire alarm, fire extinguishers, Emrgency Lighting, Earthing, HVAC & Drainage system; complete all as specified, as shown on the drawings and as per Engineer's approval. | C83: Lump Sum | D83: 1 | E83: 344459.7 | F83: =$D83*E83 -> 344459.7
B84: EVSDS
A85: 3.052 | B85: Supply LV EVSDS as per specification and Single Line Diagram approved by TAQA/TAQA complete with frequency converters, harmonic suppression equipment, etc. including witnessed factory tests all according to the TAQA/TAQA specifications, data sheets and drawings. | C85: No. | D85: 2 | E85: 123021.32 | F85: =$D85*E85 -> 246042.64
A86: 3.053 | B86: Install LV EVSDS as per specification and Single Line Diagram approved by TAQA/TAQA complete with frequency converters, harmonic suppression equipment, etc. all according to the TAQA/TAQA specifications, data sheets and drawings. | C86: No. | D86: 2 | E86: 54208.115 | F86: =$D86*E86 -> 108416.23
B87: LV DISTRIBUTION BOARD
A88: 3.054 | B88: Supply suitably rated distribution boards and sub-distribution boards as per approved single line diagram and specification with all accessories for the power supply to all the electrical and instrumentation loads in pump station as per TAQA/TAQA specification. | C88: Lump Sum | D88: 1 | E88: 49208.528 | F88: =$D88*E88 -> 49208.528
A89: 3.055 | B89: Install suitably rated distribution boards and sub-distribution boards as per approved single line diagram and specification with all accessories for the power supply to all the electrical and instrumentation loads in pump station as per TAQA/TAQA specification. | C89: Lump Sum | D89: 1 | E89: 9841.7057 | F89: =$D89*E89 -> 9841.7057
B90: LV SWITCHGEAR/MCC
A91: 3.056 | B91: Supply Low Voltage Switchboard/MCC including MCCBs, VFD, lighting distribution section, power factor correction equipment etc. complete with protection devices to feed all the electrical and instrument loads in the pump room and all the electrical loads connected to the LV Switchboard/MCC all according to the specifications, data sheet and drawings approved by TAQA Distribution. | C91: Lump Sum | D91: 1 | E91: 56589.808 | F91: =$D91*E91 -> 56589.808
A92: 3.057 | B92: Install, testing, and commissioning of the Low Voltage Switchboard/MCC, including mounting in its designated location, alignment, cable termination for all incoming and outgoing feeders (power and control), interconnection with field equipment, functional testing, and commissioning. | C92: Lump Sum | D92: 1 | E92: 14762.559 | F92: =$D92*E92 -> 14762.559
B93: LOCAL CONTROL PANELS
A94: 3.058 | B94: Supply of Local control panel for all the main pumpsets with overriding capability to the PS control system to operate the pump station in local remote including distributed I/O station for the main pump sets all according to the specifications, drawings and operation & control philosophy: | C94: No | D94: 1 | E94: 21050.818 | F94: =$D94*E94 -> 21050.818
A95: 3.059 | B95: Installation, testing, and commissioning of the Local Control Panel (LCP) and Distributed I/O station for main pump sets, including mounting, alignment, cable termination (power, signal, and communication), integration with field instruments and the main control system, and validation of local/remote control functionality. | C95: No | D95: 1 | E95: 12630.491 | F95: =$D95*E95 -> 12630.491
B96: FIELD INSTRUMENTS FOR PUMPSTATION, DISCHARGE PIPING AND SURGE VESSEL
A97: 3.06 | B97: Supply of field mounted pressure, temperature, speed, level and flow instruments complete with impulse lines, isolation valves, block and bleed valves, accessories, mounting racks, sun protection, enclosure boxes, JB, prefab cables etc. all according to specifications, finalized P&IDs, drawings and the operation and control philosophy. | C97: Lump Sum | D97: 1 | E97: 53120.606 | F97: =$D97*E97 -> 53120.606
A98: 3.061 | B98: Install, testing, and commissioning of field-mounted pressure, temperature, speed, level, and flow instruments, complete with associated impulse lines, isolation valves, block and bleed valves, mounting racks, sun protection covers, instrument enclosure boxes, JB, prefabricated signal cables, and all necessary accessories. | C98: Lump Sum | D98: 1 | E98: 31872.364 | F98: =$D98*E98 -> 31872.364
B99: COMMUNICATION SYSTEMS
B100: Communication equipment all according to the specifications and drawings, comprising but not limited to the following :
A101: 3.062 | B101: Supply of ETISALAT telephone system, including the EPABX alongwith the required number of extension at different location in the Pump Station including telephone sets and the provision for intercom, all as required. | C101: Lump Sum | D101: 1 | E101: 14639.537 | F101: =$D101*E101 -> 14639.537
A102: 3.063 | B102: Install, testing, and commissioning of the complete ETISALAT telephone system including the EPABX unit, telephone handsets, interconnecting cables, termination at designated extension points across the pump station and configuration of intercom features all in accordance with project specifications, approved drawings, and communication system requirements. | C102: Lump Sum | D102: 1 | E102: 8783.7223 | F102: =$D102*E102 -> 8783.7223
B103: JUNCTION BOXES/ENCLOSURES FOR INSTRUMENTS/EQUIPMENT INSIDE PUMPSTATION
A104: 3.064 | B104: Supply of junction boxes with sufficient terminals plus 30% spares to allow multicore cabling all according to specifications. | C104: Lump Sum | D104: 1 | E104: 24604.264 | F104: =$D104*E104 -> 24604.264
...

Sheet AL SAAD-Bill 04
B5: Bill No.4, CONSTRUCTION OF PIPELINES
A6: Sl.No | B6: Description | C6: UNIT | D6: Quantity (Q) | E6: Unit Rate AED (A) | F6: Total Line Costs Ecxluding VAT B= AED (Q X A)
B7: A- Construction of uPVC Pipeline
B8: Construct Upvc pipeline as specified complete include installation of detectable warning tapes and other accessories as per specification. Rates shall include all costs for commissioning and handing over in full commercial operation. For the following pipelines
B9: Upvc pipe line
A10: 4.001 | B10: Upvc pipe line for Storm Water Works | C10: Lump Sum | D10: 1 | E10: 1844.2203 | F10: =$D10*E10 -> 1844.2203
A11: 4.002 | B11: Upvc pipe line for Sewer Works | C11: Lump Sum | D11: 1 | E11: 805.57274 | F11: =$D11*E11 -> 805.57274
B12: DI Pipelines
B13: Construct the Ductile Iron (D.I) pipeline as per the approved specifications, including tie-in connection with the existing line using polyethylene sleeves and rubber gaskets, installation of detectable warning tapes, and all necessary accessories. The scope includes supply of all materials, labor, equipment, and consumables required for the complete installation, as well as testing for pressure and leakage, flushing, disinfection, commissioning, and handing over the system in full commercial operation. The quoted rates shall cover all associated costs to deliver a fully functional and operational pipeline in compliance with relevant standards and project requirements.
A14: 4.003 | B14: DI Pipelines | C14: Lump Sum | D14: 1 | E14: 62517.402 | F14: =$D14*E14 -> 62517.402
B15: Construction of PPR Pipeline
B16: Construct PPR pipeline using butt fusion method as specified complete include installation of detectable warning tapes and other accessories as per specification. Rates shall include all costs for testing, flushing, disinfection, commissioning and handing over in full commercial operation.
A17: 4.004 | B17: PPR pipe line | C17: Lump Sum | D17: 1 | E17: 894.87559 | F17: =$D17*E17 -> 894.87559
B18: Construction of HDPE Pipeline
B19: Construct the HDPE pipeline using the butt fusion method as per the approved specifications, complete with tie-in connections, installation of detectable warning tapes, and all necessary accessories. The scope shall include supply of all materials, equipment, and labor required for the complete installation. Rates shall cover all associated costs for testing, flushing, disinfection, commissioning, and handing over the system in full commercial operation, in compliance with project and industry standards.
A20: 4.005 | B20: HDPE pipeline | C20: Lump Sum | D20: 1 | E20: 9869.9325 | F20: =$D20*E20 -> 9869.9325
B21: Exta over item For pipeline construction items for installation of D.I, PPR, HDPE & uPVC fittings complete (such as restrained couplings, bends, tees, reducers, reducing flanges, Lange spigot pieces, flange socket pieces, quick dismantling joints, flanged adaptors, socket connectors, tied dismantling joints, blank flanges, double flanged extension pieces, adjustable S bends, duck foot elbows, flanged pipe pieces with anchor flange, transition pieces, collars, stepped couplings, and caps, restraining glands, etc.) for the following pipes:
B22: uPVC Fittings
A23: 4.006 | B23: uPVC pipe line for Storm Water Works | C23: Lump Sum | D23: 1 | E23: 2639.895 | F23: =$D23*E23 -> 2639.895
A24: 4.007 | B24: uPVC pipe line for Sewerage Works | C24: Lump Sum | D24: 1 | E24: 1157.544 | F24: =$D24*E24 -> 1157.544
B25: DI Pipelines
A26: 4.008 | B26: DI Pipelines | C26: Lump Sum | D26: 1 | E26: 96316.122 | F26: =$D26*E26 -> 96316.122
B27: PPR Pipelines
A28: 4.009 | B28: PPR Pipelines | C28: Lump Sum | D28: 1 | E28: 975.34453 | F28: =$D28*E28 -> 975.34453
B29: HDPE pipeline
A30: 4.01 | B30: HDPE pipeline | C30: Lump Sum | D30: 1 | E30: 12337.419 | F30: =$D30*E30 -> 12337.419
B31: Exta over item for pipeline construction for installation of flanged valves, gate valves, flowmeters, control valves, etc on DI 300mm pipe including all the accessories as per the specification.
A32: 4.011 | B32: Flow Meter Validation Unit | C32: Lump Sum | D32: 1 | E32: 37477.215 | F32: =$D32*E32 -> 37477.215
A33: 4.012 | B33: Settlement Type Electromagnetic Flow Meter | C33: Lump Sum | D33: 1 | E33: 34369.886 | F33: =$D33*E33 -> 34369.886
A34: 4.013 | B34: Control Valve Chamber | C34: Lump Sum | D34: 1 | E34: 26627.735 | F34: =$D34*E34 -> 26627.735
A35: 4.014 | B35: Gate Valve Chamber | C35: Lump Sum | D35: 1 | E35: 3011.93 | F35: =$D35*E35 -> 3011.93
A36: 4.015 | B36: Manual Butterfly Valve | C36: Lump Sum | D36: 1 | E36: 3724.5459 | F36: =$D36*E36 -> 3724.5459
A37: 4.016 | B37: Washout Valve | C37: Lump Sum | D37: 1 | E37: 2845.2836 | F37: =$D37*E37 -> 2845.2836
A38: 4.017 | B38: Air Release Valve | C38: Lump Sum | D38: 1 | E38: 5550.9377 | F38: =$D38*E38 -> 5550.9377
A39: 4.018 | B39: Manual Check Valve | C39: Lump Sum | D39: 1 | E39: 4389.9672 | F39: =$D39*E39 -> 4389.9672
B40: Service Connections
B41: Installation of Pipework for Service Connections
B42: Construct of New Tapping : Work includes Hand excavation, dewatring,and installation of new saddle strap & ferrule/pressure tapping tee with extra long outlet with all required fittings and supply of installation of moulding compound warping tap & polythene sleeve for protection of saddle & ferrule,backfilling and shutdown of distribution etc.all as per TAQA Specification.
A43: 4.019 | B43: Tapping in HDPE Main line | C43: Lump Sum | D43: 1 | E43: 8030.8318 | F43: =$D43*E43 -> 8030.8318
B44: Construct reinforced concrete encased Socket type uPVC DUCTS for the areas under car pass, for the proposed polyethylene house connection pipes, including the supply of uPVC pipe used for protection and all other materials complete with uPVC end cap at each duct end, duct end sealing, bituminous painting of concrete, excavation by hand, dewatering, backfilling and provision of 10 mm dia. pulling rope for installation of polyethylene house connection pipes etc. all as per TAQA Specification and Tender Drawings and as directed by TAQA/ENGINEER :
A45: 4.02 | B45: Reinforce concrete encasement for uPVC pipes for Storm Water Works | C45: Lump Sum | D45: 1 | E45: 18738.608 | F45: =$D45*E45 -> 18738.608
A46: 4.021 | B46: Reinforce concrete encasement for uPVC pipes for Sewerage Works | C46: Lump Sum | D46: 1 | E46: 16730.9 | F46: =$D46*E46 -> 16730.9
B47: Exta over item for pipeline construction for installation of flanged valves, gate valves, flowmeters, control valves, etc on HDPE 200mm pipe including all the accessories as per the specification.
A48: 4.022 | B48: Gate Valve Chamber | C48: Lump Sum | D48: 1 | E48: 16038.361 | F48: =$D48*E48 -> 16038.361
A49: 4.023 | B49: Flow Meter Validation Unit | C49: Lump Sum | D49: 1 | E49: 17172.99 | F49: =$D49*E49 -> 17172.99
A50: 4.024 | B50: Control Valve Chamber | C50: Lump Sum | D50: 1 | E50: 17305.345 | F50: =$D50*E50 -> 17305.345
A51: 4.025 | B51: Manual Butterfly Valve | C51: Lump Sum | D51: 1 | E51: 3496.1892 | F51: =$D51*E51 -> 3496.1892
A52: 4.026 | B52: Washout Valve | C52: Lump Sum | D52: 1 | E52: 3181.6081 | F52: =$D52*E52 -> 3181.6081
A53: 4.027 | B53: Air Release Valve | C53: Lump Sum | D53: 1 | E53: 5550.9377 | F53: =$D53*E53 -> 5550.9377
A54: 4.028 | B54: Manual Check Valve | C54: Lump Sum | D54: 1 | E54: 3496.2126 | F54: =$D54*E54 -> 3496.2126
B55: Total Costs for Bill No.4 excluding VAT (AED) | F55: =SUM(F10:F54) -> 417097.81

Sheet AL SAAD- Bill 05
B5: Bill No.5, INSTRUMENTATION AND CONTROL/ SCADA
A6: Sl.No | B6: Description | C6: UNIT | D6: Quantity (Q) | E6: Unit Rate AED (A) | F6: Total Line Costs Ecxluding VAT B= AED (Q X A)
B7: TANKER CONTROL SYSTEM/SCADA
B8: CONTROL SYSTEM
A9: 5.001 | B9: Dual system servers including but not limited to, CPU, HDD, keyboard mouse, DVDD, USB drive, software interface devices. | C9: No | D9: 1 | E9: 124949.7 | F9: =$D9*E9 -> 124949.7
A10: 5.002 | B10: Operator workstation including but not limited to, two computers each 21" LCD monitor, CPU, keyboard, mouse, interface devices, 2 GB RAM min., HDD, USB drive, DVDD etc. including one printer. | C10: No | D10: 1 | E10: 40667.798 | F10: =$D10*E10 -> 40667.798
A11: 5.003 | B11: Electronic cabinets including but not limited to, one dual redundant, PLC, communication and power supply modules, interface/signal/alarm etc. modules alongwith suitable communication equipment. | C11: No | D11: 1 | E11: 513387.66 | F11: =$D11*E11 -> 513387.66
A12: 5.004 | B12: Redundant secured communication network, bus and interfaces and other auxiliaries, as required | C12: Lump Sum | D12: 1 | E12: 115153.76 | F12: =$D12*E12 -> 115153.76
A13: 5.005 | B13: Software packages including but not limited to the original license including all application, engineering and HMI software, configuration software etc., as required. | C13: Lump Sum | D13: 1 | E13: 419627.69 | F13: =$D13*E13 -> 419627.69
A14: 5.006 | B14: Field Process Unit, which consists of flow computer with card reader, push buttons for Start / Stop, Emergency push button, lamps for indication, remote I/O module/ RTU | C14: No | D14: 4 | E14: 184262.42 | F14: =$D14*E14 -> 737049.67
A15: 5.007 | B15: Start / Stop Panel for Manual Tanker Filling Operation as specified | C15: No | D15: 4 | E15: 3588.778 | F15: =$D15*E15 -> 14355.112
A16: 5.008 | B16: Fiscal Ticket Printers for printing the prepaid cards etc. as required showing tanker information , volume and amount. To be installed in Customer Service Unit of the office building | C16: No | D16: 2 | E16: 29513.307 | F16: =$D16*E16 -> 59026.614
A17: 5.009 | B17: Supply and Install A3 & A4 printer | C17: Lump Sum | D17: 1 | E17: 7968.9275 | F17: =$D17*E17 -> 7968.9275
A18: 5.01 | B18: Supply and Install UPS as required | C18: Lump Sum | D18: 1 | E18: 119528.89 | F18: =$D18*E18 -> 119528.89
B19: CONTROL SYSTEM FOR PUMP STATION
B20: Supply Control System, RTU/PLC with HMI to be connected to Tanker Filling Station main SCADA complete with witnessed factory tests all according to the specifications, data sheets, drawings and process & control philosophy, comprising but not limited to the following :
A21: 5.009 | B21: Consoles, 2 telephone sets and all auxiliaries. | C21: Lump Sum | D21: 1 | E21: 79685.929 | F21: =$D21*E21 -> 79685.929
A22: 5.011 | B22: Distributed I/O modules with enclosures connected to hot standby PLC for Tanker Filling Station | C22: Lump Sum | D22: 1 | E22: 373835.22 | F22: =$D22*E22 -> 373835.22
A23: 5.012 | B23: Redundant communication network, bus and interfaces and other auxiliaries, as required | C23: Lump Sum | D23: 1 | E23: 39842.964 | F23: =$D23*E23 -> 39842.964
B24: LEVEL SWITCHES | F24: 0
A25: 5.013 | B25: Supply of level switches of suitable type for tanker overflow detection complete with cable and other installation accessories to be installed on the filling hose. | C25: No. | D25: 4 | E25: 14221.265 | F25: =$D25*E25 -> 56885.059
A26: 5.014 | B26: ACCESS CONTROL SYSTEM
A27: 5.015 | B27: Proximity Card Reader Unit / including all accessories required for installing at the entrance of the station, complete with power supply unit, modules etc and all other accessories as required for communication to centralised loading system PLC. | C27: No | D27: 2 | E27: 99607.411 | F27: =$D27*E27 -> 199214.82
A28: 5.016 | B28: Motorised boom including warning beacons, audible alram and all other accessries, to be installed at the entrance and exit of the station as required including interfaces with the loading system PLC. | C28: No | D28: 2 | E28: 119528.89 | F28: =$D28*E28 -> 239057.79
A29: 5.017 | B29: Display units for bay identifcation and driver information including all required accessories and interfaces. | C29: No | D29: 6 | E29: 39842.964 | F29: =$D29*E29 -> 239057.79
B30: SPARE PARTS FOR I & C SYSTEM & F.O CABLE
B31: SPARE FOR THE FIELD INSTRUMENTS
A32: 5.018 | B32: Electromagnetic flowmeter transmitter. | C32: No | D32: 1 | E32: 39707.444 | F32: =$D32*E32 -> 39707.444
A33: 5.019 | B33: Pressure transmitter (One from each range selected) | C33: No | D33: 1 | E33: 7528.9049 | F33: =$D33*E33 -> 7528.9049
A34: 5.02 | B34: Differential pressure switch, one no. for the highest range selected. | C34: No | D34: 1 | E34: 11910.727 | F34: =$D34*E34 -> 11910.727
A35: 5.021 | B35: Pressure gauge, one no. for each range selected. | C35: No | D35: 1 | E35: 1425.4727 | F35: =$D35*E35 -> 1425.4727
A36: 5.022 | B36: Level Switches | C36: No | D36: 1 | E36: 8345.3728 | F36: =$D36*E36 -> 8345.3728
B37: SPARES FOR CONTROL AND SCADA SYSTEM
A38: 5.023 | B38: The number of spare equipment modules shall be 5% of the installed units, rounded upto the nearest integer i.e. CPU, CP, power supply modules, I/O modules of each type, bus controller, fibre optic interfaace modules, all communication device and modules etc. alongwith 10% spare hardware accessories like relays, batteries, MCB's, etc, and EPROM/EEPROM shall be 2 minimum of each type. | C38: Lump Sum | D38: 1 | E38: 239057.79 | F38: =$D38*E38 -> 239057.79
B39: SPARE FOR F.O. CABLE SYSTEM
A40: 5.024 | B40: Fibre optical splicing kit, 1 set for tap off location. | C40: Lump Sum | D40: 1 | E40: 103296.57 | F40: =$D40*E40 -> 103296.57
A41: 5.025 | B41: 10% minimum F.O. interfacing module/component of each type installed at the F.O. system cabinet/panel including interfacing module, power supply module, patch panel etc. | C41: Lump Sum | D41: 1 | E41: 44269.961 | F41: =$D41*E41 -> 44269.961
A42: 5.026 | B42: Recommended consumables for 2 years trouble free operation | C42: Lump Sum | D42: 1 | E42: 44269.961 | F42: =$D42*E42 -> 44269.961
A43: 5.027 | B43: SCADA System Integration with existing main SCADA and Customer care and Billing System ( CC&B) | C43: Lump Sum | D43: 1 | E43: 49208.528 | F43: =$D43*E43 -> 49208.528
B44: Total Costs for Bill No.5 excluding VAT (AED) | F44: =SUM(F9:F43) -> 3928316.1

Sheet SWEIHAN-Summary 
B5: SUMMARY SHEET - SWEIHAN
A6: Bill No. | B6: Description | C6: Total Costs Excluding VAT (AED)
A7: 1 | B7: SUPPLY OF PIPEWORKS | C7: ='SWEIHAN-Bill 01'!F49 -> 1060736.6
A8: 2 | B8: CIVIL WORKS | C8: ='SWEIHAN-Bill 02'!F119 -> 4633003.3
A9: 3 | B9: ELECTRICAL WORKS | C9: ='SWEIHAN-Bill 03'!F119 -> 2457049.5
A10: 4 | B10: CONSTRUCTION OF PIPELINES | C10: ='SWEIHAN-Bill 04'!F46 -> 423263.16
A11: 5 | B11: INSTRUMENTATION AND CONTROL/ SCADA | C11: ='SWEIHAN-Bill 05'!F44 -> 3958204.2
B13: Total Costs Excluding VAT ( AED) | C13: =SUM(C7:C11) -> 12532257
B14: Total Value Added Tax (VAT/5%) (AED) | C14: =C13*0.05 -> 626612.84
B15: Total Costs Including VAT (AED) | C15: =SUM(C13:C14) -> 13158870
B18: Total Costs in Words Excluding VAT (AED): | C18: Dirhams Twelve million, five hundred thirty-two thousand, two hundred fifty-six and seventy-two Fils
B19: VAT Amount in Words (AED): | C19: Dirhams Six hundred twenty-six thousand, six hundred twelve and eighty-four Fils
B20: Total Costs in Words Including VAT (AED): | C20: Dirhams Thirteen million, one hundred fifty-eight thousand, eight hundred sixty-nine and fifty-sixFils

Sheet SWEIHAN-Bill 01
B5: Bill No.1, SUPPLY OF PIPEWORKS
A6: Sl.No | B6: Description | C6: UNIT | D6: Quantity (Q) | E6: Unit Rate AED (A) | F6: Total Line Costs Ecxluding VAT B= AED (Q X A)
B7: Storm Water Works
A8: 1.001 | B8: Supply the following ISO standard uPVC including warning tape and all other accessories as per ADEWA standard specifications | C8: Lump Sum | D8: 1 | E8: 6102.458 | F8: =$D8*E8 -> 6102.458
B9: Gully Trap
A10: 1.002 | B10: Supply the following ISO standard Gully trap including all other accessories as per ADEWA standard specifications | C10: Lump Sum | D10: 1 | E10: 225.86715 | F10: =$D10*E10 -> 225.86715
B11: Potable Water Works
B12: Ductile Iron (DI) Pipe
B13: Supply and Install DI pipe as specified complete with installation of detectable warning tapes and other accessories all in accordance with TAQA standard specification, data sheet and drawings.
A14: =MAX(A7:A13)+0.001 -> 1.003 | B14: DI - Standard Socket Spigot pipes | C14: Lump Sum | D14: 1 | E14: 85426.685 | F14: =$D14*E14 -> 85426.685
A15: 1.003a | B15: DI - Restrained | C15: Lump Sum | D15: 1 | E15: 85426.685 | F15: =$D15*E15 -> 85426.685
B16: Sewerage Works
A17: =MAX(A8:A16)+0.001 -> 1.004 | B17: Supply the following ISO standard uPVC including warning tape and all other accessories as per ADEWA standard specifications | C17: Lump Sum | D17: 1 | E17: 2480.2767 | F17: =$D17*E17 -> 2480.2767
B18: Gully for Sewerage Pipes
A19: =MAX(A10:A18)+0.001 -> 1.005 | B19: Supply the following ISO standard Gully trap including warning tape and all other accessories as per ADEWA standard specifications | C19: Lump Sum | D19: 1 | E19: 225.86715 | F19: =$D19*E19 -> 225.86715
B20: Gate Valves
A21: =MAX(A12:A20)+0.001 -> 1.006 | B21: Supply of PN 16 Manual Gate Valves above ground in inaccordance with specification, drawings and data sheet. | C21: Lump Sum | D21: 1 | E21: 66881.268 | F21: =$D21*E21 -> 66881.268
B22: Check Valves
A23: =MAX(A14:A22)+0.001 -> 1.007 | B23: Supply of Check Valves above ground in inaccordance with specification, drawings and data sheet. | C23: Lump Sum | D23: 1 | E23: 6584.953 | F23: =$D23*E23 -> 6584.953
B24: Bulk Connection Chamber Valves & Fittings
A25: =MAX(A16:A24)+0.001 -> 1.008 | B25: Supply of Manual Check Valves & Fittings in accordance with specification, drawings and data sheet. | C25: Lump Sum | D25: 1 | E25: 8268.115 | F25: =$D25*E25 -> 8268.115
A26: =MAX(A17:A25)+0.001 -> 1.009 | B26: Supply of Manual Butterfly Valves & Fittings in accordance with specification, drawings and data sheet. | C26: Lump Sum | D26: 1 | E26: 5586.8172 | F26: =$D26*E26 -> 5586.8172
A27: =MAX(A18:A26)+0.001 -> 1.01 | B27: Supply of Settlement Type Electromagnetic Flow Meter & Fittings on 300mm dia line in accordance with specification, drawings and data sheet. | C27: Lump Sum | D27: 1 | E27: 60811.993 | F27: =$D27*E27 -> 60811.993
A28: =MAX(A19:A27)+0.001 -> 1.011 | B28: Supply of Control Valve & Fittings in accordance with specification, drawings and data sheet. | C28: Lump Sum | D28: 1 | E28: 39941.6 | F28: =$D28*E28 -> 39941.6
B29: Bip Tap
A30: =MAX(A21:A29)+0.001 -> 1.012 | B30: Supply of BIP TAP including all fittings and accessories | C30: Lump Sum | D30: 1 | E30: 451.73429 | F30: =$D30*E30 -> 451.73429
B31: Flow Meter Validation Unit
A32: =MAX(A23:A31)+0.001 -> 1.013 | B32: Supply flow meter validation unit with validation software all as per specifications. The unit shall be supplied with power supply with rechargeable batteries and integral charger unit. | C32: Lump Sum | D32: 1 | E32: 32123.327 | F32: =$D32*E32 -> 32123.327
B33: Flow Control Valve
A34: 1.013a | B34: Supply a flow control valve for the above-ground (vertical pipeline) validation unit, complete with validation software, in full compliance with the project specifications. The unit shall include a power supply with rechargeable batteries and an integral charging unit, ensuring continuous and reliable operation. All components shall be suitable for the intended application and delivered ready for installation and commissioning. | C34: Lump Sum | D34: 1 | E34: 45605.276 | F34: =$D34*E34 -> 45605.276
B35: Electromagnetic Flow Meter
A36: =MAX(A27:A35)+0.001 -> 1.014 | B36: Supply of 8" flow meter. all in accordance with specification, data sheet and drawings. | C36: Lump Sum | D36: 1 | E36: 124228.94 | F36: =$D36*E36 -> 124228.94
B37: PPR Pipes
A38: =MAX(A29:A37)+0.001 -> 1.015 | B38: Supply , PPR 20-25mm pipes Including valves and chambers all as specified and shown on drawings. | C38: Lump Sum | D38: 1 | E38: 3642.7753 | F38: =$D38*E38 -> 3642.7753
B39: Flexible hoses
A40: =MAX(A31:A39)+0.001 -> 1.016 | B40: Supply of PN 16 Flexible hoses of sufficient length, with one end flanged and necessary attachments including fasteners, gaskets etc. for filling bays as specified. | C40: Lump Sum | D40: 1 | E40: 25932.894 | F40: =$D40*E40 -> 25932.894
B41: HDPE Pipes
A42: =MAX(A33:A41)+0.001 -> 1.017 | B42: Supply and Testing of HDPE pipes Including valves and chambers all as specified and shown on drawings. | C42: Lump Sum | D42: 1 | E42: 18069.372 | F42: =$D42*E42 -> 18069.372
B43: Water booster set
B44: Water booster set, with two or three vertical multi-stage pumps as shown on drawings, control box, skid mounted, installed, connected and tested complete with stainless steel headers, pump individual isolating ball valves, check valves, isolating butterfly valves PN 20, lug and wafer type lever operated, strainer cast iron body PN 20, flexible connections, concrete inertia pad, house pad, vibration eliminator pad, low level control float switches, local control panel, pressure switch and controls all supplied from pump manufacturer diaphragm tank (s), food quality synthetic rubber membrane, steel painted body, working pressure 10 bars with isolating valve and pressure gauge, electric connections, wiring and accessories all as specified and shown on the drawings.
A45: =MAX(A36:A44)+0.001 -> 1.018 | B45: Pump Capacity 80 l/s @ 2Bar(1 Duty + 1 Standby) | C45: Lump Sum | D45: 1 | E45: 429679.67 | F45: =$D45*E45 -> 429679.67
B46: Domestic water pump set
B47: Domestic water pump set for building, with single stage pumps and pressure vessel as shown on drawings, control box, skid mounted, installed, connected and tested complete with stainless steel headers, pump individual isolating ball valves, check valves, isolating butterfly valves PN 20, lug and wafer type lever operated, strainer cast iron body PN 20, flexible connections, concrete inertia pad, house pad, vibration eliminator pad, low level control float switches, pressure switch and controls all supplied from pump manufacturer diaphragm tank (s), food quality synthetic rubber membrane, steel painted body, working pressure 2 bars with isolating valve and pressure gauge, electric connections, wiring and accessories all as specified and shown on the drawings.
A48: =MAX(A39:A47)+0.001 -> 1.019 | B48: Water pump set 1 duty + 1 standby 1.0 L/S @30m head each pump | C48: Lump Sum | D48: 1 | E48: 13040.063 | F48: =$D48*E48 -> 13040.063
B49: Total Costs for Bill No.1 excluding VAT (AED) | F49: =SUM(F8:F48) -> 1060736.6

Sheet SWEIHAN-Bill 02
B5: Bill No.2, CIVIL WORKS
A6: Sl.No | B6: Description | C6: UNIT | D6: Quantity (Q) | E6: Unit Rate AED (A) | F6: Total Line Costs Ecxluding VAT B= AED (Q X A)
B7: Trial trench and Trial pits
A8: 2.001 | B8: Trial trench and Trial pits | C8: Lump Sum | D8: 1 | E8: 6512.0008 | F8: =$D8*E8 -> 6512.0008
B9: Trenches for Pipelines
B10: Excavate and Backfill Trenches for Pipelines
B11: Excavate, dewater and backfill trenches for pipelines including shoring, surveying, etc. for a maximum cover to pipelines of 1.2 m as per specification and as shown in drawings for the following sizes of pipelines
B12: PPR Pipelines
A13: 2.002 | B13: PPR Pipelines | C13: Lump Sum | D13: 1 | E13: 68665.581 | F13: =$D13*E13 -> 68665.581
B14: DI Pipelines
A15: 2.003 | B15: DI Pipelines | C15: Lump Sum | D15: 1 | E15: 172313.5 | F15: =$D15*E15 -> 172313.5
B16: HDPE Pipelines
A17: 2.004 | B17: HDPE Pipelines | C17: Lump Sum | D17: 1 | E17: 43520.023 | F17: =$D17*E17 -> 43520.023
B18: uPVC Pipelines for Storm Water Works
A19: 2.005 | B19: uPVC Pipelines | C19: Lump Sum | D19: 1 | E19: 20731.553 | F19: =$D19*E19 -> 20731.553
B20: uPVC Pipelines for Sewerage Works
A21: 2.006 | B21: uPVC Pipelines | C21: Lump Sum | D21: 1 | E21: 23752.957 | F21: =$D21*E21 -> 23752.957
B22: E.O.I for Excavate and Backfill Trenches for Pipelines
B23: E.O.I. for excavation of every additional 500 mm excavation depth exceeding 1.2 m cover, including dewatering, shoring, backfilling and disposal of surplus material all as per specification for the following pipelines
B24: PPR Pipelines
A25: 2.007 | B25: PPR Pipelines | C25: Lump Sum | D25: 1 | E25: 4920.8528 | F25: =$D25*E25 -> 4920.8528
B26: uPVC Pipelines for Storm Water Works
A27: 2.008 | B27: uPVC Pipelines | C27: Lump Sum | D27: 1 | E27: 4920.8528 | F27: =$D27*E27 -> 4920.8528
B28: uPVC Pipelines for Sewerage Works
A29: 2.009 | B29: uPVC Pipelines | C29: Lump Sum | D29: 1 | E29: 4920.8528 | F29: =$D29*E29 -> 4920.8528
B30: HDPE Pipelines
A31: 2.01 | B31: HDPE Pipelines | C31: Lump Sum | D31: 1 | E31: 4920.8528 | F31: =$D31*E31 -> 4920.8528
B32: DI Pipelines
A33: 2.011 | B33: DI Pipelines | C33: Lump Sum | D33: 1 | E33: 4920.8528 | F33: =$D33*E33 -> 4920.8528
A34: 2.012 | B34: E.O.I for excavation in rock using rock breaker including disposal of excavated material as per the Municipality requirements - the rock should be classified as per specs by lab test | C34: Lump Sum | D34: 1 | E34: 4920.8528 | F34: =$D34*E34 -> 4920.8528
A35: 2.013 | B35: E.O.I. for supply, place and compact aPPRoved imported bedding / fill material/gatch including disposal of surplus material as per specifications and as ordered and authorized by TAQA Engineer | C35: Lump Sum | D35: 1 | E35: 4920.8528 | F35: =$D35*E35 -> 4920.8528
A36: 2.014 | B36: General excavation for any other purpose including dewatering, backfilling as required or instructed by TAQA Engineer. | C36: Lump Sum | D36: 1 | E36: 20160.734 | F36: =$D36*E36 -> 20160.734
B37: Construction of Manholes and Facilities at Pipelines for Storm Water Works
A38: 2.015 | B38: Manholes including excavation, dewatering, shoring, backfilling, concrete works including the Removable cover slab, benching, blinding and screeds connection joints and protection coating to all internal concrete surfaces, waterproofing , tanking , heavy duty ductile cover & frame, complete in all respect as detailed on drawing and as per specification | C38: Lump Sum | D38: 1 | E38: 91380.237 | F38: =$D38*E38 -> 91380.237
B39: Construction of Manholes and Facilities at Pipelines for Sewer Works
A40: 2.016 | B40: Manholes including excavation, dewatering, shoring, backfilling, concrete works including the Removable cover slab, benching, blinding and screeds connection joints and protection coating to all internal concrete surfaces, waterproofing , tanking , heavy duty ductile cover & frame, complete in all respect as detailed on drawing and as per specification | C40: Lump Sum | D40: 1 | E40: 184822.31 | F40: =$D40*E40 -> 184822.31
A41: 2.017 | B41: Construction of Concrete support (thrust blocks) for fittngs including reinforcement, formwork, backfilling etc. as per authority requirements, specifications and drawings | C41: Lump Sum | D41: 1 | E41: 40843.079 | F41: =$D41*E41 -> 40843.079
B42: Soakaway
A43: 2.018 | B43: Construction of Soakaway | C43: Lump Sum | D43: 1 | E43: 13906.33 | F43: =$D43*E43 -> 13906.33
A44: 2.019 | B44: Construction Storm water channels excavation, dewatering, shoring, backfilling, concrete works including the gratings complete in all respect as detailed on drawing and as per specification | C44: Lump Sum | D44: 1 | E44: 49618.575 | F44: =$D44*E44 -> 49618.575
B45: Backdrops
A46: 2.02 | B46: Construction of Backdrop complete with concrete surround as per SWS standard drawing | C46: Lump Sum | D46: 1 | E46: 26572.605 | F46: =$D46*E46 -> 26572.605
B47: Proposed Road Crossing Ducts
A48: 2.020a | B48: Supply and installation of HDPE ducts for road crossing, including reinforced concrete surround and all associated works such as excavation, duct laying, concrete casting, backfilling, compaction, and testing, all as per drawings and specifications | C48: Lump Sum | D48: 1 | E48: 11947.831 | F48: =$D48*E48 -> 11947.831
B49: Construction of Chambers, and Facilities at Pipelines
B50: Construction of Concrete Chambers
B51: Construct reinforced concrete chambers, as per TAQA's standard specification with precast cover slab for chambers on pipelines including the supply of all materials complete with protection board and water proofing of outside walls from top to bottom water stop at construction joints, installation of hot dipped galvanized lifting hooks in cover slab, supports for valve spindle extension casting in of anchor flange sealing flange (water stop),access cover frame, surface box, chamber indication plate owner information plate ventilation pipes bolting of aluminum ladder excavation dewatering, backfilling, etc., all as per specification and as shown on tender drawings (for lifting hooks, ladder, vent pipes, chamber protection & water stop) all as directed and authorized by TAQA Engineer (not include supply of pipework inside chambers)
A52: 2.021 | B52: Gate Valve Chamber (s) as per Drawing | C52: Lump Sum | D52: 1 | E52: 21651.753 | F52: =$D52*E52 -> 21651.753
A53: 2.022 | B53: Flow Meter Chamber (s) as per Drawings | C53: Lump Sum | D53: 1 | E53: 21651.753 | F53: =$D53*E53 -> 21651.753
A54: 2.023 | B54: Control Valve Chamber (s) as per Drawing | C54: Lump Sum | D54: 1 | E54: 21651.753 | F54: =$D54*E54 -> 21651.753
A55: 2.024 | B55: Bulk Connection Chamber (s) as per Drawings | C55: Lump Sum | D55: 1 | E55: 30017.202 | F55: =$D55*E55 -> 30017.202
A56: 2.025 | B56: Check Valve Chamber (s) as per Drawings | C56: Lump Sum | D56: 1 | E56: 21651.753 | F56: =$D56*E56 -> 21651.753
A57: 2.026 | B57: Manual Check Valve Chamber (s) as per Drawings | C57: Lump Sum | D57: 1 | E57: 21651.753 | F57: =$D57*E57 -> 21651.753
B58: GRP Tank
A59: 2.027 | B59: Supply, GRP tank glass reinforced plastic construction, GRP panel not less than 8mm, insulation 25mm, all as specified and shown on drawings. | C59: Lump Sum | D59: 1 | E59: 10629.042 | F59: =$D59*E59 -> 10629.042
A60: 2.028 | B60: Install,test and commissioning GRP tank glass reinforced plastic construction, GRP panel not less than 8mm, insulation 25mm, all as specified and shown on drawings. | C60: Lump Sum | D60: 1 | E60: 10050.547 | F60: =$D60*E60 -> 10050.547
B61: Structural Steel Column for Ladder Support
A62: =MAX(A51:A61)+0.001 -> 2.029 | B62: Supply, fabrication, and installation of structural steel column for ladder support, including all required base plates, anchor bolts, connections, welding, surface treatment, and complete erection at site. Works shall be carried out as per approved drawings, specifications, and relevant standards. All associated materials, labor, equipment, and coordination are to be included to complete the item in all respects. | C62: Lump Sum | D62: 1 | E62: 58030.54 | F62: =$D62*E62 -> 58030.54
B63: Steel Ladders
A64: 2.031 | B64: Supply and Install Steel adjustable ladder including supporting frame, shade and hand rail as shown on drawing | C64: Lump Sum | D64: 1 | E64: 47104.091 | F64: =$D64*E64 -> 47104.091
B65: Car Parking Shed
A66: 2.032 | B66: Car Parking Shed including post, foundation and designated signages all as specified and shown on drawings. | C66: Lump Sum | D66: 1 | E66: 33461.799 | F66: =$D66*E66 -> 33461.799
B67: Garbage Containers
A68: 2.033 | B68: Garbage containers and bins with lid all as specified and shown on drawings. | C68: Lump Sum | D68: 1 | E68: 2710.4057 | F68: =$D68*E68 -> 2710.4057
B69: Road Surface Markings
B70: Surface markings
A71: 2.034 | B71: In accordance with Traffic Control Devices Manual on uniform traffic control devices TR-511 Surface markings including all necessary preparation works, etc.; all in accordance with Road Markings Plan drawings and specifications | C71: Lump Sum | D71: 1 | E71: 6451.4349 | F71: =$D71*E71 -> 6451.4349
B72: Traffic Signs
A73: 2.035 | B73: Supply In accordance with Traffic Control Devices Manual Second Edition September 2020 of Abu Dhabi City Municipality Warning and Regulatory Sign and Posts etc.; all in accordance with Traffic Device Plan drawings and Specification | C73: Lump Sum | D73: 1 | E73: 13250.873 | F73: =$D73*E73 -> 13250.873
A74: 2.036 | B74: Install In accordance with Traffic Control Devices Manual Second Edition September 2020 of Abu Dhabi City Municipality Warning and Regulatory Sign and Posts including all necessary civil works, etc.; all in accordance with Traffic Device Plan drawings and Specification | C74: Lump Sum | D74: 1 | E74: 8833.915 | F74: =$D74*E74 -> 8833.915
B75: Concrete Works
A76: 2.037 | B76: Reinforced concrete Coloumn including Concrete foundation, Aluminum Cladding, Steel Truss, Tension cables, 40mm mild steel painted hollow section, lighting, telephone etc as shown on drawing and as per specification. | C76: Lump Sum | D76: 1 | E76: 111844.39 | F76: =$D76*E76 -> 111844.39
A77: 2.038 | B77: Reinforced concrete pedestal for steel ladders as shown on drawing | C77: Lump Sum | D77: 1 | E77: 20868.117 | F77: =$D77*E77 -> 20868.117
A78: 2.039 | B78: Concrete Paving including underneath layers all as specified and shown on drawings. | C78: Lump Sum | D78: 1 | E78: 522688.36 | F78: =$D78*E78 -> 522688.36
A79: 2.04 | B79: Reinforced concrete foundation for LED Screen as shown on drawing | C79: Lump Sum | D79: 1 | E79: 30115.619 | F79: =$D79*E79 -> 30115.619
A80: 2.041 | B80: Reinforced concrete foundation for 14m light pole as shown on drawing | C80: Lump Sum | D80: 1 | E80: 273236.2 | F80: =$D80*E80 -> 273236.2
A81: 2.042 | B81: Supply of Concrete interlock concrete pedestrian paving block; Including sand bed. | C81: Lump Sum | D81: 1 | E81: 38206.682 | F81: =$D81*E81 -> 38206.682
A82: 2.043 | B82: Installation of Concrete interlock concrete pedestrian paving block; Including sand bed all as specified and shown on drawings. | C82: Lump Sum | D82: 1 | E82: 25471.122 | F82: =$D82*E82 -> 25471.122
A83: 2.044 | B83: Supply of Concrete interlock concrete vehicular paving block; Including sand bed. | C83: Lump Sum | D83: 1 | E83: 192097.5 | F83: =$D83*E83 -> 192097.5
A84: 2.045 | B84: Installation of Concrete interlock concrete vehicular paving block; Including sand bed all as specified and shown on drawings. | C84: Lump Sum | D84: 1 | E84: 128065 | F84: =$D84*E84 -> 128065
A85: 2.046 | B85: Supply of Kerbs, Wheel Stoppers all in accordance with drawing and specifications | C85: Lump Sum | D85: 1 | E85: 21750.504 | F85: =$D85*E85 -> 21750.504
A86: 2.047 | B86: Installation of Kerbs, Wheel stoppers complete including excavation, concrete foundation and haunching, cement mortar and backfilling (where required) etc. ; all in accordance with drawing and specifications | C86: Lump Sum | D86: 1 | E86: 14500.336 | F86: =$D86*E86 -> 14500.336
A87: 2.048 | B87: Supply of Chlorinated rubber based paint for kerb, colour as per specification and as directed by the Engineer. | C87: Lump Sum | D87: 1 | E87: 21177.304 | F87: =$D87*E87 -> 21177.304
A88: 2.049 | B88: Installation of Chlorinated rubber based quick drying paint for kerbs applied in two coats to exposed faces of concrete kerbs and road separator; colour as per specification and as directed by the Engineer. | C88: Lump Sum | D88: 1 | E88: 11765.169 | F88: =$D88*E88 -> 11765.169
B89: Buildings
B90: Construct the buildings including excavation, backfilling, disposal of surplus material, anti-termite treatment, waterproofings, shoring works, plain cement concrete works, screed, reinforced concrete works, masonry works, metal works, internal finishes, external finishes, doors and windows, all necessary complete all as specified, as shown on the drawings and as per Engineer's approval.
A91: 2.05 | B91: Office Building | C91: Lump Sum | D91: 1 | E91: 586904.82 | F91: =$D91*E91 -> 586904.82
A92: 2.051 | B92: Guard Room, Operator Room & drivers toilet | C92: Lump Sum | D92: 1 | E92: 278082.61 | F92: =$D92*E92 -> 278082.61
A93: 2.052 | B93: Pump Room and MCC Room | C93: Lump Sum | D93: 1 | E93: 308022.56 | F93: =$D93*E93 -> 308022.56
B94: Gates, Fences and Barbed Wires
A95: 2.053 | B95: Supply Automatic Gate Barrier with Arm | C95: Lump Sum | D95: 1 | E95: 54208.115 | F95: =$D95*E95 -> 54208.115
A96: 2.054 | B96: Install Automatic Gate Barrier with Arm | C96: Lump Sum | D96: 1 | E96: 10038.54 | F96: =$D96*E96 -> 10038.54
A97: 2.055 | B97: Supply Barbed wire 1m length | C97: Lump Sum | D97: 1 | E97: 10038.54 | F97: =$D97*E97 -> 10038.54
A98: 2.056 | B98: Install Barbed wire 1m length | C98: Lump Sum | D98: 1 | E98: 3346.1799 | F98: =$D98*E98 -> 3346.1799
B99: Removal, Refurbishment and Demolishing of Miscellaneous Objects
B100: Demolition
A101: 2.057 | B101: Removal of existing trees and dispose to approved tip. | C101: Lump Sum | D101: 1 | E101: 17567.445 | F101: =$D101*E101 -> 17567.445
A102: 2.058 | B102: Demolition of Existing 2.1m Boundary wall including foundation and dispose to approved tip. | C102: Lump Sum | D102: 1 | E102: 200101.56 | F102: =$D102*E102 -> 200101.56
A103: 2.059 | B103: Removal of the existing Prefab structures and hand over to Client store | C103: Lump Sum | D103: 1 | E103: 16730.9 | F103: =$D103*E103 -> 16730.9
A104: 2.06 | B104: Removal of existing Tanker Filling Bays and handover to Client store | C104: Lump Sum | D104: 1 | E104: 20077.08 | F104: =$D104*E104 -> 20077.08
...

Sheet SWEIHAN-Bill 03
B5: Bill No.3, Electrical Works
A6: Sl.No | B6: Description | C6: UNIT | D6: Quantity (Q) | E6: Unit Rate AED (A) | F6: Total Line Costs Ecxluding VAT B= AED (Q X A)
B7: Electrical
B8: LV Cable
A9: 3.001 | B9: Supply of LV Cables as per drawings and specifications | C9: Lump Sum | D9: 1 | E9: 41641.536 | F9: =D9*E9 -> 41641.536
A10: 3.002 | B10: Installation of LV Cables as per drawings and specifications | C10: Lump Sum | D10: 1 | E10: 24984.922 | F10: =D10*E10 -> 24984.922
B11: CAT 6 Cables
A12: 3.003 | B12: Supply of CAT 6 Cables as per drawings and specifications | C12: Lump Sum | D12: 1 | E12: 2949.6576 | F12: =D12*E12 -> 2949.6576
A13: 3.004 | B13: Installation OF CAT 6 Cables as per drawings and specifications | C13: Lump Sum | D13: 1 | E13: 1769.7946 | F13: =D13*E13 -> 1769.7946
B14: Ultrasonic Level Detectors
A15: 3.005 | B15: Supply of ultrasonic level detectors | C15: Lump Sum | D15: 1 | E15: 20507.934 | F15: =D15*E15 -> 20507.934
A16: 3.006 | B16: Installtion of ultrasonic level detectors | C16: Lump Sum | D16: 1 | E16: 12304.76 | F16: =D16*E16 -> 12304.76
B17: Induction Loop Cables
A18: 3.007 | B18: Supply of Induction Loop cables | C18: Lump Sum | D18: 1 | E18: 8365.4498 | F18: =D18*E18 -> 8365.4498
A19: 3.008 | B19: Installtion of Induction Loop cables | C19: Lump Sum | D19: 1 | E19: 5019.2699 | F19: =D19*E19 -> 5019.2699
B20: FOC Cables | F20: =D20*E20 -> 0
A21: 3.009 | B21: Supply of FOC Cables as per drawings and specifications | C21: Lump Sum | D21: 1 | E21: 21331.897 | F21: =D21*E21 -> 21331.897
A22: 3.01 | B22: Installation OF FOC Cables as per drawings and specifications | C22: Lump Sum | D22: 1 | E22: 12799.138 | F22: =D22*E22 -> 12799.138
B23: uPVC Ducts
A24: 3.011 | B24: Supply of uPVC ducts including , end caps, draw ropes, aluminium duct marker, warning tapes, cable tiles etc;complete; as per drawings, specification and authority requirement | C24: Lump Sum | D24: 1 | E24: 27754.889 | F24: =D24*E24 -> 27754.889
A25: 3.012 | B25: Installation of uPVC ducts including excavation, shuttering, reinforcement, concrete encasement, back filling, reinstatement, end caps, draw ropes, aluminium duct marker, warning tapes, cable tiles etc;complete; as per drawings, specification and authority requirement | C25: Lump Sum | D25: 1 | E25: 16652.934 | F25: =D25*E25 -> 16652.934
B26: Road Crossing uPVC Ducts for LV, FOC & CAT Cables
A27: 3.013 | B27: Supply of uPVC ducts complete; as per drawings, specification and authority requirement | C27: Lump Sum | D27: 1 | E27: 20913.625 | F27: =D27*E27 -> 20913.625
A28: 3.014 | B28: Installation of uPVC ducts including excavation, shuttering, reinforcement, concrete encasement, back filling, reinstatement, end caps, draw ropes, aluminium duct marker, warning tapes, cable tiles etc;complete; as per drawings, specification and authority requirement | C28: Lump Sum | D28: 1 | E28: 12548.175 | F28: =D28*E28 -> 12548.175
B29: Manholes
A30: 3.015 | B30: Manholes including excavation, backfilling, concrete works, blinding and screeds connection joints and protection coating to all internal concrete surfaces, waterproofing, cover & frame, complete in all respect as detailed on drawing and as per specification | C30: Lump Sum | D30: 1 | E30: 110226.51 | F30: =D30*E30 -> 110226.51
B31: Main Distribution Board (MDB)
A32: 3.016 | B32: Supply, Main Distribution Board(MDB) complete including enclosure, bus bars, circuit breakers, and insulators, complete all as specified and as shown on drawings. | C32: Lump Sum | D32: 1 | E32: 467481.02 | F32: =D32*E32 -> 467481.02
A33: 3.017 | B33: Installed, connected, and tested, complete including enclosure, bus bars, circuit breakers, and insulators,complete all as specified and as shown on drawings. | C33: Lump Sum | D33: 1 | E33: 24604.264 | F33: =D33*E33 -> 24604.264
B34: Distribution Board(DB)
A35: 3.018 | B35: Supply, Distribution board complete including enclosure, bus bars, circuit breakers, and insulators, complete all as specified and as shown on drawings. | C35: Lump Sum | D35: 1 | E35: 14762.559 | F35: =D35*E35 -> 14762.559
A36: 3.019 | B36: Install, Distribution board connected, and tested, complete including enclosure, bus bars, circuit breakers, and insulators,complete all as specified and as shown on drawings. | C36: Lump Sum | D36: 1 | E36: 4173.021 | F36: =D36*E36 -> 4173.021
B37: Single Pole and Neutral (SPN) Isolator 20A
A38: 3.02 | B38: Supply, Single Pole and Neutral (SPN) Isolator 20A complete all as specified and as shown on drawings. | C38: Lump Sum | D38: 1 | E38: 2509.635 | F38: =D38*E38 -> 2509.635
A39: 3.021 | B39: Install, connected, and tested, Single Pole and Neutral (SPN) Isolator 20A complete all as specified and as shown on drawings. | C39: Lump Sum | D39: 1 | E39: 1505.781 | F39: =D39*E39 -> 1505.781
B40: Capacitor Bank 35 KVAR
A41: 3.022 | B41: Supply, Capacitor Bank 35 KVAR complete all as specified and as shown on drawings. | C41: Lump Sum | D41: 1 | E41: 14762.559 | F41: =D41*E41 -> 14762.559
A42: 3.023 | B42: Install, connected, and tested, Capacitor Bank 35 KVAR complete all as specified and as shown on drawings. | C42: Lump Sum | D42: 1 | E42: 9841.7057 | F42: =D42*E42 -> 9841.7057
B43: Electrical Meter IP55 Metal Case Meter Enclosure Recessed on wall
A44: 3.024 | B44: Supply, Electrical Meter 83A IP55 Metal Case Meter Enclosure Recessed on wall complete all as specified and as shown on drawings. | C44: Lump Sum | D44: 1 | E44: 4920.8528 | F44: =D44*E44 -> 4920.8528
A45: 3.025 | B45: Install, connected, and tested, Electrical Meter 83A IP55 Metal Case Meter Enclosure Recessed on wall complete all as specified and as shown on drawings. | C45: Lump Sum | D45: 1 | E45: 1279.9138 | F45: =D45*E45 -> 1279.9138
B46: LED SCREEN including Foundation
A47: 3.026 | B47: Supply, LED SCREEN complete all as specified and as shown on drawings. | C47: Lump Sum | D47: 1 | E47: 2133.1897 | F47: =D47*E47 -> 2133.1897
A48: 3.027 | B48: Install, connected, and tested, LED SCREEN complete all as specified and as shown on drawings. | C48: Lump Sum | D48: 1 | E48: 1279.9138 | F48: =D48*E48 -> 1279.9138
B49: Telecommunication System
A50: 3.028 | B50: Supply UPVC ducts complete; as per drawings, specification and authority requirement | C50: Lump Sum | D50: 1 | E50: 3828.0298 | F50: =D50*E50 -> 3828.0298
A51: 3.029 | B51: Installation of upvc ducts including excavation, back filling, reinstatement, end caps, draw ropes, aluminium duct marker, warning tapes etc;complete; as per drawings, specification and authority requirement | C51: Lump Sum | D51: 1 | E51: 2296.8179 | F51: =D51*E51 -> 2296.8179
B52: Manholes / Joint Boxes
A53: 3.03 | B53: Construct Reinforced concrete Manholes complete including excavation, filling, Manhole concrete, formwork, water proofing, cover & frame etc. in accordance with drawings, specifications and authority requirements. | C53: Lump Sum | D53: 1 | E53: 81966.351 | F53: =D53*E53 -> 81966.351
B54: Telecom Box
A55: 3.031 | B55: Supply, Telecom Box complete all as specified and as shown on drawings. | C55: Lump Sum | D55: 1 | E55: 43488.628 | F55: =D55*E55 -> 43488.628
A56: 3.032 | B56: Install, connected, and tested, Telecom Box including Foundation complete all as specified and as shown on drawings. | C56: Lump Sum | D56: 1 | E56: 26093.177 | F56: =D56*E56 -> 26093.177
B57: Main Distribution Frame (MDF)
A58: 3.033 | B58: Supply, Main Distribution Frame (MDF) complete all as specified and as shown on drawings. | C58: Lump Sum | D58: 1 | E58: 37644.524 | F58: =D58*E58 -> 37644.524
A59: 3.034 | B59: Install, connected, and tested, Main Distribution Frame (MDF) including Foundation complete all as specified and as shown on drawings. | C59: Lump Sum | D59: 1 | E59: 22586.715 | F59: =D59*E59 -> 22586.715
B60: ANPR Camera ( Part of Tanker Management System) ( Mounted Height 3M )
A61: 3.035 | B61: Supply, ANPR Camera ( Part of Tanker Management System) ( Mounted Height 3M ) complete all as specified and as shown on drawings. | C61: Lump Sum | D61: 1 | E61: 30078.811 | F61: =D61*E61 -> 30078.811
A62: 3.036 | B62: Install, ANPR Camera ( Part of Tanker Management System) ( Mounted Height 3M ) complete all as specified and as shown on drawings. | C62: Lump Sum | D62: 1 | E62: 18047.287 | F62: =D62*E62 -> 18047.287
B63: ANPR Camera Pole 3M Height
A64: 3.037 | B64: Supply, Camera Pole 3M Height complete all as specified and as shown on drawings. | C64: Lump Sum | D64: 1 | E64: 2927.9074 | F64: =D64*E64 -> 2927.9074
A65: 3.038 | B65: Install, Camera Pole 3M Height including Foundation complete all as specified and as shown on drawings. | C65: Lump Sum | D65: 1 | E65: 1756.7445 | F65: =D65*E65 -> 1756.7445
B66: Road Crossing uPVC Ducts for Telecommunication Network
A67: 3.039 | B67: Supply of uPVC ducts complete; as per drawings, specification and authority requirement | C67: Lump Sum | D67: 1 | E67: 24741.654 | F67: =D67*E67 -> 24741.654
A68: 3.04 | B68: Installation of uPVC ducts including excavation, shuttering, reinforcement, concrete encasement, back filling, reinstatement, end caps, draw ropes, aluminium duct marker, warning tapes, cable tiles etc;complete; as per drawings, specification and authority requirement | C68: Lump Sum | D68: 1 | E68: 14844.993 | F68: =D68*E68 -> 14844.993
B69: Area Lighting
A70: 3.041 | B70: Supply, Flood Light complete all as specified and as shown on drawings. | C70: Lump Sum | D70: 1 | E70: 23004.987 | F70: =D70*E70 -> 23004.987
A71: 3.042 | B71: Install, connect, test Flood Light including complete all as specified and as shown on drawings. | C71: Lump Sum | D71: 1 | E71: 13802.992 | F71: =D71*E71 -> 13802.992
A72: 3.043 | B72: Supply, Landscape Lighting Pull Box complete all as specified and as shown on drawings. | C72: Lump Sum | D72: 1 | E72: 8365.4498 | F72: =D72*E72 -> 8365.4498
A73: 3.044 | B73: Install, connected, and tested, Landscape Lighting Pull Box complete all as specified and as shown on drawings. | C73: Lump Sum | D73: 1 | E73: 5019.2699 | F73: =D73*E73 -> 5019.2699
A74: 3.045 | B74: Supply, Lighting Pole of height 14M including luminaries complete all as specified and as shown on drawings. | C74: Lump Sum | D74: 1 | E74: 60231.239 | F74: =D74*E74 -> 60231.239
A75: 3.046 | B75: Install, connect and test Lighting Pole Height 14M including luminaries complete all as specified and as shown on drawings. | C75: Lump Sum | D75: 1 | E75: 36138.743 | F75: =D75*E75 -> 36138.743
B76: Distribution Board (Area Lighting)
A77: 3.047 | B77: Supply,DB complete all as specified and as shown on drawings. | C77: Lump Sum | D77: 1 | E77: 2857.6377 | F77: =D77*E77 -> 2857.6377
A78: 3.048 | B78: Installed, connected, and tested, DB complete including enclosure, bus bars, circuit breakers, and insulators, etc... complete all as specified and as shown on drawings. | C78: Lump Sum | D78: 1 | E78: 1714.5826 | F78: =D78*E78 -> 1714.5826
B79: Road Crossing for Area lighting Cables
A80: 3.049 | B80: Supply UPVC ducts complete; as per drawings, specification and authority requirement | C80: Lump Sum | D80: 1 | E80: 7172.5367 | F80: =D80*E80 -> 7172.5367
A81: 3.05 | B81: Installation of uPVC ducts including excavation, shuttering, reinforcement, concrete encasement, back filling, reinstatement, end caps, draw ropes, aluminium duct marker, warning tapes, cable tiles etc;complete; as per drawings, specification and authority requirement | C81: Lump Sum | D81: 1 | E81: 4303.522 | F81: =D81*E81 -> 4303.522
B82: Earthing
A83: 3.051 | B83: Supply Earthing to Control Cabinet and poles including earth electrodes, earth pits and earthing cable from LCC or light pole to earth pit, complete as shown on drawing and as per specification | C83: Lump Sum | D83: 1 | E83: 21382.09 | F83: =D83*E83 -> 21382.09
A84: 3.052 | B84: Install Earthing to Control Cabinet and poles including earth electrodes, earth pits and earthing cable from LCC or light pole to earth pit, complete as shown on drawing and as per specification | C84: Lump Sum | D84: 1 | E84: 12829.254 | F84: =D84*E84 -> 12829.254
B85: Buildings
A86: 3.053 | B86: MEP works for building includes Power, lighting, fire alarm, fire extinguishers, Emrgency Lighting, Earthing, HVAC & Drainage system; complete all as specified, as shown on the drawings and as per Engineer's approval. | C86: Lump Sum | D86: 1 | E86: 246042.64 | F86: =D86*E86 -> 246042.64
B87: EVSDS
A88: 3.054 | B88: Supply LV EVSDS as per specification and Single Line Diagram approved by TAQA/TAQA complete with frequency converters, harmonic suppression equipment, etc. including witnessed factory tests all according to the TAQA/TAQA specifications, data sheets and drawings. | C88: No. | D88: 2 | E88: 118100.47 | F88: =D88*E88 -> 236200.94
A89: 3.055 | B89: Install LV EVSDS as per specification and Single Line Diagram approved by TAQA/TAQA complete with frequency converters, harmonic suppression equipment, etc. all according to the TAQA/TAQA specifications, data sheets and drawings. | C89: No. | D89: 2 | E89: 54208.115 | F89: =D89*E89 -> 108416.23
B90: LV DISTRIBUTION BOARD
A91: 3.056 | B91: Supply suitably rated distribution boards and sub-distribution boards as per approved single line diagram and specification with all accessories for the power supply to all the electrical and instrumentation loads in pump station as per TAQA/TAQA specification. | C91: Lump Sum | D91: 1 | E91: 24604.264 | F91: =D91*E91 -> 24604.264
A92: 3.057 | B92: Install suitably rated distribution boards and sub-distribution boards as per approved single line diagram and specification with all accessories for the power supply to all the electrical and instrumentation loads in pump station as per TAQA/TAQA specification. | C92: Lump Sum | D92: 1 | E92: 9841.7057 | F92: =D92*E92 -> 9841.7057
B93: LV SWITCHGEAR/MCC
A94: 3.058 | B94: Supply Low Voltage Switchboard/MCC including MCCBs, VFD, lighting distribution section, power factor correction equipment etc. complete with protection devices to feed all the electrical and instrument loads in the pump room and all the electrical loads connected to the LV Switchboard/MCC all according to the specifications, data sheet and drawings approved by TAQA Distribution. | C94: Lump Sum | D94: 1 | E94: 73812.793 | F94: =D94*E94 -> 73812.793
A95: 3.059 | B95: Install, testing, and commissioning of the Low Voltage Switchboard/MCC, including mounting in its designated location, alignment, cable termination for all incoming and outgoing feeders (power and control), interconnection with field equipment, functional testing, and commissioning. | C95: Lump Sum | D95: 1 | E95: 9841.7057 | F95: =D95*E95 -> 9841.7057
B96: LOCAL CONTROL PANELS
A97: 3.06 | B97: Supply of Local control panel for all the main pumpsets with overriding capability to the PS control system to operate the pump station in local remote including distributed I/O station for the main pump sets all according to the specifications, drawings and operation & control philosophy: | C97: No | D97: 1 | E97: 22511.426 | F97: =D97*E97 -> 22511.426
A98: 3.061 | B98: Installation, testing, and commissioning of the Local Control Panel (LCP) and Distributed I/O station for main pump sets, including mounting, alignment, cable termination (power, signal, and communication), integration with field instruments and the main control system, and validation of local/remote control functionality. | C98: No | D98: 1 | E98: 13506.855 | F98: =D98*E98 -> 13506.855
B99: FIELD INSTRUMENTS FOR PUMPSTATION, DISCHARGE PIPING AND SURGE VESSEL
A100: 3.062 | B100: Supply of field mounted pressure, temperature, speed, level and flow instruments complete with impulse lines, isolation valves, block and bleed valves, accessories, mounting racks, sun protection, enclosure boxes, JB, prefab cables etc. all according to specifications, finalized P&IDs, drawings and the operation and control philosophy. | C100: Lump Sum | D100: 1 | E100: 53120.606 | F100: =D100*E100 -> 53120.606
A101: 3.063 | B101: Install, testing, and commissioning of field-mounted pressure, temperature, speed, level, and flow instruments, complete with associated impulse lines, isolation valves, block and bleed valves, mounting racks, sun protection covers, instrument enclosure boxes, JB, prefabricated signal cables, and all necessary accessories. | C101: Lump Sum | D101: 1 | E101: 31872.364 | F101: =D101*E101 -> 31872.364
B102: COMMUNICATION SYSTEMS
B103: Communication equipment all according to the specifications and drawings, comprising but not limited to the following :
A104: 3.064 | B104: Supply of ETISALAT telephone system, including the EPABX alongwith the required number of extension at different location in the Pump Station including telephone sets and the provision for intercom, all as required. | C104: Lump Sum | D104: 1 | E104: 14639.537 | F104: =D104*E104 -> 14639.537
...

Sheet SWEIHAN-Bill 04
B5: Bill No.4, CONSTRUCTION OF PIPELINES
A6: Sl.No | B6: Description | C6: UNIT | D6: Quantity (Q) | E6: Unit Rate AED (A) | F6: Total Line Costs Ecxluding VAT B= AED (Q X A)
B7: A- Construction of uPVC Pipeline
B8: Construct Upvc pipeline as specified complete include installation of detectable warning tapes and other accessories as per specification. Rates shall include all costs for commissioning and handing over in full commercial operation. For the following pipelines
B9: Upvc pipe line
A10: 4.001 | B10: Upvc pipe line for Storm Water Works | C10: Lump Sum | D10: 1 | E10: 1748.6467 | F10: =$D10*E10 -> 1748.6467
A11: 4.002 | B11: Upvc pipe line for Sewer Works | C11: Lump Sum | D11: 1 | E11: 734.89473 | F11: =$D11*E11 -> 734.89473
B12: DI Pipelines
B13: Construct the Ductile Iron (D.I) pipeline as per the approved specifications, including tie-in connection with the existing line using polyethylene sleeves and rubber gaskets, installation of detectable warning tapes, and all necessary accessories. The scope includes supply of all materials, labor, equipment, and consumables required for the complete installation, as well as testing for pressure and leakage, flushing, disinfection, commissioning, and handing over the system in full commercial operation. The quoted rates shall cover all associated costs to deliver a fully functional and operational pipeline in compliance with relevant standards and project requirements.
A14: 4.003 | B14: DI Pipelines | C14: Lump Sum | D14: 1 | E14: 57547.382 | F14: =$D14*E14 -> 57547.382
B15: Construction of PPR Pipeline
B16: Construct PPR pipeline using butt fusion method as specified complete include installation of detectable warning tapes and other accessories as per specification. Rates shall include all costs for testing, flushing, disinfection, commissioning and handing over in full commercial operation.
A17: 4.004 | B17: PPR pipe line | C17: Lump Sum | D17: 1 | E17: 1004.2288 | F17: =$D17*E17 -> 1004.2288
B18: Construction of HDPE Pipeline
B19: Construct the HDPE pipeline using the butt fusion method as per the approved specifications, complete with tie-in connections, installation of detectable warning tapes, and all necessary accessories. The scope shall include supply of all materials, equipment, and labor required for the complete installation. Rates shall cover all associated costs for testing, flushing, disinfection, commissioning, and handing over the system in full commercial operation, in compliance with project and industry standards.
A20: 4.005 | B20: HDPE pipeline | C20: Lump Sum | D20: 1 | E20: 12046.248 | F20: =$D20*E20 -> 12046.248
B21: Exta over item For pipeline construction items for installation of D.I, PPR, HDPE & uPVC fittings complete (such as restrained couplings, bends, tees, reducers, reducing flanges, Lange spigot pieces, flange socket pieces, quick dismantling joints, flanged adaptors, socket connectors, tied dismantling joints, blank flanges, double flanged extension pieces, adjustable S bends, duck foot elbows, flanged pipe pieces with anchor flange, transition pieces, collars, stepped couplings, and caps, restraining glands, etc.) for the following pipes:
B22: uPVC Fittings
A23: 4.006 | B23: uPVC pipe line for Storm Water Works | C23: Lump Sum | D23: 1 | E23: 2470.237 | F23: =$D23*E23 -> 2470.237
A24: 4.007 | B24: uPVC pipe line for Sewerage Works | C24: Lump Sum | D24: 1 | E24: 1069.1982 | F24: =$D24*E24 -> 1069.1982
B25: DI Pipelines
A26: 4.008 | B26: DI Pipelines | C26: Lump Sum | D26: 1 | E26: 56354.863 | F26: =$D26*E26 -> 56354.863
B27: PPR Pipelines
A28: 4.009 | B28: PPR Pipelines | C28: Lump Sum | D28: 1 | E28: 2394.6803 | F28: =$D28*E28 -> 2394.6803
B29: HDPE pipeline
A30: 4.01 | B30: HDPE pipeline | C30: Lump Sum | D30: 1 | E30: 12046.248 | F30: =$D30*E30 -> 12046.248
B31: Exta over item pipeline construction for installation of flanged valves, gate valves, flowmeters, control valves, etc. including all the accessories as per the specification.
A32: 4.011 | B32: Flow Meter Validation Unit | C32: Lump Sum | D32: 1 | E32: 37477.215 | F32: =$D32*E32 -> 37477.215
A33: 4.012 | B33: Settlement Type Electromagnetic Flow Meter | C33: Lump Sum | D33: 1 | E33: 34369.886 | F33: =$D33*E33 -> 34369.886
A34: 4.013 | B34: Control Valve | C34: Lump Sum | D34: 1 | E34: 26627.735 | F34: =$D34*E34 -> 26627.735
A35: 4.014 | B35: Check Valve | C35: Lump Sum | D35: 1 | E35: 4389.9672 | F35: =$D35*E35 -> 4389.9672
A36: 4.015 | B36: Manual Butterfly Valve | C36: Lump Sum | D36: 1 | E36: 3724.5459 | F36: =$D36*E36 -> 3724.5459
A37: 4.016 | B37: Manual Check Valve | C37: Lump Sum | D37: 1 | E37: 5512.0752 | F37: =$D37*E37 -> 5512.0752
